Workbook

Sheet まとめ
A1: KOKUSAI ELECTRIC（6525）：貿易統計による27/3期2Q売上のナウキャスト
A2: 単位：億円。数値はすべて他シートへのリンク（緑字）。作成日 2026-09-28、貿易統計は2026年8月分速報まで。
A4: 項目 | D4: 値
A5: 構造モデル k=0（基準） | D5: =ナウキャスト!G22 -> 845.54497
A6: 構造モデル k=0（低〜高） | D6: =TEXT(ナウキャスト!G21,"#,##0")&"〜"&TEXT(ナウキャスト!G23,"#,##0") -> 806〜868
A7: 構造モデル k=1（6-8月実績のみ） | D7: =ナウキャスト!G27 -> 792.45118
A8: 単一モデル k=0（基準）／k=1 | D8: =TEXT(ナウキャスト!J22,"#,##0")&"／"&TEXT(ナウキャスト!J27,"#,##0") -> 812／735
A9: 予測誤差の目安（構造 k=0 のLOOCV RMSE） | D9: =回帰!$F$23 -> 76.331108
A10: 会社計画が示す2Q売上 | D10: =ナウキャスト!D32 -> 856
A11: 計画達成に必要な9月輸出の前年比（7-8月は約＋40％） | D11: =ナウキャスト!D44 -> 0.50484762
A12: 計画が示す実質シェア（過去の最大値） | D12: =TEXT(ナウキャスト!D34,"0.0%")&"（"&TEXT(ナウキャスト!F35,"0.0%")&"）" -> 5.9%（6.1%）
A14: モデル精度（12四半期、leave-one-out）
A15: モデル | C15: R² | D15: LOOCV RMSE
A16: 単一 k=0 | C16: =回帰!$E$20 -> 0.46196353 | D16: =回帰!$F$20 -> 71.189384
A17: 構造 k=0 | C17: =回帰!$E$23 -> 0.46176286 | D17: =回帰!$F$23 -> 76.331108
A18: 単一 k=1 | C18: =回帰!$E$43 -> 0.44325558 | D18: =回帰!$F$43 -> 74.538144
A19: 構造 k=1 | C19: =回帰!$E$46 -> 0.42983211 | D19: =回帰!$F$46 -> 77.617814
A20: ランダムウォーク | D20: =回帰!$F$24 -> 112.62811
A21: うちグローバル売上×中国以外（k=0） | C21: =回帰!$E$22 -> 0.79792948
A23: 所見
A24: ・7-8月の輸出（前年比＋40％）を売上に換算すると、2Qは構造モデルで約790〜870億円（基準846億円）、単一モデルで約740〜830億円であり、計画856億円と同水準かやや下である。
A25: ・計画達成には、9月の輸出が前年比＋50％程度まで加速するか、KOKUSAIのシェアが過去最高圏に留まる必要がある。
A26: ・差は予測誤差（±70〜80億円）の範囲内であり、方向感の確認に留まる。9月速報（10/21）で再計算すれば決算前に精度が上がる。
A27: ・グローバル売上と中国以外向け輸出はR²0.8と強く連動する。一方、中国地場売上と対中輸出の連動は弱く、全社の精度を押し下げている。
A28: ・富山（伏木税関支署管内）の半導体等製造装置輸出は年23億円規模に過ぎず、税関別データから工場を特定する方法はKOKUSAIでは機能しなかった。

Sheet 速報_原データ
A1: 財務省 貿易統計 月次速報：概況品「半導体等製造装置」の地域別輸出（原データ）
A2: 青字＝各月の速報PDFから転記した値。価額は百万円、前年同月比は％（例：40.1＝＋40.1％）。
A4: 月 | B4: 地域 | C4: 価額（百万円） | D4: 前年同月比（％） | E4: 数量（トン） | F4: 数量前年比（％） | G4: 出所PDF | I4: 2024年5月の前年同月比（概要PDFより）
A5: 45383 | B5: ASEAN | C5: 17542 | D5: 27.4 | E5: 545 | F5: -1.2 | G5: https://www.customs.go.jp/toukei/shinbun/trade-st/2024/2024044.pdf | I5: 月 | J5: 地域 | K5: 前年同月比（％）
A6: 45383 | B6: Asia | C6: 322037 | D6: 45.2 | E6: 11129 | F6: 43.8 | G6: https://www.customs.go.jp/toukei/shinbun/trade-st/2024/2024044.pdf | I6: 45413 | J6: World | K6: 45.9
A7: 45383 | B7: China | C7: 188866 | D7: 95.4 | E7: 6494 | F7: 94.8 | G7: https://www.customs.go.jp/toukei/shinbun/trade-st/2024/2024044.pdf | I7: 45413 | J7: Asia | K7: 56.2
A8: 45383 | B8: EU | C8: 12280 | D8: -44.5 | E8: 395 | F8: -43.9 | G8: https://www.customs.go.jp/toukei/shinbun/trade-st/2024/2024044.pdf | I8: 45413 | J8: China | K8: 130.7
A9: 45383 | B9: Korea | C9: 45082 | D9: -0.4 | E9: 1611 | F9: 28.9 | G9: https://www.customs.go.jp/toukei/shinbun/trade-st/2024/2024044.pdf | I9: 45413 | J9: US | K9: 137.8
A10: 45383 | B10: US | C10: 42838 | D10: -16.3 | E10: 1188 | F10: -24.7 | G10: https://www.customs.go.jp/toukei/shinbun/trade-st/2024/2024044.pdf | I10: 出所: https://www.customs.go.jp/toukei/shinbun/trade-st/gaiyo2024_05.pdf
A11: 45383 | B11: World | C11: 379038 | D11: 28.2 | E11: 12780 | F11: 27.3 | G11: https://www.customs.go.jp/toukei/shinbun/trade-st/2024/2024044.pdf
A12: 45444 | B12: ASEAN | C12: 16156 | D12: 13.8 | E12: 426 | F12: -30 | G12: https://www.customs.go.jp/toukei/shinbun/trade-st/2024/2024064.pdf
A13: 45444 | B13: Asia | C13: 338211 | D13: 42.9 | E13: 11035 | F13: 28.5 | G13: https://www.customs.go.jp/toukei/shinbun/trade-st/2024/2024064.pdf
A14: 45444 | B14: China | C14: 192584 | D14: 47.7 | E14: 6249 | F14: 30.5 | G14: https://www.customs.go.jp/toukei/shinbun/trade-st/2024/2024064.pdf
A15: 45444 | B15: EU | C15: 10419 | D15: -48.7 | E15: 280 | F15: -49.7 | G15: https://www.customs.go.jp/toukei/shinbun/trade-st/2024/2024064.pdf
A16: 45444 | B16: Korea | C16: 54349 | D16: 7.6 | E16: 1963 | F16: 42.6 | G16: https://www.customs.go.jp/toukei/shinbun/trade-st/2024/2024064.pdf
A17: 45444 | B17: US | C17: 47981 | D17: 58.4 | E17: 1018 | F17: 18.2 | G17: https://www.customs.go.jp/toukei/shinbun/trade-st/2024/2024064.pdf
A18: 45444 | B18: World | C18: 397166 | D18: 37.9 | E18: 12343 | F18: 23 | G18: https://www.customs.go.jp/toukei/shinbun/trade-st/2024/2024064.pdf
A19: 45474 | B19: ASEAN | C19: 19766 | D19: 35.4 | E19: 564 | F19: -14.4 | G19: https://www.customs.go.jp/toukei/shinbun/trade-st/2024/2024074.pdf
A20: 45474 | B20: Asia | C20: 314213 | D20: 32.6 | E20: 9989 | F20: -2.3 | G20: https://www.customs.go.jp/toukei/shinbun/trade-st/2024/2024074.pdf
A21: 45474 | B21: China | C21: 163858 | D21: 16.6 | E21: 5287 | F21: -19.1 | G21: https://www.customs.go.jp/toukei/shinbun/trade-st/2024/2024074.pdf
A22: 45474 | B22: EU | C22: 8783 | D22: -49.1 | E22: 261 | F22: -56.9 | G22: https://www.customs.go.jp/toukei/shinbun/trade-st/2024/2024074.pdf
... A200: 46235 | B200: World | C200: 489764 | D200: 40.1 | E200: 15572 | F200: 43.1 | G200: https://www.customs.go.jp/toukei/shinbun/trade-st/2026/2026084.pdf

Sheet 貿易_月次
A1: 半導体等製造装置の輸出（億円）— 月次パネル
A2: 当月の速報値を優先。無い月は翌年同月の速報値÷(1＋前年同月比)で逆算。2023年5月は2段逆算、韓国・ASEAN・EUの同月は前後月の平均で補間。
B3: World | C3: Asia | D3: China | E3: Korea | F3: US | G3: EU | H3: ASEAN
A4: 月 | B4: 世界 | C4: アジア | D4: 中国 | E4: 韓国 | F4: 米国 | G4: EU | H4: ASEAN | I4: 中国以外 | J4: アジア残差（台湾等） | K4: 値の出所
A5: 45017 | B5: =IF(COUNTIFS(速報_原データ!$A$5:$A$200,$A5,速報_原データ!$B$5:$B$200,B$3)>0,SUMIFS(速報_原データ!$C$5:$C$200,速報_原データ!$A$5:$A$200,$A5,速報_原データ!$B$5:$B$200,B$3)/100,IF(COUNTIFS(速報_原データ!$A$5:$A$200,EDATE($A5,12),速報_原データ!$B$5:$B$200,B$3)>0,SUMIFS(速報_原データ!$C$5:$C$200,速報_原データ!$A$5:$A$200,EDATE($A5,12),速報_原データ!$B$5:$B$200,B$3)/100/(1+SUMIFS(速報_原データ!$D$5:$D$200,速報_原データ!$A$5:$A$200,EDATE($A5,12),速報_原データ!$B$5:$B$200,B$3)/100),IF(COUNTIFS(速報_原データ!$I$6:$I$9,EDATE($A5,12),速報_原データ!$J$6:$J$9,B$3)>0,B17/(1+SUMIFS(速報_原データ!$K$6:$K$9,速報_原データ!$I$6:$I$9,EDATE($A5,12),速報_原データ!$J$6:$J$9,B$3)/100),AVERAGE(B4,B6)))) -> 2956.6147 | C5: =IF(COUNTIFS(速報_原データ!$A$5:$A$200,$A5,速報_原データ!$B$5:$B$200,C$3)>0,SUMIFS(速報_原データ!$C$5:$C$200,速報_原データ!$A$5:$A$200,$A5,速報_原データ!$B$5:$B$200,C$3)/100,IF(COUNTIFS(速報_原データ!$A$5:$A$200,EDATE($A5,12),速報_原データ!$B$5:$B$200,C$3)>0,SUMIFS(速報_原データ!$C$5:$C$200,速報_原データ!$A$5:$A$200,EDATE($A5,12),速報_原データ!$B$5:$B$200,C$3)/100/(1+SUMIFS(速報_原データ!$D$5:$D$200,速報_原データ!$A$5:$A$200,EDATE($A5,12),速報_原データ!$B$5:$B$200,C$3)/100),IF(COUNTIFS(速報_原データ!$I$6:$I$9,EDATE($A5,12),速報_原データ!$J$6:$J$9,C$3)>0,C17/(1+SUMIFS(速報_原データ!$K$6:$K$9,速報_原データ!$I$6:$I$9,EDATE($A5,12),速報_原データ!$J$6:$J$9,C$3)/100),AVERAGE(C4,C6)))) -> 2217.8857 | D5: =IF(COUNTIFS(速報_原データ!$A$5:$A$200,$A5,速報_原データ!$B$5:$B$200,D$3)>0,SUMIFS(速報_原データ!$C$5:$C$200,速報_原データ!$A$5:$A$200,$A5,速報_原データ!$B$5:$B$200,D$3)/100,IF(COUNTIFS(速報_原データ!$A$5:$A$200,EDATE($A5,12),速報_原データ!$B$5:$B$200,D$3)>0,SUMIFS(速報_原データ!$C$5:$C$200,速報_原データ!$A$5:$A$200,EDATE($A5,12),速報_原データ!$B$5:$B$200,D$3)/100/(1+SUMIFS(速報_原データ!$D$5:$D$200,速報_原データ!$A$5:$A$200,EDATE($A5,12),速報_原データ!$B$5:$B$200,D$3)/100),IF(COUNTIFS(速報_原データ!$I$6:$I$9,EDATE($A5,12),速報_原データ!$J$6:$J$9,D$3)>0,D17/(1+SUMIFS(速報_原データ!$K$6:$K$9,速報_原データ!$I$6:$I$9,EDATE($A5,12),速報_原データ!$J$6:$J$9,D$3)/100),AVERAGE(D4,D6)))) -> 966.5609 | E5: =IF(COUNTIFS(速報_原データ!$A$5:$A$200,$A5,速報_原データ!$B$5:$B$200,E$3)>0,SUMIFS(速報_原データ!$C$5:$C$200,速報_原データ!$A$5:$A$200,$A5,速報_原データ!$B$5:$B$200,E$3)/100,IF(COUNTIFS(速報_原データ!$A$5:$A$200,EDATE($A5,12),速報_原データ!$B$5:$B$200,E$3)>0,SUMIFS(速報_原データ!$C$5:$C$200,速報_原データ!$A$5:$A$200,EDATE($A5,12),速報_原データ!$B$5:$B$200,E$3)/100/(1+SUMIFS(速報_原データ!$D$5:$D$200,速報_原データ!$A$5:$A$200,EDATE($A5,12),速報_原データ!$B$5:$B$200,E$3)/100),IF(COUNTIFS(速報_原データ!$I$6:$I$9,EDATE($A5,12),速報_原データ!$J$6:$J$9,E$3)>0,E17/(1+SUMIFS(速報_原データ!$K$6:$K$9,速報_原データ!$I$6:$I$9,EDATE($A5,12),速報_原データ!$J$6:$J$9,E$3)/100),AVERAGE(E4,E6)))) -> 452.63052 | F5: =IF(COUNTIFS(速報_原データ!$A$5:$A$200,$A5,速報_原データ!$B$5:$B$200,F$3)>0,SUMIFS(速報_原データ!$C$5:$C$200,速報_原データ!$A$5:$A$200,$A5,速報_原データ!$B$5:$B$200,F$3)/100,IF(COUNTIFS(速報_原データ!$A$5:$A$200,EDATE($A5,12),速報_原データ!$B$5:$B$200,F$3)>0,SUMIFS(速報_原データ!$C$5:$C$200,速報_原データ!$A$5:$A$200,EDATE($A5,12),速報_原データ!$B$5:$B$200,F$3)/100/(1+SUMIFS(速報_原データ!$D$5:$D$200,速報_原データ!$A$5:$A$200,EDATE($A5,12),速報_原データ!$B$5:$B$200,F$3)/100),IF(COUNTIFS(速報_原データ!$I$6:$I$9,EDATE($A5,12),速報_原データ!$J$6:$J$9,F$3)>0,F17/(1+SUMIFS(速報_原データ!$K$6:$K$9,速報_原データ!$I$6:$I$9,EDATE($A5,12),速報_原データ!$J$6:$J$9,F$3)/100),AVERAGE(F4,F6)))) -> 511.80406 | G5: =IF(COUNTIFS(速報_原データ!$A$5:$A$200,$A5,速報_原データ!$B$5:$B$200,G$3)>0,SUMIFS(速報_原データ!$C$5:$C$200,速報_原データ!$A$5:$A$200,$A5,速報_原データ!$B$5:$B$200,G$3)/100,IF(COUNTIFS(速報_原データ!$A$5:$A$200,EDATE($A5,12),速報_原データ!$B$5:$B$200,G$3)>0,SUMIFS(速報_原データ!$C$5:$C$200,速報_原データ!$A$5:$A$200,EDATE($A5,12),速報_原データ!$B$5:$B$200,G$3)/100/(1+SUMIFS(速報_原データ!$D$5:$D$200,速報_原データ!$A$5:$A$200,EDATE($A5,12),速報_原データ!$B$5:$B$200,G$3)/100),IF(COUNTIFS(速報_原データ!$I$6:$I$9,EDATE($A5,12),速報_原データ!$J$6:$J$9,G$3)>0,G17/(1+SUMIFS(速報_原データ!$K$6:$K$9,速報_原データ!$I$6:$I$9,EDATE($A5,12),速報_原データ!$J$6:$J$9,G$3)/100),AVERAGE(G4,G6)))) -> 221.26126 | H5: =IF(COUNTIFS(速報_原データ!$A$5:$A$200,$A5,速報_原データ!$B$5:$B$200,H$3)>0,SUMIFS(速報_原データ!$C$5:$C$200,速報_原データ!$A$5:$A$200,$A5,速報_原データ!$B$5:$B$200,H$3)/100,IF(COUNTIFS(速報_原データ!$A$5:$A$200,EDATE($A5,12),速報_原データ!$B$5:$B$200,H$3)>0,SUMIFS(速報_原データ!$C$5:$C$200,速報_原データ!$A$5:$A$200,EDATE($A5,12),速報_原データ!$B$5:$B$200,H$3)/100/(1+SUMIFS(速報_原データ!$D$5:$D$200,速報_原データ!$A$5:$A$200,EDATE($A5,12),速報_原データ!$B$5:$B$200,H$3)/100),IF(COUNTIFS(速報_原データ!$I$6:$I$9,EDATE($A5,12),速報_原データ!$J$6:$J$9,H$3)>0,H17/(1+SUMIFS(速報_原データ!$K$6:$K$9,速報_原データ!$I$6:$I$9,EDATE($A5,12),速報_原データ!$J$6:$J$9,H$3)/100),AVERAGE(H4,H6)))) -> 137.69231 | I5: =B5-D5 -> 1990.0538 | J5: =C5-D5-E5-H5 -> 661.00194 | K5: 翌年同月速報の前年比から逆算
A6: 45047 | B6: =IF(COUNTIFS(速報_原データ!$A$5:$A$200,$A6,速報_原データ!$B$5:$B$200,B$3)>0,SUMIFS(速報_原データ!$C$5:$C$200,速報_原データ!$A$5:$A$200,$A6,速報_原データ!$B$5:$B$200,B$3)/100,IF(COUNTIFS(速報_原データ!$A$5:$A$200,EDATE($A6,12),速報_原データ!$B$5:$B$200,B$3)>0,SUMIFS(速報_原データ!$C$5:$C$200,速報_原データ!$A$5:$A$200,EDATE($A6,12),速報_原データ!$B$5:$B$200,B$3)/100/(1+SUMIFS(速報_原データ!$D$5:$D$200,速報_原データ!$A$5:$A$200,EDATE($A6,12),速報_原データ!$B$5:$B$200,B$3)/100),IF(COUNTIFS(速報_原データ!$I$6:$I$9,EDATE($A6,12),速報_原データ!$J$6:$J$9,B$3)>0,B18/(1+SUMIFS(速報_原データ!$K$6:$K$9,速報_原データ!$I$6:$I$9,EDATE($A6,12),速報_原データ!$J$6:$J$9,B$3)/100),AVERAGE(B5,B7)))) -> 2348.2233 | C6: =IF(COUNTIFS(速報_原データ!$A$5:$A$200,$A6,速報_原データ!$B$5:$B$200,C$3)>0,SUMIFS(速報_原データ!$C$5:$C$200,速報_原データ!$A$5:$A$200,$A6,速報_原データ!$B$5:$B$200,C$3)/100,IF(COUNTIFS(速報_原データ!$A$5:$A$200,EDATE($A6,12),速報_原データ!$B$5:$B$200,C$3)>0,SUMIFS(速報_原データ!$C$5:$C$200,速報_原データ!$A$5:$A$200,EDATE($A6,12),速報_原データ!$B$5:$B$200,C$3)/100/(1+SUMIFS(速報_原データ!$D$5:$D$200,速報_原データ!$A$5:$A$200,EDATE($A6,12),速報_原データ!$B$5:$B$200,C$3)/100),IF(COUNTIFS(速報_原データ!$I$6:$I$9,EDATE($A6,12),速報_原データ!$J$6:$J$9,C$3)>0,C18/(1+SUMIFS(速報_原データ!$K$6:$K$9,速報_原データ!$I$6:$I$9,EDATE($A6,12),速報_原データ!$J$6:$J$9,C$3)/100),AVERAGE(C5,C7)))) -> 1897.3356 | D6: =IF(COUNTIFS(速報_原データ!$A$5:$A$200,$A6,速報_原データ!$B$5:$B$200,D$3)>0,SUMIFS(速報_原データ!$C$5:$C$200,速報_原データ!$A$5:$A$200,$A6,速報_原データ!$B$5:$B$200,D$3)/100,IF(COUNTIFS(速報_原データ!$A$5:$A$200,EDATE($A6,12),速報_原データ!$B$5:$B$200,D$3)>0,SUMIFS(速報_原データ!$C$5:$C$200,速報_原データ!$A$5:$A$200,EDATE($A6,12),速報_原データ!$B$5:$B$200,D$3)/100/(1+SUMIFS(速報_原データ!$D$5:$D$200,速報_原データ!$A$5:$A$200,EDATE($A6,12),速報_原データ!$B$5:$B$200,D$3)/100),IF(COUNTIFS(速報_原データ!$I$6:$I$9,EDATE($A6,12),速報_原データ!$J$6:$J$9,D$3)>0,D18/(1+SUMIFS(速報_原データ!$K$6:$K$9,速報_原データ!$I$6:$I$9,EDATE($A6,12),速報_原データ!$J$6:$J$9,D$3)/100),AVERAGE(D5,D7)))) -> 816.893 | E6: =IF(COUNTIFS(速報_原データ!$A$5:$A$200,$A6,速報_原データ!$B$5:$B$200,E$3)>0,SUMIFS(速報_原データ!$C$5:$C$200,速報_原データ!$A$5:$A$200,$A6,速報_原データ!$B$5:$B$200,E$3)/100,IF(COUNTIFS(速報_原データ!$A$5:$A$200,EDATE($A6,12),速報_原データ!$B$5:$B$200,E$3)>0,SUMIFS(速報_原データ!$C$5:$C$200,速報_原データ!$A$5:$A$200,EDATE($A6,12),速報_原データ!$B$5:$B$200,E$3)/100/(1+SUMIFS(速報_原データ!$D$5:$D$200,速報_原データ!$A$5:$A$200,EDATE($A6,12),速報_原データ!$B$5:$B$200,E$3)/100),IF(COUNTIFS(速報_原データ!$I$6:$I$9,EDATE($A6,12),速報_原データ!$J$6:$J$9,E$3)>0,E18/(1+SUMIFS(速報_原データ!$K$6:$K$9,速報_原データ!$I$6:$I$9,EDATE($A6,12),速報_原データ!$J$6:$J$9,E$3)/100),AVERAGE(E5,E7)))) -> 478.86638 | F6: =IF(COUNTIFS(速報_原データ!$A$5:$A$200,$A6,速報_原データ!$B$5:$B$200,F$3)>0,SUMIFS(速報_原データ!$C$5:$C$200,速報_原データ!$A$5:$A$200,$A6,速報_原データ!$B$5:$B$200,F$3)/100,IF(COUNTIFS(速報_原データ!$A$5:$A$200,EDATE($A6,12),速報_原データ!$B$5:$B$200,F$3)>0,SUMIFS(速報_原データ!$C$5:$C$200,速報_原データ!$A$5:$A$200,EDATE($A6,12),速報_原データ!$B$5:$B$200,F$3)/100/(1+SUMIFS(速報_原データ!$D$5:$D$200,速報_原データ!$A$5:$A$200,EDATE($A6,12),速報_原データ!$B$5:$B$200,F$3)/100),IF(COUNTIFS(速報_原データ!$I$6:$I$9,EDATE($A6,12),速報_原データ!$J$6:$J$9,F$3)>0,F18/(1+SUMIFS(速報_原データ!$K$6:$K$9,速報_原データ!$I$6:$I$9,EDATE($A6,12),速報_原データ!$J$6:$J$9,F$3)/100),AVERAGE(F5,F7)))) -> 165.80106 | G6: =IF(COUNTIFS(速報_原データ!$A$5:$A$200,$A6,速報_原データ!$B$5:$B$200,G$3)>0,SUMIFS(速報_原データ!$C$5:$C$200,速報_原データ!$A$5:$A$200,$A6,速報_原データ!$B$5:$B$200,G$3)/100,IF(COUNTIFS(速報_原データ!$A$5:$A$200,EDATE($A6,12),速報_原データ!$B$5:$B$200,G$3)>0,SUMIFS(速報_原データ!$C$5:$C$200,速報_原データ!$A$5:$A$200,EDATE($A6,12),速報_原データ!$B$5:$B$200,G$3)/100/(1+SUMIFS(速報_原データ!$D$5:$D$200,速報_原データ!$A$5:$A$200,EDATE($A6,12),速報_原データ!$B$5:$B$200,G$3)/100),IF(COUNTIFS(速報_原データ!$I$6:$I$9,EDATE($A6,12),速報_原データ!$J$6:$J$9,G$3)>0,G18/(1+SUMIFS(速報_原データ!$K$6:$K$9,速報_原データ!$I$6:$I$9,EDATE($A6,12),速報_原データ!$J$6:$J$9,G$3)/100),AVERAGE(G5,G7)))) -> 212.18034 | H6: =IF(COUNTIFS(速報_原データ!$A$5:$A$200,$A6,速報_原データ!$B$5:$B$200,H$3)>0,SUMIFS(速報_原データ!$C$5:$C$200,速報_原データ!$A$5:$A$200,$A6,速報_原データ!$B$5:$B$200,H$3)/100,IF(COUNTIFS(速報_原データ!$A$5:$A$200,EDATE($A6,12),速報_原データ!$B$5:$B$200,H$3)>0,SUMIFS(速報_原データ!$C$5:$C$200,速報_原データ!$A$5:$A$200,EDATE($A6,12),速報_原データ!$B$5:$B$200,H$3)/100/(1+SUMIFS(速報_原データ!$D$5:$D$200,速報_原データ!$A$5:$A$200,EDATE($A6,12),速報_原データ!$B$5:$B$200,H$3)/100),IF(COUNTIFS(速報_原データ!$I$6:$I$9,EDATE($A6,12),速報_原データ!$J$6:$J$9,H$3)>0,H18/(1+SUMIFS(速報_原データ!$K$6:$K$9,速報_原データ!$I$6:$I$9,EDATE($A6,12),速報_原データ!$J$6:$J$9,H$3)/100),AVERAGE(H5,H7)))) -> 139.83034 | I6: =B6-D6 -> 1531.3303 | J6: =C6-D6-E6-H6 -> 461.74586 | K6: 2段逆算（韓国・ASEAN・EUは補間）
A7: 45078 | B7: =IF(COUNTIFS(速報_原データ!$A$5:$A$200,$A7,速報_原データ!$B$5:$B$200,B$3)>0,SUMIFS(速報_原データ!$C$5:$C$200,速報_原データ!$A$5:$A$200,$A7,速報_原データ!$B$5:$B$200,B$3)/100,IF(COUNTIFS(速報_原データ!$A$5:$A$200,EDATE($A7,12),速報_原データ!$B$5:$B$200,B$3)>0,SUMIFS(速報_原データ!$C$5:$C$200,速報_原データ!$A$5:$A$200,EDATE($A7,12),速報_原データ!$B$5:$B$200,B$3)/100/(1+SUMIFS(速報_原データ!$D$5:$D$200,速報_原データ!$A$5:$A$200,EDATE($A7,12),速報_原データ!$B$5:$B$200,B$3)/100),IF(COUNTIFS(速報_原データ!$I$6:$I$9,EDATE($A7,12),速報_原データ!$J$6:$J$9,B$3)>0,B19/(1+SUMIFS(速報_原データ!$K$6:$K$9,速報_原データ!$I$6:$I$9,EDATE($A7,12),速報_原データ!$J$6:$J$9,B$3)/100),AVERAGE(B6,B8)))) -> 2880.1015 | C7: =IF(COUNTIFS(速報_原データ!$A$5:$A$200,$A7,速報_原データ!$B$5:$B$200,C$3)>0,SUMIFS(速報_原データ!$C$5:$C$200,速報_原データ!$A$5:$A$200,$A7,速報_原データ!$B$5:$B$200,C$3)/100,IF(COUNTIFS(速報_原データ!$A$5:$A$200,EDATE($A7,12),速報_原データ!$B$5:$B$200,C$3)>0,SUMIFS(速報_原データ!$C$5:$C$200,速報_原データ!$A$5:$A$200,EDATE($A7,12),速報_原データ!$B$5:$B$200,C$3)/100/(1+SUMIFS(速報_原データ!$D$5:$D$200,速報_原データ!$A$5:$A$200,EDATE($A7,12),速報_原データ!$B$5:$B$200,C$3)/100),IF(COUNTIFS(速報_原データ!$I$6:$I$9,EDATE($A7,12),速報_原データ!$J$6:$J$9,C$3)>0,C19/(1+SUMIFS(速報_原データ!$K$6:$K$9,速報_原データ!$I$6:$I$9,EDATE($A7,12),速報_原データ!$J$6:$J$9,C$3)/100),AVERAGE(C6,C8)))) -> 2366.767 | D7: =IF(COUNTIFS(速報_原データ!$A$5:$A$200,$A7,速報_原データ!$B$5:$B$200,D$3)>0,SUMIFS(速報_原データ!$C$5:$C$200,速報_原データ!$A$5:$A$200,$A7,速報_原データ!$B$5:$B$200,D$3)/100,IF(COUNTIFS(速報_原データ!$A$5:$A$200,EDATE($A7,12),速報_原データ!$B$5:$B$200,D$3)>0,SUMIFS(速報_原データ!$C$5:$C$200,速報_原データ!$A$5:$A$200,EDATE($A7,12),速報_原データ!$B$5:$B$200,D$3)/100/(1+SUMIFS(速報_原データ!$D$5:$D$200,速報_原データ!$A$5:$A$200,EDATE($A7,12),速報_原データ!$B$5:$B$200,D$3)/100),IF(COUNTIFS(速報_原データ!$I$6:$I$9,EDATE($A7,12),速報_原データ!$J$6:$J$9,D$3)>0,D19/(1+SUMIFS(速報_原データ!$K$6:$K$9,速報_原データ!$I$6:$I$9,EDATE($A7,12),速報_原データ!$J$6:$J$9,D$3)/100),AVERAGE(D6,D8)))) -> 1303.8863 | E7: =IF(COUNTIFS(速報_原データ!$A$5:$A$200,$A7,速報_原データ!$B$5:$B$200,E$3)>0,SUMIFS(速報_原データ!$C$5:$C$200,速報_原データ!$A$5:$A$200,$A7,速報_原データ!$B$5:$B$200,E$3)/100,IF(COUNTIFS(速報_原データ!$A$5:$A$200,EDATE($A7,12),速報_原データ!$B$5:$B$200,E$3)>0,SUMIFS(速報_原データ!$C$5:$C$200,速報_原データ!$A$5:$A$200,EDATE($A7,12),速報_原データ!$B$5:$B$200,E$3)/100/(1+SUMIFS(速報_原データ!$D$5:$D$200,速報_原データ!$A$5:$A$200,EDATE($A7,12),速報_原データ!$B$5:$B$200,E$3)/100),IF(COUNTIFS(速報_原データ!$I$6:$I$9,EDATE($A7,12),速報_原データ!$J$6:$J$9,E$3)>0,E19/(1+SUMIFS(速報_原データ!$K$6:$K$9,速報_原データ!$I$6:$I$9,EDATE($A7,12),速報_原データ!$J$6:$J$9,E$3)/100),AVERAGE(E6,E8)))) -> 505.10223 | F7: =IF(COUNTIFS(速報_原データ!$A$5:$A$200,$A7,速報_原データ!$B$5:$B$200,F$3)>0,SUMIFS(速報_原データ!$C$5:$C$200,速報_原データ!$A$5:$A$200,$A7,速報_原データ!$B$5:$B$200,F$3)/100,IF(COUNTIFS(速報_原データ!$A$5:$A$200,EDATE($A7,12),速報_原データ!$B$5:$B$200,F$3)>0,SUMIFS(速報_原データ!$C$5:$C$200,速報_原データ!$A$5:$A$200,EDATE($A7,12),速報_原データ!$B$5:$B$200,F$3)/100/(1+SUMIFS(速報_原データ!$D$5:$D$200,速報_原データ!$A$5:$A$200,EDATE($A7,12),速報_原データ!$B$5:$B$200,F$3)/100),IF(COUNTIFS(速報_原データ!$I$6:$I$9,EDATE($A7,12),速報_原データ!$J$6:$J$9,F$3)>0,F19/(1+SUMIFS(速報_原データ!$K$6:$K$9,速報_原データ!$I$6:$I$9,EDATE($A7,12),速報_原データ!$J$6:$J$9,F$3)/100),AVERAGE(F6,F8)))) -> 302.91035 | G7: =IF(COUNTIFS(速報_原データ!$A$5:$A$200,$A7,速報_原データ!$B$5:$B$200,G$3)>0,SUMIFS(速報_原データ!$C$5:$C$200,速報_原データ!$A$5:$A$200,$A7,速報_原データ!$B$5:$B$200,G$3)/100,IF(COUNTIFS(速報_原データ!$A$5:$A$200,EDATE($A7,12),速報_原データ!$B$5:$B$200,G$3)>0,SUMIFS(速報_原データ!$C$5:$C$200,速報_原データ!$A$5:$A$200,EDATE($A7,12),速報_原データ!$B$5:$B$200,G$3)/100/(1+SUMIFS(速報_原データ!$D$5:$D$200,速報_原データ!$A$5:$A$200,EDATE($A7,12),速報_原データ!$B$5:$B$200,G$3)/100),IF(COUNTIFS(速報_原データ!$I$6:$I$9,EDATE($A7,12),速報_原データ!$J$6:$J$9,G$3)>0,G19/(1+SUMIFS(速報_原データ!$K$6:$K$9,速報_原データ!$I$6:$I$9,EDATE($A7,12),速報_原データ!$J$6:$J$9,G$3)/100),AVERAGE(G6,G8)))) -> 203.09942 | H7: =IF(COUNTIFS(速報_原データ!$A$5:$A$200,$A7,速報_原データ!$B$5:$B$200,H$3)>0,SUMIFS(速報_原データ!$C$5:$C$200,速報_原データ!$A$5:$A$200,$A7,速報_原データ!$B$5:$B$200,H$3)/100,IF(COUNTIFS(速報_原データ!$A$5:$A$200,EDATE($A7,12),速報_原データ!$B$5:$B$200,H$3)>0,SUMIFS(速報_原データ!$C$5:$C$200,速報_原データ!$A$5:$A$200,EDATE($A7,12),速報_原データ!$B$5:$B$200,H$3)/100/(1+SUMIFS(速報_原データ!$D$5:$D$200,速報_原データ!$A$5:$A$200,EDATE($A7,12),速報_原データ!$B$5:$B$200,H$3)/100),IF(COUNTIFS(速報_原データ!$I$6:$I$9,EDATE($A7,12),速報_原データ!$J$6:$J$9,H$3)>0,H19/(1+SUMIFS(速報_原データ!$K$6:$K$9,速報_原データ!$I$6:$I$9,EDATE($A7,12),速報_原データ!$J$6:$J$9,H$3)/100),AVERAGE(H6,H8)))) -> 141.96837 | I7: =B7-D7 -> 1576.2153 | J7: =C7-D7-E7-H7 -> 415.81012 | K7: 翌年同月速報の前年比から逆算
A8: 45108 | B8: =IF(COUNTIFS(速報_原データ!$A$5:$A$200,$A8,速報_原データ!$B$5:$B$200,B$3)>0,SUMIFS(速報_原データ!$C$5:$C$200,速報_原データ!$A$5:$A$200,$A8,速報_原データ!$B$5:$B$200,B$3)/100,IF(COUNTIFS(速報_原データ!$A$5:$A$200,EDATE($A8,12),速報_原データ!$B$5:$B$200,B$3)>0,SUMIFS(速報_原データ!$C$5:$C$200,速報_原データ!$A$5:$A$200,EDATE($A8,12),速報_原データ!$B$5:$B$200,B$3)/100/(1+SUMIFS(速報_原データ!$D$5:$D$200,速報_原データ!$A$5:$A$200,EDATE($A8,12),速報_原データ!$B$5:$B$200,B$3)/100),IF(COUNTIFS(速報_原データ!$I$6:$I$9,EDATE($A8,12),速報_原データ!$J$6:$J$9,B$3)>0,B20/(1+SUMIFS(速報_原データ!$K$6:$K$9,速報_原データ!$I$6:$I$9,EDATE($A8,12),速報_原データ!$J$6:$J$9,B$3)/100),AVERAGE(B7,B9)))) -> 2883.7559 | C8: =IF(COUNTIFS(速報_原データ!$A$5:$A$200,$A8,速報_原データ!$B$5:$B$200,C$3)>0,SUMIFS(速報_原データ!$C$5:$C$200,速報_原データ!$A$5:$A$200,$A8,速報_原データ!$B$5:$B$200,C$3)/100,IF(COUNTIFS(速報_原データ!$A$5:$A$200,EDATE($A8,12),速報_原データ!$B$5:$B$200,C$3)>0,SUMIFS(速報_原データ!$C$5:$C$200,速報_原データ!$A$5:$A$200,EDATE($A8,12),速報_原データ!$B$5:$B$200,C$3)/100/(1+SUMIFS(速報_原データ!$D$5:$D$200,速報_原データ!$A$5:$A$200,EDATE($A8,12),速報_原データ!$B$5:$B$200,C$3)/100),IF(COUNTIFS(速報_原データ!$I$6:$I$9,EDATE($A8,12),速報_原データ!$J$6:$J$9,C$3)>0,C20/(1+SUMIFS(速報_原データ!$K$6:$K$9,速報_原データ!$I$6:$I$9,EDATE($A8,12),速報_原データ!$J$6:$J$9,C$3)/100),AVERAGE(C7,C9)))) -> 2369.6305 | D8: =IF(COUNTIFS(速報_原データ!$A$5:$A$200,$A8,速報_原データ!$B$5:$B$200,D$3)>0,SUMIFS(速報_原データ!$C$5:$C$200,速報_原データ!$A$5:$A$200,$A8,速報_原データ!$B$5:$B$200,D$3)/100,IF(COUNTIFS(速報_原データ!$A$5:$A$200,EDATE($A8,12),速報_原データ!$B$5:$B$200,D$3)>0,SUMIFS(速報_原データ!$C$5:$C$200,速報_原データ!$A$5:$A$200,EDATE($A8,12),速報_原データ!$B$5:$B$200,D$3)/100/(1+SUMIFS(速報_原データ!$D$5:$D$200,速報_原データ!$A$5:$A$200,EDATE($A8,12),速報_原データ!$B$5:$B$200,D$3)/100),IF(COUNTIFS(速報_原データ!$I$6:$I$9,EDATE($A8,12),速報_原データ!$J$6:$J$9,D$3)>0,D20/(1+SUMIFS(速報_原データ!$K$6:$K$9,速報_原データ!$I$6:$I$9,EDATE($A8,12),速報_原データ!$J$6:$J$9,D$3)/100),AVERAGE(D7,D9)))) -> 1405.3002 | E8: =IF(COUNTIFS(速報_原データ!$A$5:$A$200,$A8,速報_原データ!$B$5:$B$200,E$3)>0,SUMIFS(速報_原データ!$C$5:$C$200,速報_原データ!$A$5:$A$200,$A8,速報_原データ!$B$5:$B$200,E$3)/100,IF(COUNTIFS(速報_原データ!$A$5:$A$200,EDATE($A8,12),速報_原データ!$B$5:$B$200,E$3)>0,SUMIFS(速報_原データ!$C$5:$C$200,速報_原データ!$A$5:$A$200,EDATE($A8,12),速報_原データ!$B$5:$B$200,E$3)/100/(1+SUMIFS(速報_原データ!$D$5:$D$200,速報_原データ!$A$5:$A$200,EDATE($A8,12),速報_原データ!$B$5:$B$200,E$3)/100),IF(COUNTIFS(速報_原データ!$I$6:$I$9,EDATE($A8,12),速報_原データ!$J$6:$J$9,E$3)>0,E20/(1+SUMIFS(速報_原データ!$K$6:$K$9,速報_原データ!$I$6:$I$9,EDATE($A8,12),速報_原データ!$J$6:$J$9,E$3)/100),AVERAGE(E7,E9)))) -> 440.55938 | F8: =IF(COUNTIFS(速報_原データ!$A$5:$A$200,$A8,速報_原データ!$B$5:$B$200,F$3)>0,SUMIFS(速報_原データ!$C$5:$C$200,速報_原データ!$A$5:$A$200,$A8,速報_原データ!$B$5:$B$200,F$3)/100,IF(COUNTIFS(速報_原データ!$A$5:$A$200,EDATE($A8,12),速報_原データ!$B$5:$B$200,F$3)>0,SUMIFS(速報_原データ!$C$5:$C$200,速報_原データ!$A$5:$A$200,EDATE($A8,12),速報_原データ!$B$5:$B$200,F$3)/100/(1+SUMIFS(速報_原データ!$D$5:$D$200,速報_原データ!$A$5:$A$200,EDATE($A8,12),速報_原データ!$B$5:$B$200,F$3)/100),IF(COUNTIFS(速報_原データ!$I$6:$I$9,EDATE($A8,12),速報_原データ!$J$6:$J$9,F$3)>0,F20/(1+SUMIFS(速報_原データ!$K$6:$K$9,速報_原データ!$I$6:$I$9,EDATE($A8,12),速報_原データ!$J$6:$J$9,F$3)/100),AVERAGE(F7,F9)))) -> 336.11621 | G8: =IF(COUNTIFS(速報_原データ!$A$5:$A$200,$A8,速報_原データ!$B$5:$B$200,G$3)>0,SUMIFS(速報_原データ!$C$5:$C$200,速報_原データ!$A$5:$A$200,$A8,速報_原データ!$B$5:$B$200,G$3)/100,IF(COUNTIFS(速報_原データ!$A$5:$A$200,EDATE($A8,12),速報_原データ!$B$5:$B$200,G$3)>0,SUMIFS(速報_原データ!$C$5:$C$200,速報_原データ!$A$5:$A$200,EDATE($A8,12),速報_原データ!$B$5:$B$200,G$3)/100/(1+SUMIFS(速報_原データ!$D$5:$D$200,速報_原データ!$A$5:$A$200,EDATE($A8,12),速報_原データ!$B$5:$B$200,G$3)/100),IF(COUNTIFS(速報_原データ!$I$6:$I$9,EDATE($A8,12),速報_原データ!$J$6:$J$9,G$3)>0,G20/(1+SUMIFS(速報_原データ!$K$6:$K$9,速報_原データ!$I$6:$I$9,EDATE($A8,12),速報_原データ!$J$6:$J$9,G$3)/100),AVERAGE(G7,G9)))) -> 172.55403 | H8: =IF(COUNTIFS(速報_原データ!$A$5:$A$200,$A8,速報_原データ!$B$5:$B$200,H$3)>0,SUMIFS(速報_原データ!$C$5:$C$200,速報_原データ!$A$5:$A$200,$A8,速報_原データ!$B$5:$B$200,H$3)/100,IF(COUNTIFS(速報_原データ!$A$5:$A$200,EDATE($A8,12),速報_原データ!$B$5:$B$200,H$3)>0,SUMIFS(速報_原データ!$C$5:$C$200,速報_原データ!$A$5:$A$200,EDATE($A8,12),速報_原データ!$B$5:$B$200,H$3)/100/(1+SUMIFS(速報_原データ!$D$5:$D$200,速報_原データ!$A$5:$A$200,EDATE($A8,12),速報_原データ!$B$5:$B$200,H$3)/100),IF(COUNTIFS(速報_原データ!$I$6:$I$9,EDATE($A8,12),速報_原データ!$J$6:$J$9,H$3)>0,H20/(1+SUMIFS(速報_原データ!$K$6:$K$9,速報_原データ!$I$6:$I$9,EDATE($A8,12),速報_原データ!$J$6:$J$9,H$3)/100),AVERAGE(H7,H9)))) -> 145.98227 | I8: =B8-D8 -> 1478.4557 | J8: =C8-D8-E8-H8 -> 377.78864 | K8: 翌年同月速報の前年比から逆算
A9: 45139 | B9: =IF(COUNTIFS(速報_原データ!$A$5:$A$200,$A9,速報_原データ!$B$5:$B$200,B$3)>0,SUMIFS(速報_原データ!$C$5:$C$200,速報_原データ!$A$5:$A$200,$A9,速報_原データ!$B$5:$B$200,B$3)/100,IF(COUNTIFS(速報_原データ!$A$5:$A$200,EDATE($A9,12),速報_原データ!$B$5:$B$200,B$3)>0,SUMIFS(速報_原データ!$C$5:$C$200,速報_原データ!$A$5:$A$200,EDATE($A9,12),速報_原データ!$B$5:$B$200,B$3)/100/(1+SUMIFS(速報_原データ!$D$5:$D$200,速報_原データ!$A$5:$A$200,EDATE($A9,12),速報_原データ!$B$5:$B$200,B$3)/100),IF(COUNTIFS(速報_原データ!$I$6:$I$9,EDATE($A9,12),速報_原データ!$J$6:$J$9,B$3)>0,B21/(1+SUMIFS(速報_原データ!$K$6:$K$9,速報_原データ!$I$6:$I$9,EDATE($A9,12),速報_原データ!$J$6:$J$9,B$3)/100),AVERAGE(B8,B10)))) -> 2209.5619 | C9: =IF(COUNTIFS(速報_原データ!$A$5:$A$200,$A9,速報_原データ!$B$5:$B$200,C$3)>0,SUMIFS(速報_原データ!$C$5:$C$200,速報_原データ!$A$5:$A$200,$A9,速報_原データ!$B$5:$B$200,C$3)/100,IF(COUNTIFS(速報_原データ!$A$5:$A$200,EDATE($A9,12),速報_原データ!$B$5:$B$200,C$3)>0,SUMIFS(速報_原データ!$C$5:$C$200,速報_原データ!$A$5:$A$200,EDATE($A9,12),速報_原データ!$B$5:$B$200,C$3)/100/(1+SUMIFS(速報_原データ!$D$5:$D$200,速報_原データ!$A$5:$A$200,EDATE($A9,12),速報_原データ!$B$5:$B$200,C$3)/100),IF(COUNTIFS(速報_原データ!$I$6:$I$9,EDATE($A9,12),速報_原データ!$J$6:$J$9,C$3)>0,C21/(1+SUMIFS(速報_原データ!$K$6:$K$9,速報_原データ!$I$6:$I$9,EDATE($A9,12),速報_原データ!$J$6:$J$9,C$3)/100),AVERAGE(C8,C10)))) -> 1788.133 | D9: =IF(COUNTIFS(速報_原データ!$A$5:$A$200,$A9,速報_原データ!$B$5:$B$200,D$3)>0,SUMIFS(速報_原データ!$C$5:$C$200,速報_原データ!$A$5:$A$200,$A9,速報_原データ!$B$5:$B$200,D$3)/100,IF(COUNTIFS(速報_原データ!$A$5:$A$200,EDATE($A9,12),速報_原データ!$B$5:$B$200,D$3)>0,SUMIFS(速報_原データ!$C$5:$C$200,速報_原データ!$A$5:$A$200,EDATE($A9,12),速報_原データ!$B$5:$B$200,D$3)/100/(1+SUMIFS(速報_原データ!$D$5:$D$200,速報_原データ!$A$5:$A$200,EDATE($A9,12),速報_原データ!$B$5:$B$200,D$3)/100),IF(COUNTIFS(速報_原データ!$I$6:$I$9,EDATE($A9,12),速報_原データ!$J$6:$J$9,D$3)>0,D21/(1+SUMIFS(速報_原データ!$K$6:$K$9,速報_原データ!$I$6:$I$9,EDATE($A9,12),速報_原データ!$J$6:$J$9,D$3)/100),AVERAGE(D8,D10)))) -> 1113.4097 | E9: =IF(COUNTIFS(速報_原データ!$A$5:$A$200,$A9,速報_原データ!$B$5:$B$200,E$3)>0,SUMIFS(速報_原データ!$C$5:$C$200,速報_原データ!$A$5:$A$200,$A9,速報_原データ!$B$5:$B$200,E$3)/100,IF(COUNTIFS(速報_原データ!$A$5:$A$200,EDATE($A9,12),速報_原データ!$B$5:$B$200,E$3)>0,SUMIFS(速報_原データ!$C$5:$C$200,速報_原データ!$A$5:$A$200,EDATE($A9,12),速報_原データ!$B$5:$B$200,E$3)/100/(1+SUMIFS(速報_原データ!$D$5:$D$200,速報_原データ!$A$5:$A$200,EDATE($A9,12),速報_原データ!$B$5:$B$200,E$3)/100),IF(COUNTIFS(速報_原データ!$I$6:$I$9,EDATE($A9,12),速報_原データ!$J$6:$J$9,E$3)>0,E21/(1+SUMIFS(速報_原データ!$K$6:$K$9,速報_原データ!$I$6:$I$9,EDATE($A9,12),速報_原データ!$J$6:$J$9,E$3)/100),AVERAGE(E8,E10)))) -> 290.47249 | F9: =IF(COUNTIFS(速報_原データ!$A$5:$A$200,$A9,速報_原データ!$B$5:$B$200,F$3)>0,SUMIFS(速報_原データ!$C$5:$C$200,速報_原データ!$A$5:$A$200,$A9,速報_原データ!$B$5:$B$200,F$3)/100,IF(COUNTIFS(速報_原データ!$A$5:$A$200,EDATE($A9,12),速報_原データ!$B$5:$B$200,F$3)>0,SUMIFS(速報_原データ!$C$5:$C$200,速報_原データ!$A$5:$A$200,EDATE($A9,12),速報_原データ!$B$5:$B$200,F$3)/100/(1+SUMIFS(速報_原データ!$D$5:$D$200,速報_原データ!$A$5:$A$200,EDATE($A9,12),速報_原データ!$B$5:$B$200,F$3)/100),IF(COUNTIFS(速報_原データ!$I$6:$I$9,EDATE($A9,12),速報_原データ!$J$6:$J$9,F$3)>0,F21/(1+SUMIFS(速報_原データ!$K$6:$K$9,速報_原データ!$I$6:$I$9,EDATE($A9,12),速報_原データ!$J$6:$J$9,F$3)/100),AVERAGE(F8,F10)))) -> 263.91089 | G9: =IF(COUNTIFS(速報_原データ!$A$5:$A$200,$A9,速報_原データ!$B$5:$B$200,G$3)>0,SUMIFS(速報_原データ!$C$5:$C$200,速報_原データ!$A$5:$A$200,$A9,速報_原データ!$B$5:$B$200,G$3)/100,IF(COUNTIFS(速報_原データ!$A$5:$A$200,EDATE($A9,12),速報_原データ!$B$5:$B$200,G$3)>0,SUMIFS(速報_原データ!$C$5:$C$200,速報_原データ!$A$5:$A$200,EDATE($A9,12),速報_原データ!$B$5:$B$200,G$3)/100/(1+SUMIFS(速報_原データ!$D$5:$D$200,速報_原データ!$A$5:$A$200,EDATE($A9,12),速報_原データ!$B$5:$B$200,G$3)/100),IF(COUNTIFS(速報_原データ!$I$6:$I$9,EDATE($A9,12),速報_原データ!$J$6:$J$9,G$3)>0,G21/(1+SUMIFS(速報_原データ!$K$6:$K$9,速報_原データ!$I$6:$I$9,EDATE($A9,12),速報_原データ!$J$6:$J$9,G$3)/100),AVERAGE(G8,G10)))) -> 139.9759 | H9: =IF(COUNTIFS(速報_原データ!$A$5:$A$200,$A9,速報_原データ!$B$5:$B$200,H$3)>0,SUMIFS(速報_原データ!$C$5:$C$200,速報_原データ!$A$5:$A$200,$A9,速報_原データ!$B$5:$B$200,H$3)/100,IF(COUNTIFS(速報_原データ!$A$5:$A$200,EDATE($A9,12),速報_原データ!$B$5:$B$200,H$3)>0,SUMIFS(速報_原データ!$C$5:$C$200,速報_原データ!$A$5:$A$200,EDATE($A9,12),速報_原データ!$B$5:$B$200,H$3)/100/(1+SUMIFS(速報_原データ!$D$5:$D$200,速報_原データ!$A$5:$A$200,EDATE($A9,12),速報_原データ!$B$5:$B$200,H$3)/100),IF(COUNTIFS(速報_原データ!$I$6:$I$9,EDATE($A9,12),速報_原データ!$J$6:$J$9,H$3)>0,H21/(1+SUMIFS(速報_原データ!$K$6:$K$9,速報_原データ!$I$6:$I$9,EDATE($A9,12),速報_原データ!$J$6:$J$9,H$3)/100),AVERAGE(H8,H10)))) -> 139.41216 | I9: =B9-D9 -> 1096.1522 | J9: =C9-D9-E9-H9 -> 244.8387 | K9: 翌年同月速報の前年比から逆算
A10: 45170 | B10: =IF(COUNTIFS(速報_原データ!$A$5:$A$200,$A10,速報_原データ!$B$5:$B$200,B$3)>0,SUMIFS(速報_原データ!$C$5:$C$200,速報_原データ!$A$5:$A$200,$A10,速報_原データ!$B$5:$B$200,B$3)/100,IF(COUNTIFS(速報_原データ!$A$5:$A$200,EDATE($A10,12),速報_原データ!$B$5:$B$200,B$3)>0,SUMIFS(速報_原データ!$C$5:$C$200,速報_原データ!$A$5:$A$200,EDATE($A10,12),速報_原データ!$B$5:$B$200,B$3)/100/(1+SUMIFS(速報_原データ!$D$5:$D$200,速報_原データ!$A$5:$A$200,EDATE($A10,12),速報_原データ!$B$5:$B$200,B$3)/100),IF(COUNTIFS(速報_原データ!$I$6:$I$9,EDATE($A10,12),速報_原データ!$J$6:$J$9,B$3)>0,B22/(1+SUMIFS(速報_原データ!$K$6:$K$9,速報_原データ!$I$6:$I$9,EDATE($A10,12),速報_原データ!$J$6:$J$9,B$3)/100),AVERAGE(B9,B11)))) -> 3143.5234 | C10: =IF(COUNTIFS(速報_原データ!$A$5:$A$200,$A10,速報_原データ!$B$5:$B$200,C$3)>0,SUMIFS(速報_原データ!$C$5:$C$200,速報_原データ!$A$5:$A$200,$A10,速報_原データ!$B$5:$B$200,C$3)/100,IF(COUNTIFS(速報_原データ!$A$5:$A$200,EDATE($A10,12),速報_原データ!$B$5:$B$200,C$3)>0,SUMIFS(速報_原データ!$C$5:$C$200,速報_原データ!$A$5:$A$200,EDATE($A10,12),速報_原データ!$B$5:$B$200,C$3)/100/(1+SUMIFS(速報_原データ!$D$5:$D$200,速報_原データ!$A$5:$A$200,EDATE($A10,12),速報_原データ!$B$5:$B$200,C$3)/100),IF(COUNTIFS(速報_原データ!$I$6:$I$9,EDATE($A10,12),速報_原データ!$J$6:$J$9,C$3)>0,C22/(1+SUMIFS(速報_原データ!$K$6:$K$9,速報_原データ!$I$6:$I$9,EDATE($A10,12),速報_原データ!$J$6:$J$9,C$3)/100),AVERAGE(C9,C11)))) -> 2634.847 | D10: =IF(COUNTIFS(速報_原データ!$A$5:$A$200,$A10,速報_原データ!$B$5:$B$200,D$3)>0,SUMIFS(速報_原データ!$C$5:$C$200,速報_原データ!$A$5:$A$200,$A10,速報_原データ!$B$5:$B$200,D$3)/100,IF(COUNTIFS(速報_原データ!$A$5:$A$200,EDATE($A10,12),速報_原データ!$B$5:$B$200,D$3)>0,SUMIFS(速報_原データ!$C$5:$C$200,速報_原データ!$A$5:$A$200,EDATE($A10,12),速報_原データ!$B$5:$B$200,D$3)/100/(1+SUMIFS(速報_原データ!$D$5:$D$200,速報_原データ!$A$5:$A$200,EDATE($A10,12),速報_原データ!$B$5:$B$200,D$3)/100),IF(COUNTIFS(速報_原データ!$I$6:$I$9,EDATE($A10,12),速報_原データ!$J$6:$J$9,D$3)>0,D22/(1+SUMIFS(速報_原データ!$K$6:$K$9,速報_原データ!$I$6:$I$9,EDATE($A10,12),速報_原データ!$J$6:$J$9,D$3)/100),AVERAGE(D9,D11)))) -> 1666.7038 | E10: =IF(COUNTIFS(速報_原データ!$A$5:$A$200,$A10,速報_原データ!$B$5:$B$200,E$3)>0,SUMIFS(速報_原データ!$C$5:$C$200,速報_原データ!$A$5:$A$200,$A10,速報_原データ!$B$5:$B$200,E$3)/100,IF(COUNTIFS(速報_原データ!$A$5:$A$200,EDATE($A10,12),速報_原データ!$B$5:$B$200,E$3)>0,SUMIFS(速報_原データ!$C$5:$C$200,速報_原データ!$A$5:$A$200,EDATE($A10,12),速報_原データ!$B$5:$B$200,E$3)/100/(1+SUMIFS(速報_原データ!$D$5:$D$200,速報_原データ!$A$5:$A$200,EDATE($A10,12),速報_原データ!$B$5:$B$200,E$3)/100),IF(COUNTIFS(速報_原データ!$I$6:$I$9,EDATE($A10,12),速報_原データ!$J$6:$J$9,E$3)>0,E22/(1+SUMIFS(速報_原データ!$K$6:$K$9,速報_原データ!$I$6:$I$9,EDATE($A10,12),速報_原データ!$J$6:$J$9,E$3)/100),AVERAGE(E9,E11)))) -> 446.48097 | F10: =IF(COUNTIFS(速報_原データ!$A$5:$A$200,$A10,速報_原データ!$B$5:$B$200,F$3)>0,SUMIFS(速報_原データ!$C$5:$C$200,速報_原データ!$A$5:$A$200,$A10,速報_原データ!$B$5:$B$200,F$3)/100,IF(COUNTIFS(速報_原データ!$A$5:$A$200,EDATE($A10,12),速報_原データ!$B$5:$B$200,F$3)>0,SUMIFS(速報_原データ!$C$5:$C$200,速報_原データ!$A$5:$A$200,EDATE($A10,12),速報_原データ!$B$5:$B$200,F$3)/100/(1+SUMIFS(速報_原データ!$D$5:$D$200,速報_原データ!$A$5:$A$200,EDATE($A10,12),速報_原データ!$B$5:$B$200,F$3)/100),IF(COUNTIFS(速報_原データ!$I$6:$I$9,EDATE($A10,12),速報_原データ!$J$6:$J$9,F$3)>0,F22/(1+SUMIFS(速報_原データ!$K$6:$K$9,速報_原データ!$I$6:$I$9,EDATE($A10,12),速報_原データ!$J$6:$J$9,F$3)/100),AVERAGE(F9,F11)))) -> 334.7851 | G10: =IF(COUNTIFS(速報_原データ!$A$5:$A$200,$A10,速報_原データ!$B$5:$B$200,G$3)>0,SUMIFS(速報_原データ!$C$5:$C$200,速報_原データ!$A$5:$A$200,$A10,速報_原データ!$B$5:$B$200,G$3)/100,IF(COUNTIFS(速報_原データ!$A$5:$A$200,EDATE($A10,12),速報_原データ!$B$5:$B$200,G$3)>0,SUMIFS(速報_原データ!$C$5:$C$200,速報_原データ!$A$5:$A$200,EDATE($A10,12),速報_原データ!$B$5:$B$200,G$3)/100/(1+SUMIFS(速報_原データ!$D$5:$D$200,速報_原データ!$A$5:$A$200,EDATE($A10,12),速報_原データ!$B$5:$B$200,G$3)/100),IF(COUNTIFS(速報_原データ!$I$6:$I$9,EDATE($A10,12),速報_原データ!$J$6:$J$9,G$3)>0,G22/(1+SUMIFS(速報_原データ!$K$6:$K$9,速報_原データ!$I$6:$I$9,EDATE($A10,12),速報_原データ!$J$6:$J$9,G$3)/100),AVERAGE(G9,G11)))) -> 167.20395 | H10: =IF(COUNTIFS(速報_原データ!$A$5:$A$200,$A10,速報_原データ!$B$5:$B$200,H$3)>0,SUMIFS(速報_原データ!$C$5:$C$200,速報_原データ!$A$5:$A$200,$A10,速報_原データ!$B$5:$B$200,H$3)/100,IF(COUNTIFS(速報_原データ!$A$5:$A$200,EDATE($A10,12),速報_原データ!$B$5:$B$200,H$3)>0,SUMIFS(速報_原データ!$C$5:$C$200,速報_原データ!$A$5:$A$200,EDATE($A10,12),速報_原データ!$B$5:$B$200,H$3)/100/(1+SUMIFS(速報_原データ!$D$5:$D$200,速報_原データ!$A$5:$A$200,EDATE($A10,12),速報_原データ!$B$5:$B$200,H$3)/100),IF(COUNTIFS(速報_原データ!$I$6:$I$9,EDATE($A10,12),速報_原データ!$J$6:$J$9,H$3)>0,H22/(1+SUMIFS(速報_原データ!$K$6:$K$9,速報_原データ!$I$6:$I$9,EDATE($A10,12),速報_原データ!$J$6:$J$9,H$3)/100),AVERAGE(H9,H11)))) -> 174.63538 | I10: =B10-D10 -> 1476.8196 | J10: =C10-D10-E10-H10 -> 347.0269 | K10: 翌年同月速報の前年比から逆算
A11: 45200 | B11: =IF(COUNTIFS(速報_原データ!$A$5:$A$200,$A11,速報_原データ!$B$5:$B$200,B$3)>0,SUMIFS(速報_原データ!$C$5:$C$200,速報_原データ!$A$5:$A$200,$A11,速報_原データ!$B$5:$B$200,B$3)/100,IF(COUNTIFS(速報_原データ!$A$5:$A$200,EDATE($A11,12),速報_原データ!$B$5:$B$200,B$3)>0,SUMIFS(速報_原データ!$C$5:$C$200,速報_原データ!$A$5:$A$200,EDATE($A11,12),速報_原データ!$B$5:$B$200,B$3)/100/(1+SUMIFS(速報_原データ!$D$5:$D$200,速報_原データ!$A$5:$A$200,EDATE($A11,12),速報_原データ!$B$5:$B$200,B$3)/100),IF(COUNTIFS(速報_原データ!$I$6:$I$9,EDATE($A11,12),速報_原データ!$J$6:$J$9,B$3)>0,B23/(1+SUMIFS(速報_原データ!$K$6:$K$9,速報_原データ!$I$6:$I$9,EDATE($A11,12),速報_原データ!$J$6:$J$9,B$3)/100),AVERAGE(B10,B12)))) -> 2858.331 | C11: =IF(COUNTIFS(速報_原データ!$A$5:$A$200,$A11,速報_原データ!$B$5:$B$200,C$3)>0,SUMIFS(速報_原データ!$C$5:$C$200,速報_原データ!$A$5:$A$200,$A11,速報_原データ!$B$5:$B$200,C$3)/100,IF(COUNTIFS(速報_原データ!$A$5:$A$200,EDATE($A11,12),速報_原データ!$B$5:$B$200,C$3)>0,SUMIFS(速報_原データ!$C$5:$C$200,速報_原データ!$A$5:$A$200,EDATE($A11,12),速報_原データ!$B$5:$B$200,C$3)/100/(1+SUMIFS(速報_原データ!$D$5:$D$200,速報_原データ!$A$5:$A$200,EDATE($A11,12),速報_原データ!$B$5:$B$200,C$3)/100),IF(COUNTIFS(速報_原データ!$I$6:$I$9,EDATE($A11,12),速報_原データ!$J$6:$J$9,C$3)>0,C23/(1+SUMIFS(速報_原データ!$K$6:$K$9,速報_原データ!$I$6:$I$9,EDATE($A11,12),速報_原データ!$J$6:$J$9,C$3)/100),AVERAGE(C10,C12)))) -> 2188.3844 | D11: =IF(COUNTIFS(速報_原データ!$A$5:$A$200,$A11,速報_原データ!$B$5:$B$200,D$3)>0,SUMIFS(速報_原データ!$C$5:$C$200,速報_原データ!$A$5:$A$200,$A11,速報_原データ!$B$5:$B$200,D$3)/100,IF(COUNTIFS(速報_原データ!$A$5:$A$200,EDATE($A11,12),速報_原データ!$B$5:$B$200,D$3)>0,SUMIFS(速報_原データ!$C$5:$C$200,速報_原データ!$A$5:$A$200,EDATE($A11,12),速報_原データ!$B$5:$B$200,D$3)/100/(1+SUMIFS(速報_原データ!$D$5:$D$200,速報_原データ!$A$5:$A$200,EDATE($A11,12),速報_原データ!$B$5:$B$200,D$3)/100),IF(COUNTIFS(速報_原データ!$I$6:$I$9,EDATE($A11,12),速報_原データ!$J$6:$J$9,D$3)>0,D23/(1+SUMIFS(速報_原データ!$K$6:$K$9,速報_原データ!$I$6:$I$9,EDATE($A11,12),速報_原データ!$J$6:$J$9,D$3)/100),AVERAGE(D10,D12)))) -> 1379.6177 | E11: =IF(COUNTIFS(速報_原データ!$A$5:$A$200,$A11,速報_原データ!$B$5:$B$200,E$3)>0,SUMIFS(速報_原データ!$C$5:$C$200,速報_原データ!$A$5:$A$200,$A11,速報_原データ!$B$5:$B$200,E$3)/100,IF(COUNTIFS(速報_原データ!$A$5:$A$200,EDATE($A11,12),速報_原データ!$B$5:$B$200,E$3)>0,SUMIFS(速報_原データ!$C$5:$C$200,速報_原データ!$A$5:$A$200,EDATE($A11,12),速報_原データ!$B$5:$B$200,E$3)/100/(1+SUMIFS(速報_原データ!$D$5:$D$200,速報_原データ!$A$5:$A$200,EDATE($A11,12),速報_原データ!$B$5:$B$200,E$3)/100),IF(COUNTIFS(速報_原データ!$I$6:$I$9,EDATE($A11,12),速報_原データ!$J$6:$J$9,E$3)>0,E23/(1+SUMIFS(速報_原データ!$K$6:$K$9,速報_原データ!$I$6:$I$9,EDATE($A11,12),速報_原データ!$J$6:$J$9,E$3)/100),AVERAGE(E10,E12)))) -> 279.40784 | F11: =IF(COUNTIFS(速報_原データ!$A$5:$A$200,$A11,速報_原データ!$B$5:$B$200,F$3)>0,SUMIFS(速報_原データ!$C$5:$C$200,速報_原データ!$A$5:$A$200,$A11,速報_原データ!$B$5:$B$200,F$3)/100,IF(COUNTIFS(速報_原データ!$A$5:$A$200,EDATE($A11,12),速報_原データ!$B$5:$B$200,F$3)>0,SUMIFS(速報_原データ!$C$5:$C$200,速報_原データ!$A$5:$A$200,EDATE($A11,12),速報_原データ!$B$5:$B$200,F$3)/100/(1+SUMIFS(速報_原データ!$D$5:$D$200,速報_原データ!$A$5:$A$200,EDATE($A11,12),速報_原データ!$B$5:$B$200,F$3)/100),IF(COUNTIFS(速報_原データ!$I$6:$I$9,EDATE($A11,12),速報_原データ!$J$6:$J$9,F$3)>0,F23/(1+SUMIFS(速報_原データ!$K$6:$K$9,速報_原データ!$I$6:$I$9,EDATE($A11,12),速報_原データ!$J$6:$J$9,F$3)/100),AVERAGE(F10,F12)))) -> 499.86111 | G11: =IF(COUNTIFS(速報_原データ!$A$5:$A$200,$A11,速報_原データ!$B$5:$B$200,G$3)>0,SUMIFS(速報_原データ!$C$5:$C$200,速報_原データ!$A$5:$A$200,$A11,速報_原データ!$B$5:$B$200,G$3)/100,IF(COUNTIFS(速報_原データ!$A$5:$A$200,EDATE($A11,12),速報_原データ!$B$5:$B$200,G$3)>0,SUMIFS(速報_原データ!$C$5:$C$200,速報_原データ!$A$5:$A$200,EDATE($A11,12),速報_原データ!$B$5:$B$200,G$3)/100/(1+SUMIFS(速報_原データ!$D$5:$D$200,速報_原データ!$A$5:$A$200,EDATE($A11,12),速報_原データ!$B$5:$B$200,G$3)/100),IF(COUNTIFS(速報_原データ!$I$6:$I$9,EDATE($A11,12),速報_原データ!$J$6:$J$9,G$3)>0,G23/(1+SUMIFS(速報_原データ!$K$6:$K$9,速報_原データ!$I$6:$I$9,EDATE($A11,12),速報_原データ!$J$6:$J$9,G$3)/100),AVERAGE(G10,G12)))) -> 166.2169 | H11: =IF(COUNTIFS(速報_原データ!$A$5:$A$200,$A11,速報_原データ!$B$5:$B$200,H$3)>0,SUMIFS(速報_原データ!$C$5:$C$200,速報_原データ!$A$5:$A$200,$A11,速報_原データ!$B$5:$B$200,H$3)/100,IF(COUNTIFS(速報_原データ!$A$5:$A$200,EDATE($A11,12),速報_原データ!$B$5:$B$200,H$3)>0,SUMIFS(速報_原データ!$C$5:$C$200,速報_原データ!$A$5:$A$200,EDATE($A11,12),速報_原データ!$B$5:$B$200,H$3)/100/(1+SUMIFS(速報_原データ!$D$5:$D$200,速報_原データ!$A$5:$A$200,EDATE($A11,12),速報_原データ!$B$5:$B$200,H$3)/100),IF(COUNTIFS(速報_原データ!$I$6:$I$9,EDATE($A11,12),速報_原データ!$J$6:$J$9,H$3)>0,H23/(1+SUMIFS(速報_原データ!$K$6:$K$9,速報_原データ!$I$6:$I$9,EDATE($A11,12),速報_原データ!$J$6:$J$9,H$3)/100),AVERAGE(H10,H12)))) -> 143.84651 | I11: =B11-D11 -> 1478.7133 | J11: =C11-D11-E11-H11 -> 385.51233 | K11: 翌年同月速報の前年比から逆算
A12: 45231 | B12: =IF(COUNTIFS(速報_原データ!$A$5:$A$200,$A12,速報_原データ!$B$5:$B$200,B$3)>0,SUMIFS(速報_原データ!$C$5:$C$200,速報_原データ!$A$5:$A$200,$A12,速報_原データ!$B$5:$B$200,B$3)/100,IF(COUNTIFS(速報_原データ!$A$5:$A$200,EDATE($A12,12),速報_原データ!$B$5:$B$200,B$3)>0,SUMIFS(速報_原データ!$C$5:$C$200,速報_原データ!$A$5:$A$200,EDATE($A12,12),速報_原データ!$B$5:$B$200,B$3)/100/(1+SUMIFS(速報_原データ!$D$5:$D$200,速報_原データ!$A$5:$A$200,EDATE($A12,12),速報_原データ!$B$5:$B$200,B$3)/100),IF(COUNTIFS(速報_原データ!$I$6:$I$9,EDATE($A12,12),速報_原データ!$J$6:$J$9,B$3)>0,B24/(1+SUMIFS(速報_原データ!$K$6:$K$9,速報_原データ!$I$6:$I$9,EDATE($A12,12),速報_原データ!$J$6:$J$9,B$3)/100),AVERAGE(B11,B13)))) -> 2833.9137 | C12: =IF(COUNTIFS(速報_原データ!$A$5:$A$200,$A12,速報_原データ!$B$5:$B$200,C$3)>0,SUMIFS(速報_原データ!$C$5:$C$200,速報_原データ!$A$5:$A$200,$A12,速報_原データ!$B$5:$B$200,C$3)/100,IF(COUNTIFS(速報_原データ!$A$5:$A$200,EDATE($A12,12),速報_原データ!$B$5:$B$200,C$3)>0,SUMIFS(速報_原データ!$C$5:$C$200,速報_原データ!$A$5:$A$200,EDATE($A12,12),速報_原データ!$B$5:$B$200,C$3)/100/(1+SUMIFS(速報_原データ!$D$5:$D$200,速報_原データ!$A$5:$A$200,EDATE($A12,12),速報_原データ!$B$5:$B$200,C$3)/100),IF(COUNTIFS(速報_原データ!$I$6:$I$9,EDATE($A12,12),速報_原データ!$J$6:$J$9,C$3)>0,C24/(1+SUMIFS(速報_原データ!$K$6:$K$9,速報_原データ!$I$6:$I$9,EDATE($A12,12),速報_原データ!$J$6:$J$9,C$3)/100),AVERAGE(C11,C13)))) -> 2353.8231 | D12: =IF(COUNTIFS(速報_原データ!$A$5:$A$200,$A12,速報_原データ!$B$5:$B$200,D$3)>0,SUMIFS(速報_原データ!$C$5:$C$200,速報_原データ!$A$5:$A$200,$A12,速報_原データ!$B$5:$B$200,D$3)/100,IF(COUNTIFS(速報_原データ!$A$5:$A$200,EDATE($A12,12),速報_原データ!$B$5:$B$200,D$3)>0,SUMIFS(速報_原データ!$C$5:$C$200,速報_原データ!$A$5:$A$200,EDATE($A12,12),速報_原データ!$B$5:$B$200,D$3)/100/(1+SUMIFS(速報_原データ!$D$5:$D$200,速報_原データ!$A$5:$A$200,EDATE($A12,12),速報_原データ!$B$5:$B$200,D$3)/100),IF(COUNTIFS(速報_原データ!$I$6:$I$9,EDATE($A12,12),速報_原データ!$J$6:$J$9,D$3)>0,D24/(1+SUMIFS(速報_原データ!$K$6:$K$9,速報_原データ!$I$6:$I$9,EDATE($A12,12),速報_原データ!$J$6:$J$9,D$3)/100),AVERAGE(D11,D13)))) -> 1575.1823 | E12: =IF(COUNTIFS(速報_原データ!$A$5:$A$200,$A12,速報_原データ!$B$5:$B$200,E$3)>0,SUMIFS(速報_原データ!$C$5:$C$200,速報_原データ!$A$5:$A$200,$A12,速報_原データ!$B$5:$B$200,E$3)/100,IF(COUNTIFS(速報_原データ!$A$5:$A$200,EDATE($A12,12),速報_原データ!$B$5:$B$200,E$3)>0,SUMIFS(速報_原データ!$C$5:$C$200,速報_原データ!$A$5:$A$200,EDATE($A12,12),速報_原データ!$B$5:$B$200,E$3)/100/(1+SUMIFS(速報_原データ!$D$5:$D$200,速報_原データ!$A$5:$A$200,EDATE($A12,12),速報_原データ!$B$5:$B$200,E$3)/100),IF(COUNTIFS(速報_原データ!$I$6:$I$9,EDATE($A12,12),速報_原データ!$J$6:$J$9,E$3)>0,E24/(1+SUMIFS(速報_原データ!$K$6:$K$9,速報_原データ!$I$6:$I$9,EDATE($A12,12),速報_原データ!$J$6:$J$9,E$3)/100),AVERAGE(E11,E13)))) -> 293.03844 | F12: =IF(COUNTIFS(速報_原データ!$A$5:$A$200,$A12,速報_原データ!$B$5:$B$200,F$3)>0,SUMIFS(速報_原データ!$C$5:$C$200,速報_原データ!$A$5:$A$200,$A12,速報_原データ!$B$5:$B$200,F$3)/100,IF(COUNTIFS(速報_原データ!$A$5:$A$200,EDATE($A12,12),速報_原データ!$B$5:$B$200,F$3)>0,SUMIFS(速報_原データ!$C$5:$C$200,速報_原データ!$A$5:$A$200,EDATE($A12,12),速報_原データ!$B$5:$B$200,F$3)/100/(1+SUMIFS(速報_原データ!$D$5:$D$200,速報_原データ!$A$5:$A$200,EDATE($A12,12),速報_原データ!$B$5:$B$200,F$3)/100),IF(COUNTIFS(速報_原データ!$I$6:$I$9,EDATE($A12,12),速報_原データ!$J$6:$J$9,F$3)>0,F24/(1+SUMIFS(速報_原データ!$K$6:$K$9,速報_原データ!$I$6:$I$9,EDATE($A12,12),速報_原データ!$J$6:$J$9,F$3)/100),AVERAGE(F11,F13)))) -> 357.14286 | G12: =IF(COUNTIFS(速報_原データ!$A$5:$A$200,$A12,速報_原データ!$B$5:$B$200,G$3)>0,SUMIFS(速報_原データ!$C$5:$C$200,速報_原データ!$A$5:$A$200,$A12,速報_原データ!$B$5:$B$200,G$3)/100,IF(COUNTIFS(速報_原データ!$A$5:$A$200,EDATE($A12,12),速報_原データ!$B$5:$B$200,G$3)>0,SUMIFS(速報_原データ!$C$5:$C$200,速報_原データ!$A$5:$A$200,EDATE($A12,12),速報_原データ!$B$5:$B$200,G$3)/100/(1+SUMIFS(速報_原データ!$D$5:$D$200,速報_原データ!$A$5:$A$200,EDATE($A12,12),速報_原データ!$B$5:$B$200,G$3)/100),IF(COUNTIFS(速報_原データ!$I$6:$I$9,EDATE($A12,12),速報_原データ!$J$6:$J$9,G$3)>0,G24/(1+SUMIFS(速報_原データ!$K$6:$K$9,速報_原データ!$I$6:$I$9,EDATE($A12,12),速報_原データ!$J$6:$J$9,G$3)/100),AVERAGE(G11,G13)))) -> 114.23645 | H12: =IF(COUNTIFS(速報_原データ!$A$5:$A$200,$A12,速報_原データ!$B$5:$B$200,H$3)>0,SUMIFS(速報_原データ!$C$5:$C$200,速報_原データ!$A$5:$A$200,$A12,速報_原データ!$B$5:$B$200,H$3)/100,IF(COUNTIFS(速報_原データ!$A$5:$A$200,EDATE($A12,12),速報_原データ!$B$5:$B$200,H$3)>0,SUMIFS(速報_原データ!$C$5:$C$200,速報_原データ!$A$5:$A$200,EDATE($A12,12),速報_原データ!$B$5:$B$200,H$3)/100/(1+SUMIFS(速報_原データ!$D$5:$D$200,速報_原データ!$A$5:$A$200,EDATE($A12,12),速報_原データ!$B$5:$B$200,H$3)/100),IF(COUNTIFS(速報_原データ!$I$6:$I$9,EDATE($A12,12),速報_原データ!$J$6:$J$9,H$3)>0,H24/(1+SUMIFS(速報_原データ!$K$6:$K$9,速報_原データ!$I$6:$I$9,EDATE($A12,12),速報_原データ!$J$6:$J$9,H$3)/100),AVERAGE(H11,H13)))) -> 143.6339 | I12: =B12-D12 -> 1258.7314 | J12: =C12-D12-E12-H12 -> 341.96842 | K12: 翌年同月速報の前年比から逆算
A13: 45261 | B13: =IF(COUNTIFS(速報_原データ!$A$5:$A$200,$A13,速報_原データ!$B$5:$B$200,B$3)>0,SUMIFS(速報_原データ!$C$5:$C$200,速報_原データ!$A$5:$A$200,$A13,速報_原データ!$B$5:$B$200,B$3)/100,IF(COUNTIFS(速報_原データ!$A$5:$A$200,EDATE($A13,12),速報_原データ!$B$5:$B$200,B$3)>0,SUMIFS(速報_原データ!$C$5:$C$200,速報_原データ!$A$5:$A$200,EDATE($A13,12),速報_原データ!$B$5:$B$200,B$3)/100/(1+SUMIFS(速報_原データ!$D$5:$D$200,速報_原データ!$A$5:$A$200,EDATE($A13,12),速報_原データ!$B$5:$B$200,B$3)/100),IF(COUNTIFS(速報_原データ!$I$6:$I$9,EDATE($A13,12),速報_原データ!$J$6:$J$9,B$3)>0,B25/(1+SUMIFS(速報_原データ!$K$6:$K$9,速報_原データ!$I$6:$I$9,EDATE($A13,12),速報_原データ!$J$6:$J$9,B$3)/100),AVERAGE(B12,B14)))) -> 4071.0759 | C13: =IF(COUNTIFS(速報_原データ!$A$5:$A$200,$A13,速報_原データ!$B$5:$B$200,C$3)>0,SUMIFS(速報_原データ!$C$5:$C$200,速報_原データ!$A$5:$A$200,$A13,速報_原データ!$B$5:$B$200,C$3)/100,IF(COUNTIFS(速報_原データ!$A$5:$A$200,EDATE($A13,12),速報_原データ!$B$5:$B$200,C$3)>0,SUMIFS(速報_原データ!$C$5:$C$200,速報_原データ!$A$5:$A$200,EDATE($A13,12),速報_原データ!$B$5:$B$200,C$3)/100/(1+SUMIFS(速報_原データ!$D$5:$D$200,速報_原データ!$A$5:$A$200,EDATE($A13,12),速報_原データ!$B$5:$B$200,C$3)/100),IF(COUNTIFS(速報_原データ!$I$6:$I$9,EDATE($A13,12),速報_原データ!$J$6:$J$9,C$3)>0,C25/(1+SUMIFS(速報_原データ!$K$6:$K$9,速報_原データ!$I$6:$I$9,EDATE($A13,12),速報_原データ!$J$6:$J$9,C$3)/100),AVERAGE(C12,C14)))) -> 3532.6619 | D13: =IF(COUNTIFS(速報_原データ!$A$5:$A$200,$A13,速報_原データ!$B$5:$B$200,D$3)>0,SUMIFS(速報_原データ!$C$5:$C$200,速報_原データ!$A$5:$A$200,$A13,速報_原データ!$B$5:$B$200,D$3)/100,IF(COUNTIFS(速報_原データ!$A$5:$A$200,EDATE($A13,12),速報_原データ!$B$5:$B$200,D$3)>0,SUMIFS(速報_原データ!$C$5:$C$200,速報_原データ!$A$5:$A$200,EDATE($A13,12),速報_原データ!$B$5:$B$200,D$3)/100/(1+SUMIFS(速報_原データ!$D$5:$D$200,速報_原データ!$A$5:$A$200,EDATE($A13,12),速報_原データ!$B$5:$B$200,D$3)/100),IF(COUNTIFS(速報_原データ!$I$6:$I$9,EDATE($A13,12),速報_原データ!$J$6:$J$9,D$3)>0,D25/(1+SUMIFS(速報_原データ!$K$6:$K$9,速報_原データ!$I$6:$I$9,EDATE($A13,12),速報_原データ!$J$6:$J$9,D$3)/100),AVERAGE(D12,D14)))) -> 2224.1518 | E13: =IF(COUNTIFS(速報_原データ!$A$5:$A$200,$A13,速報_原データ!$B$5:$B$200,E$3)>0,SUMIFS(速報_原データ!$C$5:$C$200,速報_原データ!$A$5:$A$200,$A13,速報_原データ!$B$5:$B$200,E$3)/100,IF(COUNTIFS(速報_原データ!$A$5:$A$200,EDATE($A13,12),速報_原データ!$B$5:$B$200,E$3)>0,SUMIFS(速報_原データ!$C$5:$C$200,速報_原データ!$A$5:$A$200,EDATE($A13,12),速報_原データ!$B$5:$B$200,E$3)/100/(1+SUMIFS(速報_原データ!$D$5:$D$200,速報_原データ!$A$5:$A$200,EDATE($A13,12),速報_原データ!$B$5:$B$200,E$3)/100),IF(COUNTIFS(速報_原データ!$I$6:$I$9,EDATE($A13,12),速報_原データ!$J$6:$J$9,E$3)>0,E25/(1+SUMIFS(速報_原データ!$K$6:$K$9,速報_原データ!$I$6:$I$9,EDATE($A13,12),速報_原データ!$J$6:$J$9,E$3)/100),AVERAGE(E12,E14)))) -> 576.84341 | F13: =IF(COUNTIFS(速報_原データ!$A$5:$A$200,$A13,速報_原データ!$B$5:$B$200,F$3)>0,SUMIFS(速報_原データ!$C$5:$C$200,速報_原データ!$A$5:$A$200,$A13,速報_原データ!$B$5:$B$200,F$3)/100,IF(COUNTIFS(速報_原データ!$A$5:$A$200,EDATE($A13,12),速報_原データ!$B$5:$B$200,F$3)>0,SUMIFS(速報_原データ!$C$5:$C$200,速報_原データ!$A$5:$A$200,EDATE($A13,12),速報_原データ!$B$5:$B$200,F$3)/100/(1+SUMIFS(速報_原データ!$D$5:$D$200,速報_原データ!$A$5:$A$200,EDATE($A13,12),速報_原データ!$B$5:$B$200,F$3)/100),IF(COUNTIFS(速報_原データ!$I$6:$I$9,EDATE($A13,12),速報_原データ!$J$6:$J$9,F$3)>0,F25/(1+SUMIFS(速報_原データ!$K$6:$K$9,速報_原データ!$I$6:$I$9,EDATE($A13,12),速報_原データ!$J$6:$J$9,F$3)/100),AVERAGE(F12,F14)))) -> 407.62231 | G13: =IF(COUNTIFS(速報_原データ!$A$5:$A$200,$A13,速報_原データ!$B$5:$B$200,G$3)>0,SUMIFS(速報_原データ!$C$5:$C$200,速報_原データ!$A$5:$A$200,$A13,速報_原データ!$B$5:$B$200,G$3)/100,IF(COUNTIFS(速報_原データ!$A$5:$A$200,EDATE($A13,12),速報_原データ!$B$5:$B$200,G$3)>0,SUMIFS(速報_原データ!$C$5:$C$200,速報_原データ!$A$5:$A$200,EDATE($A13,12),速報_原データ!$B$5:$B$200,G$3)/100/(1+SUMIFS(速報_原データ!$D$5:$D$200,速報_原データ!$A$5:$A$200,EDATE($A13,12),速報_原データ!$B$5:$B$200,G$3)/100),IF(COUNTIFS(速報_原データ!$I$6:$I$9,EDATE($A13,12),速報_原データ!$J$6:$J$9,G$3)>0,G25/(1+SUMIFS(速報_原データ!$K$6:$K$9,速報_原データ!$I$6:$I$9,EDATE($A13,12),速報_原データ!$J$6:$J$9,G$3)/100),AVERAGE(G12,G14)))) -> 119.26941 | H13: =IF(COUNTIFS(速報_原データ!$A$5:$A$200,$A13,速報_原データ!$B$5:$B$200,H$3)>0,SUMIFS(速報_原データ!$C$5:$C$200,速報_原データ!$A$5:$A$200,$A13,速報_原データ!$B$5:$B$200,H$3)/100,IF(COUNTIFS(速報_原データ!$A$5:$A$200,EDATE($A13,12),速報_原データ!$B$5:$B$200,H$3)>0,SUMIFS(速報_原データ!$C$5:$C$200,速報_原データ!$A$5:$A$200,EDATE($A13,12),速報_原データ!$B$5:$B$200,H$3)/100/(1+SUMIFS(速報_原データ!$D$5:$D$200,速報_原データ!$A$5:$A$200,EDATE($A13,12),速報_原データ!$B$5:$B$200,H$3)/100),IF(COUNTIFS(速報_原データ!$I$6:$I$9,EDATE($A13,12),速報_原データ!$J$6:$J$9,H$3)>0,H25/(1+SUMIFS(速報_原データ!$K$6:$K$9,速報_原データ!$I$6:$I$9,EDATE($A13,12),速報_原データ!$J$6:$J$9,H$3)/100),AVERAGE(H12,H14)))) -> 202.08955 | I13: =B13-D13 -> 1846.9242 | J13: =C13-D13-E13-H13 -> 529.57712 | K13: 翌年同月速報の前年比から逆算
A14: 45292 | B14: =IF(COUNTIFS(速報_原データ!$A$5:$A$200,$A14,速報_原データ!$B$5:$B$200,B$3)>0,SUMIFS(速報_原データ!$C$5:$C$200,速報_原データ!$A$5:$A$200,$A14,速報_原データ!$B$5:$B$200,B$3)/100,IF(COUNTIFS(速報_原データ!$A$5:$A$200,EDATE($A14,12),速報_原データ!$B$5:$B$200,B$3)>0,SUMIFS(速報_原データ!$C$5:$C$200,速報_原データ!$A$5:$A$200,EDATE($A14,12),速報_原データ!$B$5:$B$200,B$3)/100/(1+SUMIFS(速報_原データ!$D$5:$D$200,速報_原データ!$A$5:$A$200,EDATE($A14,12),速報_原データ!$B$5:$B$200,B$3)/100),IF(COUNTIFS(速報_原データ!$I$6:$I$9,EDATE($A14,12),速報_原データ!$J$6:$J$9,B$3)>0,B26/(1+SUMIFS(速報_原データ!$K$6:$K$9,速報_原データ!$I$6:$I$9,EDATE($A14,12),速報_原データ!$J$6:$J$9,B$3)/100),AVERAGE(B13,B15)))) -> 2911.3246 | C14: =IF(COUNTIFS(速報_原データ!$A$5:$A$200,$A14,速報_原データ!$B$5:$B$200,C$3)>0,SUMIFS(速報_原データ!$C$5:$C$200,速報_原データ!$A$5:$A$200,$A14,速報_原データ!$B$5:$B$200,C$3)/100,IF(COUNTIFS(速報_原データ!$A$5:$A$200,EDATE($A14,12),速報_原データ!$B$5:$B$200,C$3)>0,SUMIFS(速報_原データ!$C$5:$C$200,速報_原データ!$A$5:$A$200,EDATE($A14,12),速報_原データ!$B$5:$B$200,C$3)/100/(1+SUMIFS(速報_原データ!$D$5:$D$200,速報_原データ!$A$5:$A$200,EDATE($A14,12),速報_原データ!$B$5:$B$200,C$3)/100),IF(COUNTIFS(速報_原データ!$I$6:$I$9,EDATE($A14,12),速報_原データ!$J$6:$J$9,C$3)>0,C26/(1+SUMIFS(速報_原データ!$K$6:$K$9,速報_原データ!$I$6:$I$9,EDATE($A14,12),速報_原データ!$J$6:$J$9,C$3)/100),AVERAGE(C13,C15)))) -> 2413.3721 | D14: =IF(COUNTIFS(速報_原データ!$A$5:$A$200,$A14,速報_原データ!$B$5:$B$200,D$3)>0,SUMIFS(速報_原データ!$C$5:$C$200,速報_原データ!$A$5:$A$200,$A14,速報_原データ!$B$5:$B$200,D$3)/100,IF(COUNTIFS(速報_原データ!$A$5:$A$200,EDATE($A14,12),速報_原データ!$B$5:$B$200,D$3)>0,SUMIFS(速報_原データ!$C$5:$C$200,速報_原データ!$A$5:$A$200,EDATE($A14,12),速報_原データ!$B$5:$B$200,D$3)/100/(1+SUMIFS(速報_原データ!$D$5:$D$200,速報_原データ!$A$5:$A$200,EDATE($A14,12),速報_原データ!$B$5:$B$200,D$3)/100),IF(COUNTIFS(速報_原データ!$I$6:$I$9,EDATE($A14,12),速報_原データ!$J$6:$J$9,D$3)>0,D26/(1+SUMIFS(速報_原データ!$K$6:$K$9,速報_原データ!$I$6:$I$9,EDATE($A14,12),速報_原データ!$J$6:$J$9,D$3)/100),AVERAGE(D13,D15)))) -> 1240.9975 | E14: =IF(COUNTIFS(速報_原データ!$A$5:$A$200,$A14,速報_原データ!$B$5:$B$200,E$3)>0,SUMIFS(速報_原データ!$C$5:$C$200,速報_原データ!$A$5:$A$200,$A14,速報_原データ!$B$5:$B$200,E$3)/100,IF(COUNTIFS(速報_原データ!$A$5:$A$200,EDATE($A14,12),速報_原データ!$B$5:$B$200,E$3)>0,SUMIFS(速報_原データ!$C$5:$C$200,速報_原データ!$A$5:$A$200,EDATE($A14,12),速報_原データ!$B$5:$B$200,E$3)/100/(1+SUMIFS(速報_原データ!$D$5:$D$200,速報_原データ!$A$5:$A$200,EDATE($A14,12),速報_原データ!$B$5:$B$200,E$3)/100),IF(COUNTIFS(速報_原データ!$I$6:$I$9,EDATE($A14,12),速報_原データ!$J$6:$J$9,E$3)>0,E26/(1+SUMIFS(速報_原データ!$K$6:$K$9,速報_原データ!$I$6:$I$9,EDATE($A14,12),速報_原データ!$J$6:$J$9,E$3)/100),AVERAGE(E13,E15)))) -> 598.60355 | F14: =IF(COUNTIFS(速報_原データ!$A$5:$A$200,$A14,速報_原データ!$B$5:$B$200,F$3)>0,SUMIFS(速報_原データ!$C$5:$C$200,速報_原データ!$A$5:$A$200,$A14,速報_原データ!$B$5:$B$200,F$3)/100,IF(COUNTIFS(速報_原データ!$A$5:$A$200,EDATE($A14,12),速報_原データ!$B$5:$B$200,F$3)>0,SUMIFS(速報_原データ!$C$5:$C$200,速報_原データ!$A$5:$A$200,EDATE($A14,12),速報_原データ!$B$5:$B$200,F$3)/100/(1+SUMIFS(速報_原データ!$D$5:$D$200,速報_原データ!$A$5:$A$200,EDATE($A14,12),速報_原データ!$B$5:$B$200,F$3)/100),IF(COUNTIFS(速報_原データ!$I$6:$I$9,EDATE($A14,12),速報_原データ!$J$6:$J$9,F$3)>0,F26/(1+SUMIFS(速報_原データ!$K$6:$K$9,速報_原データ!$I$6:$I$9,EDATE($A14,12),速報_原データ!$J$6:$J$9,F$3)/100),AVERAGE(F13,F15)))) -> 362.10526 | G14: =IF(COUNTIFS(速報_原データ!$A$5:$A$200,$A14,速報_原データ!$B$5:$B$200,G$3)>0,SUMIFS(速報_原データ!$C$5:$C$200,速報_原データ!$A$5:$A$200,$A14,速報_原データ!$B$5:$B$200,G$3)/100,IF(COUNTIFS(速報_原データ!$A$5:$A$200,EDATE($A14,12),速報_原データ!$B$5:$B$200,G$3)>0,SUMIFS(速報_原データ!$C$5:$C$200,速報_原データ!$A$5:$A$200,EDATE($A14,12),速報_原データ!$B$5:$B$200,G$3)/100/(1+SUMIFS(速報_原データ!$D$5:$D$200,速報_原データ!$A$5:$A$200,EDATE($A14,12),速報_原データ!$B$5:$B$200,G$3)/100),IF(COUNTIFS(速報_原データ!$I$6:$I$9,EDATE($A14,12),速報_原データ!$J$6:$J$9,G$3)>0,G26/(1+SUMIFS(速報_原データ!$K$6:$K$9,速報_原データ!$I$6:$I$9,EDATE($A14,12),速報_原データ!$J$6:$J$9,G$3)/100),AVERAGE(G13,G15)))) -> 129.10663 | H14: =IF(COUNTIFS(速報_原データ!$A$5:$A$200,$A14,速報_原データ!$B$5:$B$200,H$3)>0,SUMIFS(速報_原データ!$C$5:$C$200,速報_原データ!$A$5:$A$200,$A14,速報_原データ!$B$5:$B$200,H$3)/100,IF(COUNTIFS(速報_原データ!$A$5:$A$200,EDATE($A14,12),速報_原データ!$B$5:$B$200,H$3)>0,SUMIFS(速報_原データ!$C$5:$C$200,速報_原データ!$A$5:$A$200,EDATE($A14,12),速報_原データ!$B$5:$B$200,H$3)/100/(1+SUMIFS(速報_原データ!$D$5:$D$200,速報_原データ!$A$5:$A$200,EDATE($A14,12),速報_原データ!$B$5:$B$200,H$3)/100),IF(COUNTIFS(速報_原データ!$I$6:$I$9,EDATE($A14,12),速報_原データ!$J$6:$J$9,H$3)>0,H26/(1+SUMIFS(速報_原データ!$K$6:$K$9,速報_原データ!$I$6:$I$9,EDATE($A14,12),速報_原データ!$J$6:$J$9,H$3)/100),AVERAGE(H13,H15)))) -> 187.63547 | I14: =B14-D14 -> 1670.3271 | J14: =C14-D14-E14-H14 -> 386.1356 | K14: 翌年同月速報の前年比から逆算
A15: 45323 | B15: =IF(COUNTIFS(速報_原データ!$A$5:$A$200,$A15,速報_原データ!$B$5:$B$200,B$3)>0,SUMIFS(速報_原データ!$C$5:$C$200,速報_原データ!$A$5:$A$200,$A15,速報_原データ!$B$5:$B$200,B$3)/100,IF(COUNTIFS(速報_原データ!$A$5:$A$200,EDATE($A15,12),速報_原データ!$B$5:$B$200,B$3)>0,SUMIFS(速報_原データ!$C$5:$C$200,速報_原データ!$A$5:$A$200,EDATE($A15,12),速報_原データ!$B$5:$B$200,B$3)/100/(1+SUMIFS(速報_原データ!$D$5:$D$200,速報_原データ!$A$5:$A$200,EDATE($A15,12),速報_原データ!$B$5:$B$200,B$3)/100),IF(COUNTIFS(速報_原データ!$I$6:$I$9,EDATE($A15,12),速報_原データ!$J$6:$J$9,B$3)>0,B27/(1+SUMIFS(速報_原データ!$K$6:$K$9,速報_原データ!$I$6:$I$9,EDATE($A15,12),速報_原データ!$J$6:$J$9,B$3)/100),AVERAGE(B14,B16)))) -> 3104.3975 | C15: =IF(COUNTIFS(速報_原データ!$A$5:$A$200,$A15,速報_原データ!$B$5:$B$200,C$3)>0,SUMIFS(速報_原データ!$C$5:$C$200,速報_原データ!$A$5:$A$200,$A15,速報_原データ!$B$5:$B$200,C$3)/100,IF(COUNTIFS(速報_原データ!$A$5:$A$200,EDATE($A15,12),速報_原データ!$B$5:$B$200,C$3)>0,SUMIFS(速報_原データ!$C$5:$C$200,速報_原データ!$A$5:$A$200,EDATE($A15,12),速報_原データ!$B$5:$B$200,C$3)/100/(1+SUMIFS(速報_原データ!$D$5:$D$200,速報_原データ!$A$5:$A$200,EDATE($A15,12),速報_原データ!$B$5:$B$200,C$3)/100),IF(COUNTIFS(速報_原データ!$I$6:$I$9,EDATE($A15,12),速報_原データ!$J$6:$J$9,C$3)>0,C27/(1+SUMIFS(速報_原データ!$K$6:$K$9,速報_原データ!$I$6:$I$9,EDATE($A15,12),速報_原データ!$J$6:$J$9,C$3)/100),AVERAGE(C14,C16)))) -> 2612.649 | D15: =IF(COUNTIFS(速報_原データ!$A$5:$A$200,$A15,速報_原データ!$B$5:$B$200,D$3)>0,SUMIFS(速報_原データ!$C$5:$C$200,速報_原データ!$A$5:$A$200,$A15,速報_原データ!$B$5:$B$200,D$3)/100,IF(COUNTIFS(速報_原データ!$A$5:$A$200,EDATE($A15,12),速報_原データ!$B$5:$B$200,D$3)>0,SUMIFS(速報_原データ!$C$5:$C$200,速報_原データ!$A$5:$A$200,EDATE($A15,12),速報_原データ!$B$5:$B$200,D$3)/100/(1+SUMIFS(速報_原データ!$D$5:$D$200,速報_原データ!$A$5:$A$200,EDATE($A15,12),速報_原データ!$B$5:$B$200,D$3)/100),IF(COUNTIFS(速報_原データ!$I$6:$I$9,EDATE($A15,12),速報_原データ!$J$6:$J$9,D$3)>0,D27/(1+SUMIFS(速報_原データ!$K$6:$K$9,速報_原データ!$I$6:$I$9,EDATE($A15,12),速報_原データ!$J$6:$J$9,D$3)/100),AVERAGE(D14,D16)))) -> 1655.8343 | E15: =IF(COUNTIFS(速報_原データ!$A$5:$A$200,$A15,速報_原データ!$B$5:$B$200,E$3)>0,SUMIFS(速報_原データ!$C$5:$C$200,速報_原データ!$A$5:$A$200,$A15,速報_原データ!$B$5:$B$200,E$3)/100,IF(COUNTIFS(速報_原データ!$A$5:$A$200,EDATE($A15,12),速報_原データ!$B$5:$B$200,E$3)>0,SUMIFS(速報_原データ!$C$5:$C$200,速報_原データ!$A$5:$A$200,EDATE($A15,12),速報_原データ!$B$5:$B$200,E$3)/100/(1+SUMIFS(速報_原データ!$D$5:$D$200,速報_原データ!$A$5:$A$200,EDATE($A15,12),速報_原データ!$B$5:$B$200,E$3)/100),IF(COUNTIFS(速報_原データ!$I$6:$I$9,EDATE($A15,12),速報_原データ!$J$6:$J$9,E$3)>0,E27/(1+SUMIFS(速報_原データ!$K$6:$K$9,速報_原データ!$I$6:$I$9,EDATE($A15,12),速報_原データ!$J$6:$J$9,E$3)/100),AVERAGE(E14,E16)))) -> 487.67629 | F15: =IF(COUNTIFS(速報_原データ!$A$5:$A$200,$A15,速報_原データ!$B$5:$B$200,F$3)>0,SUMIFS(速報_原データ!$C$5:$C$200,速報_原データ!$A$5:$A$200,$A15,速報_原データ!$B$5:$B$200,F$3)/100,IF(COUNTIFS(速報_原データ!$A$5:$A$200,EDATE($A15,12),速報_原データ!$B$5:$B$200,F$3)>0,SUMIFS(速報_原データ!$C$5:$C$200,速報_原データ!$A$5:$A$200,EDATE($A15,12),速報_原データ!$B$5:$B$200,F$3)/100/(1+SUMIFS(速報_原データ!$D$5:$D$200,速報_原データ!$A$5:$A$200,EDATE($A15,12),速報_原データ!$B$5:$B$200,F$3)/100),IF(COUNTIFS(速報_原データ!$I$6:$I$9,EDATE($A15,12),速報_原データ!$J$6:$J$9,F$3)>0,F27/(1+SUMIFS(速報_原データ!$K$6:$K$9,速報_原データ!$I$6:$I$9,EDATE($A15,12),速報_原データ!$J$6:$J$9,F$3)/100),AVERAGE(F14,F16)))) -> 360.67278 | G15: =IF(COUNTIFS(速報_原データ!$A$5:$A$200,$A15,速報_原データ!$B$5:$B$200,G$3)>0,SUMIFS(速報_原データ!$C$5:$C$200,速報_原データ!$A$5:$A$200,$A15,速報_原データ!$B$5:$B$200,G$3)/100,IF(COUNTIFS(速報_原データ!$A$5:$A$200,EDATE($A15,12),速報_原データ!$B$5:$B$200,G$3)>0,SUMIFS(速報_原データ!$C$5:$C$200,速報_原データ!$A$5:$A$200,EDATE($A15,12),速報_原データ!$B$5:$B$200,G$3)/100/(1+SUMIFS(速報_原データ!$D$5:$D$200,速報_原データ!$A$5:$A$200,EDATE($A15,12),速報_原データ!$B$5:$B$200,G$3)/100),IF(COUNTIFS(速報_原データ!$I$6:$I$9,EDATE($A15,12),速報_原データ!$J$6:$J$9,G$3)>0,G27/(1+SUMIFS(速報_原データ!$K$6:$K$9,速報_原データ!$I$6:$I$9,EDATE($A15,12),速報_原データ!$J$6:$J$9,G$3)/100),AVERAGE(G14,G16)))) -> 126.60848 | H15: =IF(COUNTIFS(速報_原データ!$A$5:$A$200,$A15,速報_原データ!$B$5:$B$200,H$3)>0,SUMIFS(速報_原データ!$C$5:$C$200,速報_原データ!$A$5:$A$200,$A15,速報_原データ!$B$5:$B$200,H$3)/100,IF(COUNTIFS(速報_原データ!$A$5:$A$200,EDATE($A15,12),速報_原データ!$B$5:$B$200,H$3)>0,SUMIFS(速報_原データ!$C$5:$C$200,速報_原データ!$A$5:$A$200,EDATE($A15,12),速報_原データ!$B$5:$B$200,H$3)/100/(1+SUMIFS(速報_原データ!$D$5:$D$200,速報_原データ!$A$5:$A$200,EDATE($A15,12),速報_原データ!$B$5:$B$200,H$3)/100),IF(COUNTIFS(速報_原データ!$I$6:$I$9,EDATE($A15,12),速報_原データ!$J$6:$J$9,H$3)>0,H27/(1+SUMIFS(速報_原データ!$K$6:$K$9,速報_原データ!$I$6:$I$9,EDATE($A15,12),速報_原データ!$J$6:$J$9,H$3)/100),AVERAGE(H14,H16)))) -> 148.75491 | I15: =B15-D15 -> 1448.5632 | J15: =C15-D15-E15-H15 -> 320.38353 | K15: 翌年同月速報の前年比から逆算
A16: 45352 | B16: =IF(COUNTIFS(速報_原データ!$A$5:$A$200,$A16,速報_原データ!$B$5:$B$200,B$3)>0,SUMIFS(速報_原データ!$C$5:$C$200,速報_原データ!$A$5:$A$200,$A16,速報_原データ!$B$5:$B$200,B$3)/100,IF(COUNTIFS(速報_原データ!$A$5:$A$200,EDATE($A16,12),速報_原データ!$B$5:$B$200,B$3)>0,SUMIFS(速報_原データ!$C$5:$C$200,速報_原データ!$A$5:$A$200,EDATE($A16,12),速報_原データ!$B$5:$B$200,B$3)/100/(1+SUMIFS(速報_原データ!$D$5:$D$200,速報_原データ!$A$5:$A$200,EDATE($A16,12),速報_原データ!$B$5:$B$200,B$3)/100),IF(COUNTIFS(速報_原データ!$I$6:$I$9,EDATE($A16,12),速報_原データ!$J$6:$J$9,B$3)>0,B28/(1+SUMIFS(速報_原データ!$K$6:$K$9,速報_原データ!$I$6:$I$9,EDATE($A16,12),速報_原データ!$J$6:$J$9,B$3)/100),AVERAGE(B15,B17)))) -> 4349.2147 | C16: =IF(COUNTIFS(速報_原データ!$A$5:$A$200,$A16,速報_原データ!$B$5:$B$200,C$3)>0,SUMIFS(速報_原データ!$C$5:$C$200,速報_原データ!$A$5:$A$200,$A16,速報_原データ!$B$5:$B$200,C$3)/100,IF(COUNTIFS(速報_原データ!$A$5:$A$200,EDATE($A16,12),速報_原データ!$B$5:$B$200,C$3)>0,SUMIFS(速報_原データ!$C$5:$C$200,速報_原データ!$A$5:$A$200,EDATE($A16,12),速報_原データ!$B$5:$B$200,C$3)/100/(1+SUMIFS(速報_原データ!$D$5:$D$200,速報_原データ!$A$5:$A$200,EDATE($A16,12),速報_原データ!$B$5:$B$200,C$3)/100),IF(COUNTIFS(速報_原データ!$I$6:$I$9,EDATE($A16,12),速報_原データ!$J$6:$J$9,C$3)>0,C28/(1+SUMIFS(速報_原データ!$K$6:$K$9,速報_原データ!$I$6:$I$9,EDATE($A16,12),速報_原データ!$J$6:$J$9,C$3)/100),AVERAGE(C15,C17)))) -> 3731.9686 | D16: =IF(COUNTIFS(速報_原データ!$A$5:$A$200,$A16,速報_原データ!$B$5:$B$200,D$3)>0,SUMIFS(速報_原データ!$C$5:$C$200,速報_原データ!$A$5:$A$200,$A16,速報_原データ!$B$5:$B$200,D$3)/100,IF(COUNTIFS(速報_原データ!$A$5:$A$200,EDATE($A16,12),速報_原データ!$B$5:$B$200,D$3)>0,SUMIFS(速報_原データ!$C$5:$C$200,速報_原データ!$A$5:$A$200,EDATE($A16,12),速報_原データ!$B$5:$B$200,D$3)/100/(1+SUMIFS(速報_原データ!$D$5:$D$200,速報_原データ!$A$5:$A$200,EDATE($A16,12),速報_原データ!$B$5:$B$200,D$3)/100),IF(COUNTIFS(速報_原データ!$I$6:$I$9,EDATE($A16,12),速報_原データ!$J$6:$J$9,D$3)>0,D28/(1+SUMIFS(速報_原データ!$K$6:$K$9,速報_原データ!$I$6:$I$9,EDATE($A16,12),速報_原データ!$J$6:$J$9,D$3)/100),AVERAGE(D15,D17)))) -> 2315.7701 | E16: =IF(COUNTIFS(速報_原データ!$A$5:$A$200,$A16,速報_原データ!$B$5:$B$200,E$3)>0,SUMIFS(速報_原データ!$C$5:$C$200,速報_原データ!$A$5:$A$200,$A16,速報_原データ!$B$5:$B$200,E$3)/100,IF(COUNTIFS(速報_原データ!$A$5:$A$200,EDATE($A16,12),速報_原データ!$B$5:$B$200,E$3)>0,SUMIFS(速報_原データ!$C$5:$C$200,速報_原データ!$A$5:$A$200,EDATE($A16,12),速報_原データ!$B$5:$B$200,E$3)/100/(1+SUMIFS(速報_原データ!$D$5:$D$200,速報_原データ!$A$5:$A$200,EDATE($A16,12),速報_原データ!$B$5:$B$200,E$3)/100),IF(COUNTIFS(速報_原データ!$I$6:$I$9,EDATE($A16,12),速報_原データ!$J$6:$J$9,E$3)>0,E28/(1+SUMIFS(速報_原データ!$K$6:$K$9,速報_原データ!$I$6:$I$9,EDATE($A16,12),速報_原データ!$J$6:$J$9,E$3)/100),AVERAGE(E15,E17)))) -> 603.34139 | F16: =IF(COUNTIFS(速報_原データ!$A$5:$A$200,$A16,速報_原データ!$B$5:$B$200,F$3)>0,SUMIFS(速報_原データ!$C$5:$C$200,速報_原データ!$A$5:$A$200,$A16,速報_原データ!$B$5:$B$200,F$3)/100,IF(COUNTIFS(速報_原データ!$A$5:$A$200,EDATE($A16,12),速報_原データ!$B$5:$B$200,F$3)>0,SUMIFS(速報_原データ!$C$5:$C$200,速報_原データ!$A$5:$A$200,EDATE($A16,12),速報_原データ!$B$5:$B$200,F$3)/100/(1+SUMIFS(速報_原データ!$D$5:$D$200,速報_原データ!$A$5:$A$200,EDATE($A16,12),速報_原データ!$B$5:$B$200,F$3)/100),IF(COUNTIFS(速報_原データ!$I$6:$I$9,EDATE($A16,12),速報_原データ!$J$6:$J$9,F$3)>0,F28/(1+SUMIFS(速報_原データ!$K$6:$K$9,速報_原データ!$I$6:$I$9,EDATE($A16,12),速報_原データ!$J$6:$J$9,F$3)/100),AVERAGE(F15,F17)))) -> 463.94366 | G16: =IF(COUNTIFS(速報_原データ!$A$5:$A$200,$A16,速報_原データ!$B$5:$B$200,G$3)>0,SUMIFS(速報_原データ!$C$5:$C$200,速報_原データ!$A$5:$A$200,$A16,速報_原データ!$B$5:$B$200,G$3)/100,IF(COUNTIFS(速報_原データ!$A$5:$A$200,EDATE($A16,12),速報_原データ!$B$5:$B$200,G$3)>0,SUMIFS(速報_原データ!$C$5:$C$200,速報_原データ!$A$5:$A$200,EDATE($A16,12),速報_原データ!$B$5:$B$200,G$3)/100/(1+SUMIFS(速報_原データ!$D$5:$D$200,速報_原データ!$A$5:$A$200,EDATE($A16,12),速報_原データ!$B$5:$B$200,G$3)/100),IF(COUNTIFS(速報_原データ!$I$6:$I$9,EDATE($A16,12),速報_原データ!$J$6:$J$9,G$3)>0,G28/(1+SUMIFS(速報_原データ!$K$6:$K$9,速報_原データ!$I$6:$I$9,EDATE($A16,12),速報_原データ!$J$6:$J$9,G$3)/100),AVERAGE(G15,G17)))) -> 145.26485 | H16: =IF(COUNTIFS(速報_原データ!$A$5:$A$200,$A16,速報_原データ!$B$5:$B$200,H$3)>0,SUMIFS(速報_原データ!$C$5:$C$200,速報_原データ!$A$5:$A$200,$A16,速報_原データ!$B$5:$B$200,H$3)/100,IF(COUNTIFS(速報_原データ!$A$5:$A$200,EDATE($A16,12),速報_原データ!$B$5:$B$200,H$3)>0,SUMIFS(速報_原データ!$C$5:$C$200,速報_原データ!$A$5:$A$200,EDATE($A16,12),速報_原データ!$B$5:$B$200,H$3)/100/(1+SUMIFS(速報_原データ!$D$5:$D$200,速報_原データ!$A$5:$A$200,EDATE($A16,12),速報_原データ!$B$5:$B$200,H$3)/100),IF(COUNTIFS(速報_原データ!$I$6:$I$9,EDATE($A16,12),速報_原データ!$J$6:$J$9,H$3)>0,H28/(1+SUMIFS(速報_原データ!$K$6:$K$9,速報_原データ!$I$6:$I$9,EDATE($A16,12),速報_原データ!$J$6:$J$9,H$3)/100),AVERAGE(H15,H17)))) -> 191.92568 | I16: =B16-D16 -> 2033.4446 | J16: =C16-D16-E16-H16 -> 620.93141 | K16: 翌年同月速報の前年比から逆算
... A45: 46235 | B45: =IF(COUNTIFS(速報_原データ!$A$5:$A$200,$A45,速報_原データ!$B$5:$B$200,B$3)>0,SUMIFS(速報_原データ!$C$5:$C$200,速報_原データ!$A$5:$A$200,$A45,速報_原データ!$B$5:$B$200,B$3)/100,IF(COUNTIFS(速報_原データ!$A$5:$A$200,EDATE($A45,12),速報_原データ!$B$5:$B$200,B$3)>0,SUMIFS(速報_原データ!$C$5:$C$200,速報_原データ!$A$5:$A$200,EDATE($A45,12),速報_原データ!$B$5:$B$200,B$3)/100/(1+SUMIFS(速報_原データ!$D$5:$D$200,速報_原データ!$A$5:$A$200,EDATE($A45,12),速報_原データ!$B$5:$B$200,B$3)/100),IF(COUNTIFS(速報_原データ!$I$6:$I$9,EDATE($A45,12),速報_原データ!$J$6:$J$9,B$3)>0,B57/(1+SUMIFS(速報_原データ!$K$6:$K$9,速報_原データ!$I$6:$I$9,EDATE($A45,12),速報_原データ!$J$6:$J$9,B$3)/100),AVERAGE(B44,B46)))) -> 4897.64 | C45: =IF(COUNTIFS(速報_原データ!$A$5:$A$200,$A45,速報_原データ!$B$5:$B$200,C$3)>0,SUMIFS(速報_原データ!$C$5:$C$200,速報_原データ!$A$5:$A$200,$A45,速報_原データ!$B$5:$B$200,C$3)/100,IF(COUNTIFS(速報_原データ!$A$5:$A$200,EDATE($A45,12),速報_原データ!$B$5:$B$200,C$3)>0,SUMIFS(速報_原データ!$C$5:$C$200,速報_原データ!$A$5:$A$200,EDATE($A45,12),速報_原データ!$B$5:$B$200,C$3)/100/(1+SUMIFS(速報_原データ!$D$5:$D$200,速報_原データ!$A$5:$A$200,EDATE($A45,12),速報_原データ!$B$5:$B$200,C$3)/100),IF(COUNTIFS(速報_原データ!$I$6:$I$9,EDATE($A45,12),速報_原データ!$J$6:$J$9,C$3)>0,C57/(1+SUMIFS(速報_原データ!$K$6:$K$9,速報_原データ!$I$6:$I$9,EDATE($A45,12),速報_原データ!$J$6:$J$9,C$3)/100),AVERAGE(C44,C46)))) -> 4241.08 | D45: =IF(COUNTIFS(速報_原データ!$A$5:$A$200,$A45,速報_原データ!$B$5:$B$200,D$3)>0,SUMIFS(速報_原データ!$C$5:$C$200,速報_原データ!$A$5:$A$200,$A45,速報_原データ!$B$5:$B$200,D$3)/100,IF(COUNTIFS(速報_原データ!$A$5:$A$200,EDATE($A45,12),速報_原データ!$B$5:$B$200,D$3)>0,SUMIFS(速報_原データ!$C$5:$C$200,速報_原データ!$A$5:$A$200,EDATE($A45,12),速報_原データ!$B$5:$B$200,D$3)/100/(1+SUMIFS(速報_原データ!$D$5:$D$200,速報_原データ!$A$5:$A$200,EDATE($A45,12),速報_原データ!$B$5:$B$200,D$3)/100),IF(COUNTIFS(速報_原データ!$I$6:$I$9,EDATE($A45,12),速報_原データ!$J$6:$J$9,D$3)>0,D57/(1+SUMIFS(速報_原データ!$K$6:$K$9,速報_原データ!$I$6:$I$9,EDATE($A45,12),速報_原データ!$J$6:$J$9,D$3)/100),AVERAGE(D44,D46)))) -> 1947.91 | E45: =IF(COUNTIFS(速報_原データ!$A$5:$A$200,$A45,速報_原データ!$B$5:$B$200,E$3)>0,SUMIFS(速報_原データ!$C$5:$C$200,速報_原データ!$A$5:$A$200,$A45,速報_原データ!$B$5:$B$200,E$3)/100,IF(COUNTIFS(速報_原データ!$A$5:$A$200,EDATE($A45,12),速報_原データ!$B$5:$B$200,E$3)>0,SUMIFS(速報_原データ!$C$5:$C$200,速報_原データ!$A$5:$A$200,EDATE($A45,12),速報_原データ!$B$5:$B$200,E$3)/100/(1+SUMIFS(速報_原データ!$D$5:$D$200,速報_原データ!$A$5:$A$200,EDATE($A45,12),速報_原データ!$B$5:$B$200,E$3)/100),IF(COUNTIFS(速報_原データ!$I$6:$I$9,EDATE($A45,12),速報_原データ!$J$6:$J$9,E$3)>0,E57/(1+SUMIFS(速報_原データ!$K$6:$K$9,速報_原データ!$I$6:$I$9,EDATE($A45,12),速報_原データ!$J$6:$J$9,E$3)/100),AVERAGE(E44,E46)))) -> 850.51 | F45: =IF(COUNTIFS(速報_原データ!$A$5:$A$200,$A45,速報_原データ!$B$5:$B$200,F$3)>0,SUMIFS(速報_原データ!$C$5:$C$200,速報_原データ!$A$5:$A$200,$A45,速報_原データ!$B$5:$B$200,F$3)/100,IF(COUNTIFS(速報_原データ!$A$5:$A$200,EDATE($A45,12),速報_原データ!$B$5:$B$200,F$3)>0,SUMIFS(速報_原データ!$C$5:$C$200,速報_原データ!$A$5:$A$200,EDATE($A45,12),速報_原データ!$B$5:$B$200,F$3)/100/(1+SUMIFS(速報_原データ!$D$5:$D$200,速報_原データ!$A$5:$A$200,EDATE($A45,12),速報_原データ!$B$5:$B$200,F$3)/100),IF(COUNTIFS(速報_原データ!$I$6:$I$9,EDATE($A45,12),速報_原データ!$J$6:$J$9,F$3)>0,F57/(1+SUMIFS(速報_原データ!$K$6:$K$9,速報_原データ!$I$6:$I$9,EDATE($A45,12),速報_原データ!$J$6:$J$9,F$3)/100),AVERAGE(F44,F46)))) -> 484.94 | G45: =IF(COUNTIFS(速報_原データ!$A$5:$A$200,$A45,速報_原データ!$B$5:$B$200,G$3)>0,SUMIFS(速報_原データ!$C$5:$C$200,速報_原データ!$A$5:$A$200,$A45,速報_原データ!$B$5:$B$200,G$3)/100,IF(COUNTIFS(速報_原データ!$A$5:$A$200,EDATE($A45,12),速報_原データ!$B$5:$B$200,G$3)>0,SUMIFS(速報_原データ!$C$5:$C$200,速報_原データ!$A$5:$A$200,EDATE($A45,12),速報_原データ!$B$5:$B$200,G$3)/100/(1+SUMIFS(速報_原データ!$D$5:$D$200,速報_原データ!$A$5:$A$200,EDATE($A45,12),速報_原データ!$B$5:$B$200,G$3)/100),IF(COUNTIFS(速報_原データ!$I$6:$I$9,EDATE($A45,12),速報_原データ!$J$6:$J$9,G$3)>0,G57/(1+SUMIFS(速報_原データ!$K$6:$K$9,速報_原データ!$I$6:$I$9,EDATE($A45,12),速報_原データ!$J$6:$J$9,G$3)/100),AVERAGE(G44,G46)))) -> 135.5 | H45: =IF(COUNTIFS(速報_原データ!$A$5:$A$200,$A45,速報_原データ!$B$5:$B$200,H$3)>0,SUMIFS(速報_原データ!$C$5:$C$200,速報_原データ!$A$5:$A$200,$A45,速報_原データ!$B$5:$B$200,H$3)/100,IF(COUNTIFS(速報_原データ!$A$5:$A$200,EDATE($A45,12),速報_原データ!$B$5:$B$200,H$3)>0,SUMIFS(速報_原データ!$C$5:$C$200,速報_原データ!$A$5:$A$200,EDATE($A45,12),速報_原データ!$B$5:$B$200,H$3)/100/(1+SUMIFS(速報_原データ!$D$5:$D$200,速報_原データ!$A$5:$A$200,EDATE($A45,12),速報_原データ!$B$5:$B$200,H$3)/100),IF(COUNTIFS(速報_原データ!$I$6:$I$9,EDATE($A45,12),速報_原データ!$J$6:$J$9,H$3)>0,H57/(1+SUMIFS(速報_原データ!$K$6:$K$9,速報_原データ!$I$6:$I$9,EDATE($A45,12),速報_原データ!$J$6:$J$9,H$3)/100),AVERAGE(H44,H46)))) -> 356.47 | I45: =B45-D45 -> 2949.73 | J45: =C45-D45-E45-H45 -> 1086.19 | K45: 当月速報

Sheet KOKUSAI_四半期
A1: KOKUSAI ELECTRIC（6525）四半期売上収益（億円）
A2: 青字＝決算説明資料からの転記。27/3期から装置・サービスの区分基準が変更されたため、1Qの内訳は空欄。
A4: 四半期 | B4: 期間 | C4: 期末月 | D4: 売上収益 | E4: 装置（旧基準） | F4: サービス（旧基準） | G4: 中国地場比率 | H4: 中国地場売上 | I4: グローバル売上
A5: 24/3期 1Q | B5: 2023年4-6月 | C5: 45078 | D5: 327 | E5: 185 | F5: 142 | G5: 0.29 | H5: =D5*G5 -> 94.83 | I5: =D5-H5 -> 232.17
A6: 24/3期 2Q | B6: 2023年7-9月 | C6: 45170 | D6: 450 | E6: 262 | F6: 188 | G6: 0.49 | H6: =D6*G6 -> 220.5 | I6: =D6-H6 -> 229.5
A7: 24/3期 3Q | B7: 2023年10-12月 | C7: 45261 | D7: 540 | E7: 375 | F7: 164 | G7: 0.45 | H7: =D7*G7 -> 243 | I7: =D7-H7 -> 297
A8: 24/3期 4Q | B8: 2024年1-3月 | C8: 45352 | D8: 492 | E8: 361 | F8: 131 | G8: 0.5 | H8: =D8*G8 -> 246 | I8: =D8-H8 -> 246
A9: 25/3期 1Q | B9: 2024年4-6月 | C9: 45444 | D9: 652 | E9: 439 | F9: 214 | G9: 0.5 | H9: =D9*G9 -> 326 | I9: =D9-H9 -> 326
A10: 25/3期 2Q | B10: 2024年7-9月 | C10: 45536 | D10: 493 | E10: 315 | F10: 179 | G10: 0.44 | H10: =D10*G10 -> 216.92 | I10: =D10-H10 -> 276.08
A11: 25/3期 3Q | B11: 2024年10-12月 | C11: 45627 | D11: 601 | E11: 420 | F11: 182 | G11: 0.4 | H11: =D11*G11 -> 240.4 | I11: =D11-H11 -> 360.6
A12: 25/3期 4Q | B12: 2025年1-3月 | C12: 45717 | D12: 643 | E12: 470 | F12: 173 | G12: 0.41 | H12: =D12*G12 -> 263.63 | I12: =D12-H12 -> 379.37
A13: 26/3期 1Q | B13: 2025年4-6月 | C13: 45809 | D13: 518 | E13: 317 | F13: 201 | G13: 0.38 | H13: =D13*G13 -> 196.84 | I13: =D13-H13 -> 321.16
A14: 26/3期 2Q | B14: 2025年7-9月 | C14: 45901 | D14: 654 | E14: 416 | F14: 239 | G14: 0.44 | H14: =D14*G14 -> 287.76 | I14: =D14-H14 -> 366.24
A15: 26/3期 3Q | B15: 2025年10-12月 | C15: 45992 | D15: 559 | E15: 313 | F15: 246 | G15: 0.31 | H15: =D15*G15 -> 173.29 | I15: =D15-H15 -> 385.71
A16: 26/3期 4Q | B16: 2026年1-3月 | C16: 46082 | D16: 620 | E16: 355 | F16: 266 | G16: 0.26 | H16: =D16*G16 -> 161.2 | I16: =D16-H16 -> 458.8
A17: 27/3期 1Q | B17: 2026年4-6月 | C17: 46174 | D17: 754 | G17: 0.25 | H17: =D17*G17 -> 188.5 | I17: =D17-H17 -> 565.5
A19: 出所: 24/3期〜25/3期は25/3期決算説明資料、26/3期は26/3期決算説明資料、27/3期1Qは決算報道（売上754億円、中国地場25％）。
A20: 中国地場比率は会社開示の四半期比率を全社売上に掛けて金額化した近似（比率の母数が装置売上である場合は過大）。

Sheet 四半期集計
A1: 四半期ごとの輸出額（億円）— 期末月からkか月ずらした3か月合計
A2: k＝輸出（通関）が売上計上に先行する月数。k=1なら、7-9月期に6-8月の輸出を対応させる。
D3: k = | E3: 0 | F3: （k=0：同じ3か月） | I3: k = | J3: 1 | K3: （k=1：1か月先行）
A4: 四半期 | B4: 期末月 | C4: 売上収益 | D4: 世界 | E4: 中国 | F4: 中国以外 | G4: 韓国 | H4: 実質シェア | I4: 世界 | J4: 中国 | K4: 中国以外 | L4: 韓国 | M4: 実質シェア
A6: 24/3期 1Q | B6: =KOKUSAI_四半期!C5 -> 45078 | C6: =KOKUSAI_四半期!D5 -> 327 | D6: =IF(COUNTIFS(貿易_月次!$A$5:$A$45,">="&EDATE($B6,-2-$E$3),貿易_月次!$A$5:$A$45,"<="&EDATE($B6,-$E$3))=3,SUMIFS(貿易_月次!$B$5:$B$45,貿易_月次!$A$5:$A$45,">="&EDATE($B6,-2-$E$3),貿易_月次!$A$5:$A$45,"<="&EDATE($B6,-$E$3)),"") -> 8184.9395 | E6: =IF(COUNTIFS(貿易_月次!$A$5:$A$45,">="&EDATE($B6,-2-$E$3),貿易_月次!$A$5:$A$45,"<="&EDATE($B6,-$E$3))=3,SUMIFS(貿易_月次!$D$5:$D$45,貿易_月次!$A$5:$A$45,">="&EDATE($B6,-2-$E$3),貿易_月次!$A$5:$A$45,"<="&EDATE($B6,-$E$3)),"") -> 3087.3402 | F6: =IF(COUNTIFS(貿易_月次!$A$5:$A$45,">="&EDATE($B6,-2-$E$3),貿易_月次!$A$5:$A$45,"<="&EDATE($B6,-$E$3))=3,SUMIFS(貿易_月次!$I$5:$I$45,貿易_月次!$A$5:$A$45,">="&EDATE($B6,-2-$E$3),貿易_月次!$A$5:$A$45,"<="&EDATE($B6,-$E$3)),"") -> 5097.5993 | G6: =IF(COUNTIFS(貿易_月次!$A$5:$A$45,">="&EDATE($B6,-2-$E$3),貿易_月次!$A$5:$A$45,"<="&EDATE($B6,-$E$3))=3,SUMIFS(貿易_月次!$E$5:$E$45,貿易_月次!$A$5:$A$45,">="&EDATE($B6,-2-$E$3),貿易_月次!$A$5:$A$45,"<="&EDATE($B6,-$E$3)),"") -> 1436.5991 | H6: =IF(AND(ISNUMBER(C6),ISNUMBER(D6)),C6/D6,"") -> 0.039951425 | I6: =IF(COUNTIFS(貿易_月次!$A$5:$A$45,">="&EDATE($B6,-2-$J$3),貿易_月次!$A$5:$A$45,"<="&EDATE($B6,-$J$3))=3,SUMIFS(貿易_月次!$B$5:$B$45,貿易_月次!$A$5:$A$45,">="&EDATE($B6,-2-$J$3),貿易_月次!$A$5:$A$45,"<="&EDATE($B6,-$J$3)),"") | J6: =IF(COUNTIFS(貿易_月次!$A$5:$A$45,">="&EDATE($B6,-2-$J$3),貿易_月次!$A$5:$A$45,"<="&EDATE($B6,-$J$3))=3,SUMIFS(貿易_月次!$D$5:$D$45,貿易_月次!$A$5:$A$45,">="&EDATE($B6,-2-$J$3),貿易_月次!$A$5:$A$45,"<="&EDATE($B6,-$J$3)),"") | K6: =IF(COUNTIFS(貿易_月次!$A$5:$A$45,">="&EDATE($B6,-2-$J$3),貿易_月次!$A$5:$A$45,"<="&EDATE($B6,-$J$3))=3,SUMIFS(貿易_月次!$I$5:$I$45,貿易_月次!$A$5:$A$45,">="&EDATE($B6,-2-$J$3),貿易_月次!$A$5:$A$45,"<="&EDATE($B6,-$J$3)),"") | L6: =IF(COUNTIFS(貿易_月次!$A$5:$A$45,">="&EDATE($B6,-2-$J$3),貿易_月次!$A$5:$A$45,"<="&EDATE($B6,-$J$3))=3,SUMIFS(貿易_月次!$E$5:$E$45,貿易_月次!$A$5:$A$45,">="&EDATE($B6,-2-$J$3),貿易_月次!$A$5:$A$45,"<="&EDATE($B6,-$J$3)),"") | M6: =IF(AND(ISNUMBER(C6),ISNUMBER(I6)),C6/I6,"")
A7: 24/3期 2Q | B7: =KOKUSAI_四半期!C6 -> 45170 | C7: =KOKUSAI_四半期!D6 -> 450 | D7: =IF(COUNTIFS(貿易_月次!$A$5:$A$45,">="&EDATE($B7,-2-$E$3),貿易_月次!$A$5:$A$45,"<="&EDATE($B7,-$E$3))=3,SUMIFS(貿易_月次!$B$5:$B$45,貿易_月次!$A$5:$A$45,">="&EDATE($B7,-2-$E$3),貿易_月次!$A$5:$A$45,"<="&EDATE($B7,-$E$3)),"") -> 8236.8411 | E7: =IF(COUNTIFS(貿易_月次!$A$5:$A$45,">="&EDATE($B7,-2-$E$3),貿易_月次!$A$5:$A$45,"<="&EDATE($B7,-$E$3))=3,SUMIFS(貿易_月次!$D$5:$D$45,貿易_月次!$A$5:$A$45,">="&EDATE($B7,-2-$E$3),貿易_月次!$A$5:$A$45,"<="&EDATE($B7,-$E$3)),"") -> 4185.4136 | F7: =IF(COUNTIFS(貿易_月次!$A$5:$A$45,">="&EDATE($B7,-2-$E$3),貿易_月次!$A$5:$A$45,"<="&EDATE($B7,-$E$3))=3,SUMIFS(貿易_月次!$I$5:$I$45,貿易_月次!$A$5:$A$45,">="&EDATE($B7,-2-$E$3),貿易_月次!$A$5:$A$45,"<="&EDATE($B7,-$E$3)),"") -> 4051.4275 | G7: =IF(COUNTIFS(貿易_月次!$A$5:$A$45,">="&EDATE($B7,-2-$E$3),貿易_月次!$A$5:$A$45,"<="&EDATE($B7,-$E$3))=3,SUMIFS(貿易_月次!$E$5:$E$45,貿易_月次!$A$5:$A$45,">="&EDATE($B7,-2-$E$3),貿易_月次!$A$5:$A$45,"<="&EDATE($B7,-$E$3)),"") -> 1177.5128 | H7: =IF(AND(ISNUMBER(C7),ISNUMBER(D7)),C7/D7,"") -> 0.054632595 | I7: =IF(COUNTIFS(貿易_月次!$A$5:$A$45,">="&EDATE($B7,-2-$J$3),貿易_月次!$A$5:$A$45,"<="&EDATE($B7,-$J$3))=3,SUMIFS(貿易_月次!$B$5:$B$45,貿易_月次!$A$5:$A$45,">="&EDATE($B7,-2-$J$3),貿易_月次!$A$5:$A$45,"<="&EDATE($B7,-$J$3)),"") -> 7973.4192 | J7: =IF(COUNTIFS(貿易_月次!$A$5:$A$45,">="&EDATE($B7,-2-$J$3),貿易_月次!$A$5:$A$45,"<="&EDATE($B7,-$J$3))=3,SUMIFS(貿易_月次!$D$5:$D$45,貿易_月次!$A$5:$A$45,">="&EDATE($B7,-2-$J$3),貿易_月次!$A$5:$A$45,"<="&EDATE($B7,-$J$3)),"") -> 3822.5961 | K7: =IF(COUNTIFS(貿易_月次!$A$5:$A$45,">="&EDATE($B7,-2-$J$3),貿易_月次!$A$5:$A$45,"<="&EDATE($B7,-$J$3))=3,SUMIFS(貿易_月次!$I$5:$I$45,貿易_月次!$A$5:$A$45,">="&EDATE($B7,-2-$J$3),貿易_月次!$A$5:$A$45,"<="&EDATE($B7,-$J$3)),"") -> 4150.8232 | L7: =IF(COUNTIFS(貿易_月次!$A$5:$A$45,">="&EDATE($B7,-2-$J$3),貿易_月次!$A$5:$A$45,"<="&EDATE($B7,-$J$3))=3,SUMIFS(貿易_月次!$E$5:$E$45,貿易_月次!$A$5:$A$45,">="&EDATE($B7,-2-$J$3),貿易_月次!$A$5:$A$45,"<="&EDATE($B7,-$J$3)),"") -> 1236.1341 | M7: =IF(AND(ISNUMBER(C7),ISNUMBER(I7)),C7/I7,"") -> 0.056437519
A8: 24/3期 3Q | B8: =KOKUSAI_四半期!C7 -> 45261 | C8: =KOKUSAI_四半期!D7 -> 540 | D8: =IF(COUNTIFS(貿易_月次!$A$5:$A$45,">="&EDATE($B8,-2-$E$3),貿易_月次!$A$5:$A$45,"<="&EDATE($B8,-$E$3))=3,SUMIFS(貿易_月次!$B$5:$B$45,貿易_月次!$A$5:$A$45,">="&EDATE($B8,-2-$E$3),貿易_月次!$A$5:$A$45,"<="&EDATE($B8,-$E$3)),"") -> 9763.3206 | E8: =IF(COUNTIFS(貿易_月次!$A$5:$A$45,">="&EDATE($B8,-2-$E$3),貿易_月次!$A$5:$A$45,"<="&EDATE($B8,-$E$3))=3,SUMIFS(貿易_月次!$D$5:$D$45,貿易_月次!$A$5:$A$45,">="&EDATE($B8,-2-$E$3),貿易_月次!$A$5:$A$45,"<="&EDATE($B8,-$E$3)),"") -> 5178.9518 | F8: =IF(COUNTIFS(貿易_月次!$A$5:$A$45,">="&EDATE($B8,-2-$E$3),貿易_月次!$A$5:$A$45,"<="&EDATE($B8,-$E$3))=3,SUMIFS(貿易_月次!$I$5:$I$45,貿易_月次!$A$5:$A$45,">="&EDATE($B8,-2-$E$3),貿易_月次!$A$5:$A$45,"<="&EDATE($B8,-$E$3)),"") -> 4584.3688 | G8: =IF(COUNTIFS(貿易_月次!$A$5:$A$45,">="&EDATE($B8,-2-$E$3),貿易_月次!$A$5:$A$45,"<="&EDATE($B8,-$E$3))=3,SUMIFS(貿易_月次!$E$5:$E$45,貿易_月次!$A$5:$A$45,">="&EDATE($B8,-2-$E$3),貿易_月次!$A$5:$A$45,"<="&EDATE($B8,-$E$3)),"") -> 1149.2897 | H8: =IF(AND(ISNUMBER(C8),ISNUMBER(D8)),C8/D8,"") -> 0.055309051 | I8: =IF(COUNTIFS(貿易_月次!$A$5:$A$45,">="&EDATE($B8,-2-$J$3),貿易_月次!$A$5:$A$45,"<="&EDATE($B8,-$J$3))=3,SUMIFS(貿易_月次!$B$5:$B$45,貿易_月次!$A$5:$A$45,">="&EDATE($B8,-2-$J$3),貿易_月次!$A$5:$A$45,"<="&EDATE($B8,-$J$3)),"") -> 8835.7681 | J8: =IF(COUNTIFS(貿易_月次!$A$5:$A$45,">="&EDATE($B8,-2-$J$3),貿易_月次!$A$5:$A$45,"<="&EDATE($B8,-$J$3))=3,SUMIFS(貿易_月次!$D$5:$D$45,貿易_月次!$A$5:$A$45,">="&EDATE($B8,-2-$J$3),貿易_月次!$A$5:$A$45,"<="&EDATE($B8,-$J$3)),"") -> 4621.5038 | K8: =IF(COUNTIFS(貿易_月次!$A$5:$A$45,">="&EDATE($B8,-2-$J$3),貿易_月次!$A$5:$A$45,"<="&EDATE($B8,-$J$3))=3,SUMIFS(貿易_月次!$I$5:$I$45,貿易_月次!$A$5:$A$45,">="&EDATE($B8,-2-$J$3),貿易_月次!$A$5:$A$45,"<="&EDATE($B8,-$J$3)),"") -> 4214.2643 | L8: =IF(COUNTIFS(貿易_月次!$A$5:$A$45,">="&EDATE($B8,-2-$J$3),貿易_月次!$A$5:$A$45,"<="&EDATE($B8,-$J$3))=3,SUMIFS(貿易_月次!$E$5:$E$45,貿易_月次!$A$5:$A$45,">="&EDATE($B8,-2-$J$3),貿易_月次!$A$5:$A$45,"<="&EDATE($B8,-$J$3)),"") -> 1018.9272 | M8: =IF(AND(ISNUMBER(C8),ISNUMBER(I8)),C8/I8,"") -> 0.06111523
A9: 24/3期 4Q | B9: =KOKUSAI_四半期!C8 -> 45352 | C9: =KOKUSAI_四半期!D8 -> 492 | D9: =IF(COUNTIFS(貿易_月次!$A$5:$A$45,">="&EDATE($B9,-2-$E$3),貿易_月次!$A$5:$A$45,"<="&EDATE($B9,-$E$3))=3,SUMIFS(貿易_月次!$B$5:$B$45,貿易_月次!$A$5:$A$45,">="&EDATE($B9,-2-$E$3),貿易_月次!$A$5:$A$45,"<="&EDATE($B9,-$E$3)),"") -> 10364.937 | E9: =IF(COUNTIFS(貿易_月次!$A$5:$A$45,">="&EDATE($B9,-2-$E$3),貿易_月次!$A$5:$A$45,"<="&EDATE($B9,-$E$3))=3,SUMIFS(貿易_月次!$D$5:$D$45,貿易_月次!$A$5:$A$45,">="&EDATE($B9,-2-$E$3),貿易_月次!$A$5:$A$45,"<="&EDATE($B9,-$E$3)),"") -> 5212.6018 | F9: =IF(COUNTIFS(貿易_月次!$A$5:$A$45,">="&EDATE($B9,-2-$E$3),貿易_月次!$A$5:$A$45,"<="&EDATE($B9,-$E$3))=3,SUMIFS(貿易_月次!$I$5:$I$45,貿易_月次!$A$5:$A$45,">="&EDATE($B9,-2-$E$3),貿易_月次!$A$5:$A$45,"<="&EDATE($B9,-$E$3)),"") -> 5152.3349 | G9: =IF(COUNTIFS(貿易_月次!$A$5:$A$45,">="&EDATE($B9,-2-$E$3),貿易_月次!$A$5:$A$45,"<="&EDATE($B9,-$E$3))=3,SUMIFS(貿易_月次!$E$5:$E$45,貿易_月次!$A$5:$A$45,">="&EDATE($B9,-2-$E$3),貿易_月次!$A$5:$A$45,"<="&EDATE($B9,-$E$3)),"") -> 1689.6212 | H9: =IF(AND(ISNUMBER(C9),ISNUMBER(D9)),C9/D9,"") -> 0.047467728 | I9: =IF(COUNTIFS(貿易_月次!$A$5:$A$45,">="&EDATE($B9,-2-$J$3),貿易_月次!$A$5:$A$45,"<="&EDATE($B9,-$J$3))=3,SUMIFS(貿易_月次!$B$5:$B$45,貿易_月次!$A$5:$A$45,">="&EDATE($B9,-2-$J$3),貿易_月次!$A$5:$A$45,"<="&EDATE($B9,-$J$3)),"") -> 10086.798 | J9: =IF(COUNTIFS(貿易_月次!$A$5:$A$45,">="&EDATE($B9,-2-$J$3),貿易_月次!$A$5:$A$45,"<="&EDATE($B9,-$J$3))=3,SUMIFS(貿易_月次!$D$5:$D$45,貿易_月次!$A$5:$A$45,">="&EDATE($B9,-2-$J$3),貿易_月次!$A$5:$A$45,"<="&EDATE($B9,-$J$3)),"") -> 5120.9835 | K9: =IF(COUNTIFS(貿易_月次!$A$5:$A$45,">="&EDATE($B9,-2-$J$3),貿易_月次!$A$5:$A$45,"<="&EDATE($B9,-$J$3))=3,SUMIFS(貿易_月次!$I$5:$I$45,貿易_月次!$A$5:$A$45,">="&EDATE($B9,-2-$J$3),貿易_月次!$A$5:$A$45,"<="&EDATE($B9,-$J$3)),"") -> 4965.8145 | L9: =IF(COUNTIFS(貿易_月次!$A$5:$A$45,">="&EDATE($B9,-2-$J$3),貿易_月次!$A$5:$A$45,"<="&EDATE($B9,-$J$3))=3,SUMIFS(貿易_月次!$E$5:$E$45,貿易_月次!$A$5:$A$45,">="&EDATE($B9,-2-$J$3),貿易_月次!$A$5:$A$45,"<="&EDATE($B9,-$J$3)),"") -> 1663.1233 | M9: =IF(AND(ISNUMBER(C9),ISNUMBER(I9)),C9/I9,"") -> 0.048776629
A10: 25/3期 1Q | B10: =KOKUSAI_四半期!C9 -> 45444 | C10: =KOKUSAI_四半期!D9 -> 652 | D10: =IF(COUNTIFS(貿易_月次!$A$5:$A$45,">="&EDATE($B10,-2-$E$3),貿易_月次!$A$5:$A$45,"<="&EDATE($B10,-$E$3))=3,SUMIFS(貿易_月次!$B$5:$B$45,貿易_月次!$A$5:$A$45,">="&EDATE($B10,-2-$E$3),貿易_月次!$A$5:$A$45,"<="&EDATE($B10,-$E$3)),"") -> 11188.098 | E10: =IF(COUNTIFS(貿易_月次!$A$5:$A$45,">="&EDATE($B10,-2-$E$3),貿易_月次!$A$5:$A$45,"<="&EDATE($B10,-$E$3))=3,SUMIFS(貿易_月次!$D$5:$D$45,貿易_月次!$A$5:$A$45,">="&EDATE($B10,-2-$E$3),貿易_月次!$A$5:$A$45,"<="&EDATE($B10,-$E$3)),"") -> 5699.0722 | F10: =IF(COUNTIFS(貿易_月次!$A$5:$A$45,">="&EDATE($B10,-2-$E$3),貿易_月次!$A$5:$A$45,"<="&EDATE($B10,-$E$3))=3,SUMIFS(貿易_月次!$I$5:$I$45,貿易_月次!$A$5:$A$45,">="&EDATE($B10,-2-$E$3),貿易_月次!$A$5:$A$45,"<="&EDATE($B10,-$E$3)),"") -> 5489.0256 | G10: =IF(COUNTIFS(貿易_月次!$A$5:$A$45,">="&EDATE($B10,-2-$E$3),貿易_月次!$A$5:$A$45,"<="&EDATE($B10,-$E$3))=3,SUMIFS(貿易_月次!$E$5:$E$45,貿易_月次!$A$5:$A$45,">="&EDATE($B10,-2-$E$3),貿易_月次!$A$5:$A$45,"<="&EDATE($B10,-$E$3)),"") -> 1384.3523 | H10: =IF(AND(ISNUMBER(C10),ISNUMBER(D10)),C10/D10,"") -> 0.058276216 | I10: =IF(COUNTIFS(貿易_月次!$A$5:$A$45,">="&EDATE($B10,-2-$J$3),貿易_月次!$A$5:$A$45,"<="&EDATE($B10,-$J$3))=3,SUMIFS(貿易_月次!$B$5:$B$45,貿易_月次!$A$5:$A$45,">="&EDATE($B10,-2-$J$3),貿易_月次!$A$5:$A$45,"<="&EDATE($B10,-$J$3)),"") -> 11565.652 | J10: =IF(COUNTIFS(貿易_月次!$A$5:$A$45,">="&EDATE($B10,-2-$J$3),貿易_月次!$A$5:$A$45,"<="&EDATE($B10,-$J$3))=3,SUMIFS(貿易_月次!$D$5:$D$45,貿易_月次!$A$5:$A$45,">="&EDATE($B10,-2-$J$3),貿易_月次!$A$5:$A$45,"<="&EDATE($B10,-$J$3)),"") -> 6089.0022 | K10: =IF(COUNTIFS(貿易_月次!$A$5:$A$45,">="&EDATE($B10,-2-$J$3),貿易_月次!$A$5:$A$45,"<="&EDATE($B10,-$J$3))=3,SUMIFS(貿易_月次!$I$5:$I$45,貿易_月次!$A$5:$A$45,">="&EDATE($B10,-2-$J$3),貿易_月次!$A$5:$A$45,"<="&EDATE($B10,-$J$3)),"") -> 5476.6502 | L10: =IF(COUNTIFS(貿易_月次!$A$5:$A$45,">="&EDATE($B10,-2-$J$3),貿易_月次!$A$5:$A$45,"<="&EDATE($B10,-$J$3))=3,SUMIFS(貿易_月次!$E$5:$E$45,貿易_月次!$A$5:$A$45,">="&EDATE($B10,-2-$J$3),貿易_月次!$A$5:$A$45,"<="&EDATE($B10,-$J$3)),"") -> 1444.2037 | M10: =IF(AND(ISNUMBER(C10),ISNUMBER(I10)),C10/I10,"") -> 0.056373819
A11: 25/3期 2Q | B11: =KOKUSAI_四半期!C10 -> 45536 | C11: =KOKUSAI_四半期!D10 -> 493 | D11: =IF(COUNTIFS(貿易_月次!$A$5:$A$45,">="&EDATE($B11,-2-$E$3),貿易_月次!$A$5:$A$45,"<="&EDATE($B11,-$E$3))=3,SUMIFS(貿易_月次!$B$5:$B$45,貿易_月次!$A$5:$A$45,">="&EDATE($B11,-2-$E$3),貿易_月次!$A$5:$A$45,"<="&EDATE($B11,-$E$3)),"") -> 11084.95 | E11: =IF(COUNTIFS(貿易_月次!$A$5:$A$45,">="&EDATE($B11,-2-$E$3),貿易_月次!$A$5:$A$45,"<="&EDATE($B11,-$E$3))=3,SUMIFS(貿易_月次!$D$5:$D$45,貿易_月次!$A$5:$A$45,">="&EDATE($B11,-2-$E$3),貿易_月次!$A$5:$A$45,"<="&EDATE($B11,-$E$3)),"") -> 5384.56 | F11: =IF(COUNTIFS(貿易_月次!$A$5:$A$45,">="&EDATE($B11,-2-$E$3),貿易_月次!$A$5:$A$45,"<="&EDATE($B11,-$E$3))=3,SUMIFS(貿易_月次!$I$5:$I$45,貿易_月次!$A$5:$A$45,">="&EDATE($B11,-2-$E$3),貿易_月次!$A$5:$A$45,"<="&EDATE($B11,-$E$3)),"") -> 5700.39 | G11: =IF(COUNTIFS(貿易_月次!$A$5:$A$45,">="&EDATE($B11,-2-$E$3),貿易_月次!$A$5:$A$45,"<="&EDATE($B11,-$E$3))=3,SUMIFS(貿易_月次!$E$5:$E$45,貿易_月次!$A$5:$A$45,">="&EDATE($B11,-2-$E$3),貿易_月次!$A$5:$A$45,"<="&EDATE($B11,-$E$3)),"") -> 1441.57 | H11: =IF(AND(ISNUMBER(C11),ISNUMBER(D11)),C11/D11,"") -> 0.044474716 | I11: =IF(COUNTIFS(貿易_月次!$A$5:$A$45,">="&EDATE($B11,-2-$J$3),貿易_月次!$A$5:$A$45,"<="&EDATE($B11,-$J$3))=3,SUMIFS(貿易_月次!$B$5:$B$45,貿易_月次!$A$5:$A$45,">="&EDATE($B11,-2-$J$3),貿易_月次!$A$5:$A$45,"<="&EDATE($B11,-$J$3)),"") -> 11086.34 | J11: =IF(COUNTIFS(貿易_月次!$A$5:$A$45,">="&EDATE($B11,-2-$J$3),貿易_月次!$A$5:$A$45,"<="&EDATE($B11,-$J$3))=3,SUMIFS(貿易_月次!$D$5:$D$45,貿易_月次!$A$5:$A$45,">="&EDATE($B11,-2-$J$3),貿易_月次!$A$5:$A$45,"<="&EDATE($B11,-$J$3)),"") -> 5363.69 | K11: =IF(COUNTIFS(貿易_月次!$A$5:$A$45,">="&EDATE($B11,-2-$J$3),貿易_月次!$A$5:$A$45,"<="&EDATE($B11,-$J$3))=3,SUMIFS(貿易_月次!$I$5:$I$45,貿易_月次!$A$5:$A$45,">="&EDATE($B11,-2-$J$3),貿易_月次!$A$5:$A$45,"<="&EDATE($B11,-$J$3)),"") -> 5722.65 | L11: =IF(COUNTIFS(貿易_月次!$A$5:$A$45,">="&EDATE($B11,-2-$J$3),貿易_月次!$A$5:$A$45,"<="&EDATE($B11,-$J$3))=3,SUMIFS(貿易_月次!$E$5:$E$45,貿易_月次!$A$5:$A$45,">="&EDATE($B11,-2-$J$3),貿易_月次!$A$5:$A$45,"<="&EDATE($B11,-$J$3)),"") -> 1504.2 | M11: =IF(AND(ISNUMBER(C11),ISNUMBER(I11)),C11/I11,"") -> 0.044469139
A12: 25/3期 3Q | B12: =KOKUSAI_四半期!C11 -> 45627 | C12: =KOKUSAI_四半期!D11 -> 601 | D12: =IF(COUNTIFS(貿易_月次!$A$5:$A$45,">="&EDATE($B12,-2-$E$3),貿易_月次!$A$5:$A$45,"<="&EDATE($B12,-$E$3))=3,SUMIFS(貿易_月次!$B$5:$B$45,貿易_月次!$A$5:$A$45,">="&EDATE($B12,-2-$E$3),貿易_月次!$A$5:$A$45,"<="&EDATE($B12,-$E$3)),"") -> 12322.19 | E12: =IF(COUNTIFS(貿易_月次!$A$5:$A$45,">="&EDATE($B12,-2-$E$3),貿易_月次!$A$5:$A$45,"<="&EDATE($B12,-$E$3))=3,SUMIFS(貿易_月次!$D$5:$D$45,貿易_月次!$A$5:$A$45,">="&EDATE($B12,-2-$E$3),貿易_月次!$A$5:$A$45,"<="&EDATE($B12,-$E$3)),"") -> 5474.59 | F12: =IF(COUNTIFS(貿易_月次!$A$5:$A$45,">="&EDATE($B12,-2-$E$3),貿易_月次!$A$5:$A$45,"<="&EDATE($B12,-$E$3))=3,SUMIFS(貿易_月次!$I$5:$I$45,貿易_月次!$A$5:$A$45,">="&EDATE($B12,-2-$E$3),貿易_月次!$A$5:$A$45,"<="&EDATE($B12,-$E$3)),"") -> 6847.6 | G12: =IF(COUNTIFS(貿易_月次!$A$5:$A$45,">="&EDATE($B12,-2-$E$3),貿易_月次!$A$5:$A$45,"<="&EDATE($B12,-$E$3))=3,SUMIFS(貿易_月次!$E$5:$E$45,貿易_月次!$A$5:$A$45,">="&EDATE($B12,-2-$E$3),貿易_月次!$A$5:$A$45,"<="&EDATE($B12,-$E$3)),"") -> 1880.28 | H12: =IF(AND(ISNUMBER(C12),ISNUMBER(D12)),C12/D12,"") -> 0.048773798 | I12: =IF(COUNTIFS(貿易_月次!$A$5:$A$45,">="&EDATE($B12,-2-$J$3),貿易_月次!$A$5:$A$45,"<="&EDATE($B12,-$J$3))=3,SUMIFS(貿易_月次!$B$5:$B$45,貿易_月次!$A$5:$A$45,">="&EDATE($B12,-2-$J$3),貿易_月次!$A$5:$A$45,"<="&EDATE($B12,-$J$3)),"") -> 11789.85 | J12: =IF(COUNTIFS(貿易_月次!$A$5:$A$45,">="&EDATE($B12,-2-$J$3),貿易_月次!$A$5:$A$45,"<="&EDATE($B12,-$J$3))=3,SUMIFS(貿易_月次!$D$5:$D$45,貿易_月次!$A$5:$A$45,">="&EDATE($B12,-2-$J$3),貿易_月次!$A$5:$A$45,"<="&EDATE($B12,-$J$3)),"") -> 5428.46 | K12: =IF(COUNTIFS(貿易_月次!$A$5:$A$45,">="&EDATE($B12,-2-$J$3),貿易_月次!$A$5:$A$45,"<="&EDATE($B12,-$J$3))=3,SUMIFS(貿易_月次!$I$5:$I$45,貿易_月次!$A$5:$A$45,">="&EDATE($B12,-2-$J$3),貿易_月次!$A$5:$A$45,"<="&EDATE($B12,-$J$3)),"") -> 6361.39 | L12: =IF(COUNTIFS(貿易_月次!$A$5:$A$45,">="&EDATE($B12,-2-$J$3),貿易_月次!$A$5:$A$45,"<="&EDATE($B12,-$J$3))=3,SUMIFS(貿易_月次!$E$5:$E$45,貿易_月次!$A$5:$A$45,">="&EDATE($B12,-2-$J$3),貿易_月次!$A$5:$A$45,"<="&EDATE($B12,-$J$3)),"") -> 1664.89 | M12: =IF(AND(ISNUMBER(C12),ISNUMBER(I12)),C12/I12,"") -> 0.050976051
A13: 25/3期 4Q | B13: =KOKUSAI_四半期!C12 -> 45717 | C13: =KOKUSAI_四半期!D12 -> 643 | D13: =IF(COUNTIFS(貿易_月次!$A$5:$A$45,">="&EDATE($B13,-2-$E$3),貿易_月次!$A$5:$A$45,"<="&EDATE($B13,-$E$3))=3,SUMIFS(貿易_月次!$B$5:$B$45,貿易_月次!$A$5:$A$45,">="&EDATE($B13,-2-$E$3),貿易_月次!$A$5:$A$45,"<="&EDATE($B13,-$E$3)),"") -> 11830.92 | E13: =IF(COUNTIFS(貿易_月次!$A$5:$A$45,">="&EDATE($B13,-2-$E$3),貿易_月次!$A$5:$A$45,"<="&EDATE($B13,-$E$3))=3,SUMIFS(貿易_月次!$D$5:$D$45,貿易_月次!$A$5:$A$45,">="&EDATE($B13,-2-$E$3),貿易_月次!$A$5:$A$45,"<="&EDATE($B13,-$E$3)),"") -> 4516.59 | F13: =IF(COUNTIFS(貿易_月次!$A$5:$A$45,">="&EDATE($B13,-2-$E$3),貿易_月次!$A$5:$A$45,"<="&EDATE($B13,-$E$3))=3,SUMIFS(貿易_月次!$I$5:$I$45,貿易_月次!$A$5:$A$45,">="&EDATE($B13,-2-$E$3),貿易_月次!$A$5:$A$45,"<="&EDATE($B13,-$E$3)),"") -> 7314.33 | G13: =IF(COUNTIFS(貿易_月次!$A$5:$A$45,">="&EDATE($B13,-2-$E$3),貿易_月次!$A$5:$A$45,"<="&EDATE($B13,-$E$3))=3,SUMIFS(貿易_月次!$E$5:$E$45,貿易_月次!$A$5:$A$45,">="&EDATE($B13,-2-$E$3),貿易_月次!$A$5:$A$45,"<="&EDATE($B13,-$E$3)),"") -> 2230.5 | H13: =IF(AND(ISNUMBER(C13),ISNUMBER(D13)),C13/D13,"") -> 0.054349112 | I13: =IF(COUNTIFS(貿易_月次!$A$5:$A$45,">="&EDATE($B13,-2-$J$3),貿易_月次!$A$5:$A$45,"<="&EDATE($B13,-$J$3))=3,SUMIFS(貿易_月次!$B$5:$B$45,貿易_月次!$A$5:$A$45,">="&EDATE($B13,-2-$J$3),貿易_月次!$A$5:$A$45,"<="&EDATE($B13,-$J$3)),"") -> 11349.33 | J13: =IF(COUNTIFS(貿易_月次!$A$5:$A$45,">="&EDATE($B13,-2-$J$3),貿易_月次!$A$5:$A$45,"<="&EDATE($B13,-$J$3))=3,SUMIFS(貿易_月次!$D$5:$D$45,貿易_月次!$A$5:$A$45,">="&EDATE($B13,-2-$J$3),貿易_月次!$A$5:$A$45,"<="&EDATE($B13,-$J$3)),"") -> 4434.5 | K13: =IF(COUNTIFS(貿易_月次!$A$5:$A$45,">="&EDATE($B13,-2-$J$3),貿易_月次!$A$5:$A$45,"<="&EDATE($B13,-$J$3))=3,SUMIFS(貿易_月次!$I$5:$I$45,貿易_月次!$A$5:$A$45,">="&EDATE($B13,-2-$J$3),貿易_月次!$A$5:$A$45,"<="&EDATE($B13,-$J$3)),"") -> 6914.83 | L13: =IF(COUNTIFS(貿易_月次!$A$5:$A$45,">="&EDATE($B13,-2-$J$3),貿易_月次!$A$5:$A$45,"<="&EDATE($B13,-$J$3))=3,SUMIFS(貿易_月次!$E$5:$E$45,貿易_月次!$A$5:$A$45,">="&EDATE($B13,-2-$J$3),貿易_月次!$A$5:$A$45,"<="&EDATE($B13,-$J$3)),"") -> 1928.22 | M13: =IF(AND(ISNUMBER(C13),ISNUMBER(I13)),C13/I13,"") -> 0.056655327
A14: 26/3期 1Q | B14: =KOKUSAI_四半期!C13 -> 45809 | C14: =KOKUSAI_四半期!D13 -> 518 | D14: =IF(COUNTIFS(貿易_月次!$A$5:$A$45,">="&EDATE($B14,-2-$E$3),貿易_月次!$A$5:$A$45,"<="&EDATE($B14,-$E$3))=3,SUMIFS(貿易_月次!$B$5:$B$45,貿易_月次!$A$5:$A$45,">="&EDATE($B14,-2-$E$3),貿易_月次!$A$5:$A$45,"<="&EDATE($B14,-$E$3)),"") -> 10932.96 | E14: =IF(COUNTIFS(貿易_月次!$A$5:$A$45,">="&EDATE($B14,-2-$E$3),貿易_月次!$A$5:$A$45,"<="&EDATE($B14,-$E$3))=3,SUMIFS(貿易_月次!$D$5:$D$45,貿易_月次!$A$5:$A$45,">="&EDATE($B14,-2-$E$3),貿易_月次!$A$5:$A$45,"<="&EDATE($B14,-$E$3)),"") -> 4741.76 | F14: =IF(COUNTIFS(貿易_月次!$A$5:$A$45,">="&EDATE($B14,-2-$E$3),貿易_月次!$A$5:$A$45,"<="&EDATE($B14,-$E$3))=3,SUMIFS(貿易_月次!$I$5:$I$45,貿易_月次!$A$5:$A$45,">="&EDATE($B14,-2-$E$3),貿易_月次!$A$5:$A$45,"<="&EDATE($B14,-$E$3)),"") -> 6191.2 | G14: =IF(COUNTIFS(貿易_月次!$A$5:$A$45,">="&EDATE($B14,-2-$E$3),貿易_月次!$A$5:$A$45,"<="&EDATE($B14,-$E$3))=3,SUMIFS(貿易_月次!$E$5:$E$45,貿易_月次!$A$5:$A$45,">="&EDATE($B14,-2-$E$3),貿易_月次!$A$5:$A$45,"<="&EDATE($B14,-$E$3)),"") -> 1532.19 | H14: =IF(AND(ISNUMBER(C14),ISNUMBER(D14)),C14/D14,"") -> 0.047379667 | I14: =IF(COUNTIFS(貿易_月次!$A$5:$A$45,">="&EDATE($B14,-2-$J$3),貿易_月次!$A$5:$A$45,"<="&EDATE($B14,-$J$3))=3,SUMIFS(貿易_月次!$B$5:$B$45,貿易_月次!$A$5:$A$45,">="&EDATE($B14,-2-$J$3),貿易_月次!$A$5:$A$45,"<="&EDATE($B14,-$J$3)),"") -> 12039.36 | J14: =IF(COUNTIFS(貿易_月次!$A$5:$A$45,">="&EDATE($B14,-2-$J$3),貿易_月次!$A$5:$A$45,"<="&EDATE($B14,-$J$3))=3,SUMIFS(貿易_月次!$D$5:$D$45,貿易_月次!$A$5:$A$45,">="&EDATE($B14,-2-$J$3),貿易_月次!$A$5:$A$45,"<="&EDATE($B14,-$J$3)),"") -> 5066.85 | K14: =IF(COUNTIFS(貿易_月次!$A$5:$A$45,">="&EDATE($B14,-2-$J$3),貿易_月次!$A$5:$A$45,"<="&EDATE($B14,-$J$3))=3,SUMIFS(貿易_月次!$I$5:$I$45,貿易_月次!$A$5:$A$45,">="&EDATE($B14,-2-$J$3),貿易_月次!$A$5:$A$45,"<="&EDATE($B14,-$J$3)),"") -> 6972.51 | L14: =IF(COUNTIFS(貿易_月次!$A$5:$A$45,">="&EDATE($B14,-2-$J$3),貿易_月次!$A$5:$A$45,"<="&EDATE($B14,-$J$3))=3,SUMIFS(貿易_月次!$E$5:$E$45,貿易_月次!$A$5:$A$45,">="&EDATE($B14,-2-$J$3),貿易_月次!$A$5:$A$45,"<="&EDATE($B14,-$J$3)),"") -> 1896.87 | M14: =IF(AND(ISNUMBER(C14),ISNUMBER(I14)),C14/I14,"") -> 0.043025543
A15: 26/3期 2Q | B15: =KOKUSAI_四半期!C14 -> 45901 | C15: =KOKUSAI_四半期!D14 -> 654 | D15: =IF(COUNTIFS(貿易_月次!$A$5:$A$45,">="&EDATE($B15,-2-$E$3),貿易_月次!$A$5:$A$45,"<="&EDATE($B15,-$E$3))=3,SUMIFS(貿易_月次!$B$5:$B$45,貿易_月次!$A$5:$A$45,">="&EDATE($B15,-2-$E$3),貿易_月次!$A$5:$A$45,"<="&EDATE($B15,-$E$3)),"") -> 10848 | E15: =IF(COUNTIFS(貿易_月次!$A$5:$A$45,">="&EDATE($B15,-2-$E$3),貿易_月次!$A$5:$A$45,"<="&EDATE($B15,-$E$3))=3,SUMIFS(貿易_月次!$D$5:$D$45,貿易_月次!$A$5:$A$45,">="&EDATE($B15,-2-$E$3),貿易_月次!$A$5:$A$45,"<="&EDATE($B15,-$E$3)),"") -> 5209.01 | F15: =IF(COUNTIFS(貿易_月次!$A$5:$A$45,">="&EDATE($B15,-2-$E$3),貿易_月次!$A$5:$A$45,"<="&EDATE($B15,-$E$3))=3,SUMIFS(貿易_月次!$I$5:$I$45,貿易_月次!$A$5:$A$45,">="&EDATE($B15,-2-$E$3),貿易_月次!$A$5:$A$45,"<="&EDATE($B15,-$E$3)),"") -> 5638.99 | G15: =IF(COUNTIFS(貿易_月次!$A$5:$A$45,">="&EDATE($B15,-2-$E$3),貿易_月次!$A$5:$A$45,"<="&EDATE($B15,-$E$3))=3,SUMIFS(貿易_月次!$E$5:$E$45,貿易_月次!$A$5:$A$45,">="&EDATE($B15,-2-$E$3),貿易_月次!$A$5:$A$45,"<="&EDATE($B15,-$E$3)),"") -> 1456.58 | H15: =IF(AND(ISNUMBER(C15),ISNUMBER(D15)),C15/D15,"") -> 0.060287611 | I15: =IF(COUNTIFS(貿易_月次!$A$5:$A$45,">="&EDATE($B15,-2-$J$3),貿易_月次!$A$5:$A$45,"<="&EDATE($B15,-$J$3))=3,SUMIFS(貿易_月次!$B$5:$B$45,貿易_月次!$A$5:$A$45,">="&EDATE($B15,-2-$J$3),貿易_月次!$A$5:$A$45,"<="&EDATE($B15,-$J$3)),"") -> 10881.69 | J15: =IF(COUNTIFS(貿易_月次!$A$5:$A$45,">="&EDATE($B15,-2-$J$3),貿易_月次!$A$5:$A$45,"<="&EDATE($B15,-$J$3))=3,SUMIFS(貿易_月次!$D$5:$D$45,貿易_月次!$A$5:$A$45,">="&EDATE($B15,-2-$J$3),貿易_月次!$A$5:$A$45,"<="&EDATE($B15,-$J$3)),"") -> 4988.79 | K15: =IF(COUNTIFS(貿易_月次!$A$5:$A$45,">="&EDATE($B15,-2-$J$3),貿易_月次!$A$5:$A$45,"<="&EDATE($B15,-$J$3))=3,SUMIFS(貿易_月次!$I$5:$I$45,貿易_月次!$A$5:$A$45,">="&EDATE($B15,-2-$J$3),貿易_月次!$A$5:$A$45,"<="&EDATE($B15,-$J$3)),"") -> 5892.9 | L15: =IF(COUNTIFS(貿易_月次!$A$5:$A$45,">="&EDATE($B15,-2-$J$3),貿易_月次!$A$5:$A$45,"<="&EDATE($B15,-$J$3))=3,SUMIFS(貿易_月次!$E$5:$E$45,貿易_月次!$A$5:$A$45,">="&EDATE($B15,-2-$J$3),貿易_月次!$A$5:$A$45,"<="&EDATE($B15,-$J$3)),"") -> 1557.42 | M15: =IF(AND(ISNUMBER(C15),ISNUMBER(I15)),C15/I15,"") -> 0.060100959
A16: 26/3期 3Q | B16: =KOKUSAI_四半期!C15 -> 45992 | C16: =KOKUSAI_四半期!D15 -> 559 | D16: =IF(COUNTIFS(貿易_月次!$A$5:$A$45,">="&EDATE($B16,-2-$E$3),貿易_月次!$A$5:$A$45,"<="&EDATE($B16,-$E$3))=3,SUMIFS(貿易_月次!$B$5:$B$45,貿易_月次!$A$5:$A$45,">="&EDATE($B16,-2-$E$3),貿易_月次!$A$5:$A$45,"<="&EDATE($B16,-$E$3)),"") -> 11864.44 | E16: =IF(COUNTIFS(貿易_月次!$A$5:$A$45,">="&EDATE($B16,-2-$E$3),貿易_月次!$A$5:$A$45,"<="&EDATE($B16,-$E$3))=3,SUMIFS(貿易_月次!$D$5:$D$45,貿易_月次!$A$5:$A$45,">="&EDATE($B16,-2-$E$3),貿易_月次!$A$5:$A$45,"<="&EDATE($B16,-$E$3)),"") -> 4640.01 | F16: =IF(COUNTIFS(貿易_月次!$A$5:$A$45,">="&EDATE($B16,-2-$E$3),貿易_月次!$A$5:$A$45,"<="&EDATE($B16,-$E$3))=3,SUMIFS(貿易_月次!$I$5:$I$45,貿易_月次!$A$5:$A$45,">="&EDATE($B16,-2-$E$3),貿易_月次!$A$5:$A$45,"<="&EDATE($B16,-$E$3)),"") -> 7224.43 | G16: =IF(COUNTIFS(貿易_月次!$A$5:$A$45,">="&EDATE($B16,-2-$E$3),貿易_月次!$A$5:$A$45,"<="&EDATE($B16,-$E$3))=3,SUMIFS(貿易_月次!$E$5:$E$45,貿易_月次!$A$5:$A$45,">="&EDATE($B16,-2-$E$3),貿易_月次!$A$5:$A$45,"<="&EDATE($B16,-$E$3)),"") -> 1931.3 | H16: =IF(AND(ISNUMBER(C16),ISNUMBER(D16)),C16/D16,"") -> 0.047115582 | I16: =IF(COUNTIFS(貿易_月次!$A$5:$A$45,">="&EDATE($B16,-2-$J$3),貿易_月次!$A$5:$A$45,"<="&EDATE($B16,-$J$3))=3,SUMIFS(貿易_月次!$B$5:$B$45,貿易_月次!$A$5:$A$45,">="&EDATE($B16,-2-$J$3),貿易_月次!$A$5:$A$45,"<="&EDATE($B16,-$J$3)),"") -> 11271.72 | J16: =IF(COUNTIFS(貿易_月次!$A$5:$A$45,">="&EDATE($B16,-2-$J$3),貿易_月次!$A$5:$A$45,"<="&EDATE($B16,-$J$3))=3,SUMIFS(貿易_月次!$D$5:$D$45,貿易_月次!$A$5:$A$45,">="&EDATE($B16,-2-$J$3),貿易_月次!$A$5:$A$45,"<="&EDATE($B16,-$J$3)),"") -> 4860.85 | K16: =IF(COUNTIFS(貿易_月次!$A$5:$A$45,">="&EDATE($B16,-2-$J$3),貿易_月次!$A$5:$A$45,"<="&EDATE($B16,-$J$3))=3,SUMIFS(貿易_月次!$I$5:$I$45,貿易_月次!$A$5:$A$45,">="&EDATE($B16,-2-$J$3),貿易_月次!$A$5:$A$45,"<="&EDATE($B16,-$J$3)),"") -> 6410.87 | L16: =IF(COUNTIFS(貿易_月次!$A$5:$A$45,">="&EDATE($B16,-2-$J$3),貿易_月次!$A$5:$A$45,"<="&EDATE($B16,-$J$3))=3,SUMIFS(貿易_月次!$E$5:$E$45,貿易_月次!$A$5:$A$45,">="&EDATE($B16,-2-$J$3),貿易_月次!$A$5:$A$45,"<="&EDATE($B16,-$J$3)),"") -> 1704.95 | M16: =IF(AND(ISNUMBER(C16),ISNUMBER(I16)),C16/I16,"") -> 0.049593141
A17: 26/3期 4Q | B17: =KOKUSAI_四半期!C16 -> 46082 | C17: =KOKUSAI_四半期!D16 -> 620 | D17: =IF(COUNTIFS(貿易_月次!$A$5:$A$45,">="&EDATE($B17,-2-$E$3),貿易_月次!$A$5:$A$45,"<="&EDATE($B17,-$E$3))=3,SUMIFS(貿易_月次!$B$5:$B$45,貿易_月次!$A$5:$A$45,">="&EDATE($B17,-2-$E$3),貿易_月次!$A$5:$A$45,"<="&EDATE($B17,-$E$3)),"") -> 11707.45 | E17: =IF(COUNTIFS(貿易_月次!$A$5:$A$45,">="&EDATE($B17,-2-$E$3),貿易_月次!$A$5:$A$45,"<="&EDATE($B17,-$E$3))=3,SUMIFS(貿易_月次!$D$5:$D$45,貿易_月次!$A$5:$A$45,">="&EDATE($B17,-2-$E$3),貿易_月次!$A$5:$A$45,"<="&EDATE($B17,-$E$3)),"") -> 4049.63 | F17: =IF(COUNTIFS(貿易_月次!$A$5:$A$45,">="&EDATE($B17,-2-$E$3),貿易_月次!$A$5:$A$45,"<="&EDATE($B17,-$E$3))=3,SUMIFS(貿易_月次!$I$5:$I$45,貿易_月次!$A$5:$A$45,">="&EDATE($B17,-2-$E$3),貿易_月次!$A$5:$A$45,"<="&EDATE($B17,-$E$3)),"") -> 7657.82 | G17: =IF(COUNTIFS(貿易_月次!$A$5:$A$45,">="&EDATE($B17,-2-$E$3),貿易_月次!$A$5:$A$45,"<="&EDATE($B17,-$E$3))=3,SUMIFS(貿易_月次!$E$5:$E$45,貿易_月次!$A$5:$A$45,">="&EDATE($B17,-2-$E$3),貿易_月次!$A$5:$A$45,"<="&EDATE($B17,-$E$3)),"") -> 2365.89 | H17: =IF(AND(ISNUMBER(C17),ISNUMBER(D17)),C17/D17,"") -> 0.052957732 | I17: =IF(COUNTIFS(貿易_月次!$A$5:$A$45,">="&EDATE($B17,-2-$J$3),貿易_月次!$A$5:$A$45,"<="&EDATE($B17,-$J$3))=3,SUMIFS(貿易_月次!$B$5:$B$45,貿易_月次!$A$5:$A$45,">="&EDATE($B17,-2-$J$3),貿易_月次!$A$5:$A$45,"<="&EDATE($B17,-$J$3)),"") -> 10884.39 | J17: =IF(COUNTIFS(貿易_月次!$A$5:$A$45,">="&EDATE($B17,-2-$J$3),貿易_月次!$A$5:$A$45,"<="&EDATE($B17,-$J$3))=3,SUMIFS(貿易_月次!$D$5:$D$45,貿易_月次!$A$5:$A$45,">="&EDATE($B17,-2-$J$3),貿易_月次!$A$5:$A$45,"<="&EDATE($B17,-$J$3)),"") -> 3739.92 | K17: =IF(COUNTIFS(貿易_月次!$A$5:$A$45,">="&EDATE($B17,-2-$J$3),貿易_月次!$A$5:$A$45,"<="&EDATE($B17,-$J$3))=3,SUMIFS(貿易_月次!$I$5:$I$45,貿易_月次!$A$5:$A$45,">="&EDATE($B17,-2-$J$3),貿易_月次!$A$5:$A$45,"<="&EDATE($B17,-$J$3)),"") -> 7144.47 | L17: =IF(COUNTIFS(貿易_月次!$A$5:$A$45,">="&EDATE($B17,-2-$J$3),貿易_月次!$A$5:$A$45,"<="&EDATE($B17,-$J$3))=3,SUMIFS(貿易_月次!$E$5:$E$45,貿易_月次!$A$5:$A$45,">="&EDATE($B17,-2-$J$3),貿易_月次!$A$5:$A$45,"<="&EDATE($B17,-$J$3)),"") -> 2152.83 | M17: =IF(AND(ISNUMBER(C17),ISNUMBER(I17)),C17/I17,"") -> 0.05696231
A18: 27/3期 1Q | B18: =KOKUSAI_四半期!C17 -> 46174 | C18: =KOKUSAI_四半期!D17 -> 754 | D18: =IF(COUNTIFS(貿易_月次!$A$5:$A$45,">="&EDATE($B18,-2-$E$3),貿易_月次!$A$5:$A$45,"<="&EDATE($B18,-$E$3))=3,SUMIFS(貿易_月次!$B$5:$B$45,貿易_月次!$A$5:$A$45,">="&EDATE($B18,-2-$E$3),貿易_月次!$A$5:$A$45,"<="&EDATE($B18,-$E$3)),"") -> 12191.41 | E18: =IF(COUNTIFS(貿易_月次!$A$5:$A$45,">="&EDATE($B18,-2-$E$3),貿易_月次!$A$5:$A$45,"<="&EDATE($B18,-$E$3))=3,SUMIFS(貿易_月次!$D$5:$D$45,貿易_月次!$A$5:$A$45,">="&EDATE($B18,-2-$E$3),貿易_月次!$A$5:$A$45,"<="&EDATE($B18,-$E$3)),"") -> 3796.36 | F18: =IF(COUNTIFS(貿易_月次!$A$5:$A$45,">="&EDATE($B18,-2-$E$3),貿易_月次!$A$5:$A$45,"<="&EDATE($B18,-$E$3))=3,SUMIFS(貿易_月次!$I$5:$I$45,貿易_月次!$A$5:$A$45,">="&EDATE($B18,-2-$E$3),貿易_月次!$A$5:$A$45,"<="&EDATE($B18,-$E$3)),"") -> 8395.05 | G18: =IF(COUNTIFS(貿易_月次!$A$5:$A$45,">="&EDATE($B18,-2-$E$3),貿易_月次!$A$5:$A$45,"<="&EDATE($B18,-$E$3))=3,SUMIFS(貿易_月次!$E$5:$E$45,貿易_月次!$A$5:$A$45,">="&EDATE($B18,-2-$E$3),貿易_月次!$A$5:$A$45,"<="&EDATE($B18,-$E$3)),"") -> 2359.59 | H18: =IF(AND(ISNUMBER(C18),ISNUMBER(D18)),C18/D18,"") -> 0.061846825 | I18: =IF(COUNTIFS(貿易_月次!$A$5:$A$45,">="&EDATE($B18,-2-$J$3),貿易_月次!$A$5:$A$45,"<="&EDATE($B18,-$J$3))=3,SUMIFS(貿易_月次!$B$5:$B$45,貿易_月次!$A$5:$A$45,">="&EDATE($B18,-2-$J$3),貿易_月次!$A$5:$A$45,"<="&EDATE($B18,-$J$3)),"") -> 12849.88 | J18: =IF(COUNTIFS(貿易_月次!$A$5:$A$45,">="&EDATE($B18,-2-$J$3),貿易_月次!$A$5:$A$45,"<="&EDATE($B18,-$J$3))=3,SUMIFS(貿易_月次!$D$5:$D$45,貿易_月次!$A$5:$A$45,">="&EDATE($B18,-2-$J$3),貿易_月次!$A$5:$A$45,"<="&EDATE($B18,-$J$3)),"") -> 4284.66 | K18: =IF(COUNTIFS(貿易_月次!$A$5:$A$45,">="&EDATE($B18,-2-$J$3),貿易_月次!$A$5:$A$45,"<="&EDATE($B18,-$J$3))=3,SUMIFS(貿易_月次!$I$5:$I$45,貿易_月次!$A$5:$A$45,">="&EDATE($B18,-2-$J$3),貿易_月次!$A$5:$A$45,"<="&EDATE($B18,-$J$3)),"") -> 8565.22 | L18: =IF(COUNTIFS(貿易_月次!$A$5:$A$45,">="&EDATE($B18,-2-$J$3),貿易_月次!$A$5:$A$45,"<="&EDATE($B18,-$J$3))=3,SUMIFS(貿易_月次!$E$5:$E$45,貿易_月次!$A$5:$A$45,">="&EDATE($B18,-2-$J$3),貿易_月次!$A$5:$A$45,"<="&EDATE($B18,-$J$3)),"") -> 2469.52 | M18: =IF(AND(ISNUMBER(C18),ISNUMBER(I18)),C18/I18,"") -> 0.058677591
A19: 27/3期 2Q | B19: 46266 | D19: =IF(COUNTIFS(貿易_月次!$A$5:$A$45,">="&EDATE($B19,-2-$E$3),貿易_月次!$A$5:$A$45,"<="&EDATE($B19,-$E$3))=3,SUMIFS(貿易_月次!$B$5:$B$45,貿易_月次!$A$5:$A$45,">="&EDATE($B19,-2-$E$3),貿易_月次!$A$5:$A$45,"<="&EDATE($B19,-$E$3)),"") | E19: =IF(COUNTIFS(貿易_月次!$A$5:$A$45,">="&EDATE($B19,-2-$E$3),貿易_月次!$A$5:$A$45,"<="&EDATE($B19,-$E$3))=3,SUMIFS(貿易_月次!$D$5:$D$45,貿易_月次!$A$5:$A$45,">="&EDATE($B19,-2-$E$3),貿易_月次!$A$5:$A$45,"<="&EDATE($B19,-$E$3)),"") | F19: =IF(COUNTIFS(貿易_月次!$A$5:$A$45,">="&EDATE($B19,-2-$E$3),貿易_月次!$A$5:$A$45,"<="&EDATE($B19,-$E$3))=3,SUMIFS(貿易_月次!$I$5:$I$45,貿易_月次!$A$5:$A$45,">="&EDATE($B19,-2-$E$3),貿易_月次!$A$5:$A$45,"<="&EDATE($B19,-$E$3)),"") | G19: =IF(COUNTIFS(貿易_月次!$A$5:$A$45,">="&EDATE($B19,-2-$E$3),貿易_月次!$A$5:$A$45,"<="&EDATE($B19,-$E$3))=3,SUMIFS(貿易_月次!$E$5:$E$45,貿易_月次!$A$5:$A$45,">="&EDATE($B19,-2-$E$3),貿易_月次!$A$5:$A$45,"<="&EDATE($B19,-$E$3)),"") | I19: =IF(COUNTIFS(貿易_月次!$A$5:$A$45,">="&EDATE($B19,-2-$J$3),貿易_月次!$A$5:$A$45,"<="&EDATE($B19,-$J$3))=3,SUMIFS(貿易_月次!$B$5:$B$45,貿易_月次!$A$5:$A$45,">="&EDATE($B19,-2-$J$3),貿易_月次!$A$5:$A$45,"<="&EDATE($B19,-$J$3)),"") -> 14443.43 | J19: =IF(COUNTIFS(貿易_月次!$A$5:$A$45,">="&EDATE($B19,-2-$J$3),貿易_月次!$A$5:$A$45,"<="&EDATE($B19,-$J$3))=3,SUMIFS(貿易_月次!$D$5:$D$45,貿易_月次!$A$5:$A$45,">="&EDATE($B19,-2-$J$3),貿易_月次!$A$5:$A$45,"<="&EDATE($B19,-$J$3)),"") -> 5592 | K19: =IF(COUNTIFS(貿易_月次!$A$5:$A$45,">="&EDATE($B19,-2-$J$3),貿易_月次!$A$5:$A$45,"<="&EDATE($B19,-$J$3))=3,SUMIFS(貿易_月次!$I$5:$I$45,貿易_月次!$A$5:$A$45,">="&EDATE($B19,-2-$J$3),貿易_月次!$A$5:$A$45,"<="&EDATE($B19,-$J$3)),"") -> 8851.43 | L19: =IF(COUNTIFS(貿易_月次!$A$5:$A$45,">="&EDATE($B19,-2-$J$3),貿易_月次!$A$5:$A$45,"<="&EDATE($B19,-$J$3))=3,SUMIFS(貿易_月次!$E$5:$E$45,貿易_月次!$A$5:$A$45,">="&EDATE($B19,-2-$J$3),貿易_月次!$A$5:$A$45,"<="&EDATE($B19,-$J$3)),"") -> 2462.13
A21: 実質シェア＝KOKUSAI売上÷日本の半導体等製造装置輸出。27/3期2Qのk=0は9月分が未公表のため空欄（ナウキャストで推計）。

Sheet 回帰
A1: 回帰：売上収益と輸出額（サンプル＝24/3期2Q〜27/3期1Qの12四半期）
A2: 単一モデル：売上＝a＋b×世界。構造モデル：中国地場売上＝a_c＋b_c×中国、グローバル売上＝a_g＋b_g×中国以外、全社＝両者の和。LOO残差＝残差÷(1−h)（単回帰のleave-one-outの厳密式）。
A4: k=0（輸出と売上が同じ3か月）
A5: 四半期 | B5: 売上収益 | C5: 中国地場 | D5: グローバル | E5: 世界 | F5: 中国 | G5: 中国以外 | H5: 単一:予測 | I5: 単一:残差 | J5: 単一:h | K5: 単一:LOO残差 | L5: 中国地場:予測 | M5: 中国地場:残差 | N5: 中国地場:h | O5: グローバル:予測 | P5: グローバル:残差 | Q5: グローバル:h | R5: 構造:予測 | S5: 構造:残差 | T5: 構造:LOO残差
A6: =四半期集計!A7 -> 24/3期 2Q | B6: =KOKUSAI_四半期!D6 -> 450 | C6: =KOKUSAI_四半期!H6 -> 220.5 | D6: =KOKUSAI_四半期!I6 -> 229.5 | E6: =四半期集計!D7 -> 8236.8411 | F6: =四半期集計!E7 -> 4185.4136 | G6: =四半期集計!F7 -> 4051.4275 | H6: =$C$20+$D$20*E6 -> 437.22672 | I6: =B6-H6 -> 12.773275 | J6: =1/COUNT($E$6:$E$17)+(E6-AVERAGE($E$6:$E$17))^2/DEVSQ($E$6:$E$17) -> 0.6120529 | K6: =I6/(1-J6) -> 32.925302 | L6: =$C$21+$D$21*F6 -> 195.17692 | M6: =C6-L6 -> 25.32308 | N6: =1/COUNT($F$6:$F$17)+(F6-AVERAGE($F$6:$F$17))^2/DEVSQ($F$6:$F$17) -> 0.18746635 | O6: =$C$22+$D$22*G6 -> 215.69044 | P6: =D6-O6 -> 13.809563 | Q6: =1/COUNT($G$6:$G$17)+(G6-AVERAGE($G$6:$G$17))^2/DEVSQ($G$6:$G$17) -> 0.32284128 | R6: =L6+O6 -> 410.86736 | S6: =B6-R6 -> 39.132643 | T6: =M6/(1-N6)+P6/(1-Q6) -> 51.558968
A7: =四半期集計!A8 -> 24/3期 3Q | B7: =KOKUSAI_四半期!D7 -> 540 | C7: =KOKUSAI_四半期!H7 -> 243 | D7: =KOKUSAI_四半期!I7 -> 297 | E7: =四半期集計!D8 -> 9763.3206 | F7: =四半期集計!E8 -> 5178.9518 | G7: =四半期集計!F8 -> 4584.3688 | H7: =$C$20+$D$20*E7 -> 516.0395 | I7: =B7-H7 -> 23.960504 | J7: =1/COUNT($E$6:$E$17)+(E7-AVERAGE($E$6:$E$17))^2/DEVSQ($E$6:$E$17) -> 0.19187637 | K7: =I7/(1-J7) -> 29.649552 | L7: =$C$21+$D$21*F7 -> 248.48474 | M7: =C7-L7 -> -5.4847382 | N7: =1/COUNT($F$6:$F$17)+(F7-AVERAGE($F$6:$F$17))^2/DEVSQ($F$6:$F$17) -> 0.11107662 | O7: =$C$22+$D$22*G7 -> 249.45278 | P7: =D7-O7 -> 47.547218 | Q7: =1/COUNT($G$6:$G$17)+(G7-AVERAGE($G$6:$G$17))^2/DEVSQ($G$6:$G$17) -> 0.2182271 | R7: =L7+O7 -> 497.93752 | S7: =B7-R7 -> 42.062479 | T7: =M7/(1-N7)+P7/(1-Q7) -> 54.64964
A8: =四半期集計!A9 -> 24/3期 4Q | B8: =KOKUSAI_四半期!D8 -> 492 | C8: =KOKUSAI_四半期!H8 -> 246 | D8: =KOKUSAI_四半期!I8 -> 246 | E8: =四半期集計!D9 -> 10364.937 | F8: =四半期集計!E9 -> 5212.6018 | G8: =四半期集計!F9 -> 5152.3349 | H8: =$C$20+$D$20*E8 -> 547.10118 | I8: =B8-H8 -> -55.101183 | J8: =1/COUNT($E$6:$E$17)+(E8-AVERAGE($E$6:$E$17))^2/DEVSQ($E$6:$E$17) -> 0.11316833 | K8: =I8/(1-J8) -> -62.132629 | L8: =$C$21+$D$21*F8 -> 250.29021 | M8: =C8-L8 -> -4.2902142 | N8: =1/COUNT($F$6:$F$17)+(F8-AVERAGE($F$6:$F$17))^2/DEVSQ($F$6:$F$17) -> 0.11687134 | O8: =$C$22+$D$22*G8 -> 285.43398 | P8: =D8-O8 -> -39.433977 | Q8: =1/COUNT($G$6:$G$17)+(G8-AVERAGE($G$6:$G$17))^2/DEVSQ($G$6:$G$17) -> 0.13956719 | R8: =L8+O8 -> 535.72419 | S8: =B8-R8 -> -43.724191 | T8: =M8/(1-N8)+P8/(1-Q8) -> -50.688368
A9: =四半期集計!A10 -> 25/3期 1Q | B9: =KOKUSAI_四半期!D9 -> 652 | C9: =KOKUSAI_四半期!H9 -> 326 | D9: =KOKUSAI_四半期!I9 -> 326 | E9: =四半期集計!D10 -> 11188.098 | F9: =四半期集計!E10 -> 5699.0722 | G9: =四半期集計!F10 -> 5489.0256 | H9: =$C$20+$D$20*E9 -> 589.60133 | I9: =B9-H9 -> 62.39867 | J9: =1/COUNT($E$6:$E$17)+(E9-AVERAGE($E$6:$E$17))^2/DEVSQ($E$6:$E$17) -> 0.08507377 | K9: =I9/(1-J9) -> 68.200766 | L9: =$C$21+$D$21*F9 -> 276.39155 | M9: =C9-L9 -> 49.608454 | N9: =1/COUNT($F$6:$F$17)+(F9-AVERAGE($F$6:$F$17))^2/DEVSQ($F$6:$F$17) -> 0.26200195 | O9: =$C$22+$D$22*G9 -> 306.76366 | P9: =D9-O9 -> 19.236341 | Q9: =1/COUNT($G$6:$G$17)+(G9-AVERAGE($G$6:$G$17))^2/DEVSQ($G$6:$G$17) -> 0.10892964 | R9: =L9+O9 -> 583.1552 | S9: =B9-R9 -> 68.844795 | T9: =M9/(1-N9)+P9/(1-Q9) -> 88.808208
A10: =四半期集計!A11 -> 25/3期 2Q | B10: =KOKUSAI_四半期!D10 -> 493 | C10: =KOKUSAI_四半期!H10 -> 216.92 | D10: =KOKUSAI_四半期!I10 -> 276.08 | E10: =四半期集計!D11 -> 11084.95 | F10: =四半期集計!E11 -> 5384.56 | G10: =四半期集計!F11 -> 5700.39 | H10: =$C$20+$D$20*E10 -> 584.27577 | I10: =B10-H10 -> -91.275767 | J10: =1/COUNT($E$6:$E$17)+(E10-AVERAGE($E$6:$E$17))^2/DEVSQ($E$6:$E$17) -> 0.083553763 | K10: =I10/(1-J10) -> -99.597514 | L10: =$C$21+$D$21*F10 -> 259.51655 | M10: =C10-L10 -> -42.596547 | N10: =1/COUNT($F$6:$F$17)+(F10-AVERAGE($F$6:$F$17))^2/DEVSQ($F$6:$F$17) -> 0.15505725 | O10: =$C$22+$D$22*G10 -> 320.15379 | P10: =D10-O10 -> -44.073794 | Q10: =1/COUNT($G$6:$G$17)+(G10-AVERAGE($G$6:$G$17))^2/DEVSQ($G$6:$G$17) -> 0.095778307 | R10: =L10+O10 -> 579.67034 | S10: =B10-R10 -> -86.670341 | T10: =M10/(1-N10)+P10/(1-Q10) -> -99.155774
A11: =四半期集計!A12 -> 25/3期 3Q | B11: =KOKUSAI_四半期!D11 -> 601 | C11: =KOKUSAI_四半期!H11 -> 240.4 | D11: =KOKUSAI_四半期!I11 -> 360.6 | E11: =四半期集計!D12 -> 12322.19 | F11: =四半期集計!E12 -> 5474.59 | G11: =四半期集計!F12 -> 6847.6 | H11: =$C$20+$D$20*E11 -> 648.15498 | I11: =B11-H11 -> -47.15498 | J11: =1/COUNT($E$6:$E$17)+(E11-AVERAGE($E$6:$E$17))^2/DEVSQ($E$6:$E$17) -> 0.19701539 | K11: =I11/(1-J11) -> -58.724638 | L11: =$C$21+$D$21*F11 -> 264.34706 | M11: =C11-L11 -> -23.947064 | N11: =1/COUNT($F$6:$F$17)+(F11-AVERAGE($F$6:$F$17))^2/DEVSQ($F$6:$F$17) -> 0.18076954 | O11: =$C$22+$D$22*G11 -> 392.83065 | P11: =D11-O11 -> -32.230648 | Q11: =1/COUNT($G$6:$G$17)+(G11-AVERAGE($G$6:$G$17))^2/DEVSQ($G$6:$G$17) -> 0.10622844 | R11: =L11+O11 -> 657.17771 | S11: =B11-R11 -> -56.177711 | T11: =M11/(1-N11)+P11/(1-Q11) -> -65.292562
A12: =四半期集計!A13 -> 25/3期 4Q | B12: =KOKUSAI_四半期!D12 -> 643 | C12: =KOKUSAI_四半期!H12 -> 263.63 | D12: =KOKUSAI_四半期!I12 -> 379.37 | E12: =四半期集計!D13 -> 11830.92 | F12: =四半期集計!E13 -> 4516.59 | G12: =四半期集計!F13 -> 7314.33 | H12: =$C$20+$D$20*E12 -> 622.79051 | I12: =B12-H12 -> 20.209493 | J12: =1/COUNT($E$6:$E$17)+(E12-AVERAGE($E$6:$E$17))^2/DEVSQ($E$6:$E$17) -> 0.12709128 | K12: =I12/(1-J12) -> 23.151898 | L12: =$C$21+$D$21*F12 -> 212.94603 | M12: =C12-L12 -> 50.683968 | N12: =1/COUNT($F$6:$F$17)+(F12-AVERAGE($F$6:$F$17))^2/DEVSQ($F$6:$F$17) -> 0.10880913 | O12: =$C$22+$D$22*G12 -> 422.39844 | P12: =D12-O12 -> -43.028441 | Q12: =1/COUNT($G$6:$G$17)+(G12-AVERAGE($G$6:$G$17))^2/DEVSQ($G$6:$G$17) -> 0.15002973 | R12: =L12+O12 -> 635.34447 | S12: =B12-R12 -> 7.6555279 | T12: =M12/(1-N12)+P12/(1-Q12) -> 6.248716
A13: =四半期集計!A14 -> 26/3期 1Q | B13: =KOKUSAI_四半期!D13 -> 518 | C13: =KOKUSAI_四半期!H13 -> 196.84 | D13: =KOKUSAI_四半期!I13 -> 321.16 | E13: =四半期集計!D14 -> 10932.96 | F13: =四半期集計!E14 -> 4741.76 | G13: =四半期集計!F14 -> 6191.2 | H13: =$C$20+$D$20*E13 -> 576.42846 | I13: =B13-H13 -> -58.42846 | J13: =1/COUNT($E$6:$E$17)+(E13-AVERAGE($E$6:$E$17))^2/DEVSQ($E$6:$E$17) -> 0.083945843 | K13: =I13/(1-J13) -> -63.782758 | L13: =$C$21+$D$21*F13 -> 225.02742 | M13: =C13-L13 -> -28.18742 | N13: =1/COUNT($F$6:$F$17)+(F13-AVERAGE($F$6:$F$17))^2/DEVSQ($F$6:$F$17) -> 0.085707782 | O13: =$C$22+$D$22*G13 -> 351.24708 | P13: =D13-O13 -> -30.087078 | Q13: =1/COUNT($G$6:$G$17)+(G13-AVERAGE($G$6:$G$17))^2/DEVSQ($G$6:$G$17) -> 0.083334154 | R13: =L13+O13 -> 576.2745 | S13: =B13-R13 -> -58.274498 | T13: =M13/(1-N13)+P13/(1-Q13) -> -63.652068
A14: =四半期集計!A15 -> 26/3期 2Q | B14: =KOKUSAI_四半期!D14 -> 654 | C14: =KOKUSAI_四半期!H14 -> 287.76 | D14: =KOKUSAI_四半期!I14 -> 366.24 | E14: =四半期集計!D15 -> 10848 | F14: =四半期集計!E15 -> 5209.01 | G14: =四半期集計!F15 -> 5638.99 | H14: =$C$20+$D$20*E14 -> 572.04194 | I14: =B14-H14 -> 81.95806 | J14: =1/COUNT($E$6:$E$17)+(E14-AVERAGE($E$6:$E$17))^2/DEVSQ($E$6:$E$17) -> 0.085531291 | K14: =I14/(1-J14) -> 89.62369 | L14: =$C$21+$D$21*F14 -> 250.0975 | M14: =C14-L14 -> 37.662504 | N14: =1/COUNT($F$6:$F$17)+(F14-AVERAGE($F$6:$F$17))^2/DEVSQ($F$6:$F$17) -> 0.11622662 | O14: =$C$22+$D$22*G14 -> 316.26404 | P14: =D14-O14 -> 49.975955 | Q14: =1/COUNT($G$6:$G$17)+(G14-AVERAGE($G$6:$G$17))^2/DEVSQ($G$6:$G$17) -> 0.09911524 | R14: =L14+O14 -> 566.36154 | S14: =B14-R14 -> 87.638459 | T14: =M14/(1-N14)+P14/(1-Q14) -> 98.089872
A15: =四半期集計!A16 -> 26/3期 3Q | B15: =KOKUSAI_四半期!D15 -> 559 | C15: =KOKUSAI_四半期!H15 -> 173.29 | D15: =KOKUSAI_四半期!I15 -> 385.71 | E15: =四半期集計!D16 -> 11864.44 | F15: =四半期集計!E16 -> 4640.01 | G15: =四半期集計!F16 -> 7224.43 | H15: =$C$20+$D$20*E15 -> 624.52116 | I15: =B15-H15 -> -65.521158 | J15: =1/COUNT($E$6:$E$17)+(E15-AVERAGE($E$6:$E$17))^2/DEVSQ($E$6:$E$17) -> 0.13082094 | K15: =I15/(1-J15) -> -75.382808 | L15: =$C$21+$D$21*F15 -> 219.56807 | M15: =C15-L15 -> -46.278073 | N15: =1/COUNT($F$6:$F$17)+(F15-AVERAGE($F$6:$F$17))^2/DEVSQ($F$6:$F$17) -> 0.093101543 | O15: =$C$22+$D$22*G15 -> 416.70319 | P15: =D15-O15 -> -30.993189 | Q15: =1/COUNT($G$6:$G$17)+(G15-AVERAGE($G$6:$G$17))^2/DEVSQ($G$6:$G$17) -> 0.1398142 | R15: =L15+O15 -> 636.27126 | S15: =B15-R15 -> -77.271262 | T15: =M15/(1-N15)+P15/(1-Q15) -> -87.059754
A16: =四半期集計!A17 -> 26/3期 4Q | B16: =KOKUSAI_四半期!D16 -> 620 | C16: =KOKUSAI_四半期!H16 -> 161.2 | D16: =KOKUSAI_四半期!I16 -> 458.8 | E16: =四半期集計!D17 -> 11707.45 | F16: =四半期集計!E17 -> 4049.63 | G16: =四半期集計!F17 -> 7657.82 | H16: =$C$20+$D$20*E16 -> 616.4157 | I16: =B16-H16 -> 3.5843006 | J16: =1/COUNT($E$6:$E$17)+(E16-AVERAGE($E$6:$E$17))^2/DEVSQ($E$6:$E$17) -> 0.11466874 | K16: =I16/(1-J16) -> 4.0485418 | L16: =$C$21+$D$21*F16 -> 187.89152 | M16: =C16-L16 -> -26.691516 | N16: =1/COUNT($F$6:$F$17)+(F16-AVERAGE($F$6:$F$17))^2/DEVSQ($F$6:$F$17) -> 0.23509187 | O16: =$C$22+$D$22*G16 -> 444.15886 | P16: =D16-O16 -> 14.641138 | Q16: =1/COUNT($G$6:$G$17)+(G16-AVERAGE($G$6:$G$17))^2/DEVSQ($G$6:$G$17) -> 0.19687722 | R16: =L16+O16 -> 632.05038 | S16: =B16-R16 -> -12.050377 | T16: =M16/(1-N16)+P16/(1-Q16) -> -16.664799
A17: =四半期集計!A18 -> 27/3期 1Q | B17: =KOKUSAI_四半期!D17 -> 754 | C17: =KOKUSAI_四半期!H17 -> 188.5 | D17: =KOKUSAI_四半期!I17 -> 565.5 | E17: =四半期集計!D18 -> 12191.41 | F17: =四半期集計!E18 -> 3796.36 | G17: =四半期集計!F18 -> 8395.05 | H17: =$C$20+$D$20*E17 -> 641.40275 | I17: =B17-H17 -> 112.59725 | J17: =1/COUNT($E$6:$E$17)+(E17-AVERAGE($E$6:$E$17))^2/DEVSQ($E$6:$E$17) -> 0.17520138 | K17: =I17/(1-J17) -> 136.51483 | L17: =$C$21+$D$21*F17 -> 174.30244 | M17: =C17-L17 -> 14.197565 | N17: =1/COUNT($F$6:$F$17)+(F17-AVERAGE($F$6:$F$17))^2/DEVSQ($F$6:$F$17) -> 0.34782001 | O17: =$C$22+$D$22*G17 -> 490.86309 | P17: =D17-O17 -> 74.636911 | Q17: =1/COUNT($G$6:$G$17)+(G17-AVERAGE($G$6:$G$17))^2/DEVSQ($G$6:$G$17) -> 0.33925749 | R17: =L17+O17 -> 665.16552 | S17: =B17-R17 -> 88.834476 | T17: =M17/(1-N17)+P17/(1-Q17) -> 134.72854
B19: モデル | C19: 切片 a | D19: 傾き b | E19: R² | F19: LOOCV RMSE（億円）
B20: 単一：全社×世界 | C20: =INTERCEPT($B$6:$B$17,$E$6:$E$17) -> 11.955211 | D20: =SLOPE($B$6:$B$17,$E$6:$E$17) -> 0.051630414 | E20: =RSQ($B$6:$B$17,$E$6:$E$17) -> 0.46196353 | F20: =SQRT(SUMSQ($K$6:$K$17)/COUNT($K$6:$K$17)) -> 71.189384
B21: 構造：中国地場×中国 | C21: =INTERCEPT($C$6:$C$17,$F$6:$F$17) -> -29.389446 | D21: =SLOPE($C$6:$C$17,$F$6:$F$17) -> 0.053654522 | E21: =RSQ($C$6:$C$17,$F$6:$F$17) -> 0.47019977
B22: 構造：グローバル×中国以外 | C22: =INTERCEPT($D$6:$D$17,$G$6:$G$17) -> -40.971379 | D22: =SLOPE($D$6:$D$17,$G$6:$G$17) -> 0.063350959 | E22: =RSQ($D$6:$D$17,$G$6:$G$17) -> 0.79792948
B23: 構造：全社（和） | E23: =1-SUMSQ($S$6:$S$17)/DEVSQ($B$6:$B$17) -> 0.46176286 | F23: =SQRT(SUMSQ($T$6:$T$17)/COUNT($T$6:$T$17)) -> 76.331108
B24: 比較：ランダムウォーク | F24: =SQRT(SUMXMY2($B$7:$B$17,$B$6:$B$16)/(COUNT($B$6:$B$17)-1)) -> 112.62811
A27: k=1（輸出が1か月先行）
A28: 四半期 | B28: 売上収益 | C28: 中国地場 | D28: グローバル | E28: 世界 | F28: 中国 | G28: 中国以外 | H28: 単一:予測 | I28: 単一:残差 | J28: 単一:h | K28: 単一:LOO残差 | L28: 中国地場:予測 | M28: 中国地場:残差 | N28: 中国地場:h | O28: グローバル:予測 | P28: グローバル:残差 | Q28: グローバル:h | R28: 構造:予測 | S28: 構造:残差 | T28: 構造:LOO残差
A29: =四半期集計!A7 -> 24/3期 2Q | B29: =KOKUSAI_四半期!D6 -> 450 | C29: =KOKUSAI_四半期!H6 -> 220.5 | D29: =KOKUSAI_四半期!I6 -> 229.5 | E29: =四半期集計!I7 -> 7973.4192 | F29: =四半期集計!J7 -> 3822.5961 | G29: =四半期集計!K7 -> 4150.8232 | H29: =$C$43+$D$43*E29 -> 455.57663 | I29: =B29-H29 -> -5.5766282 | J29: =1/COUNT($E$29:$E$40)+(E29-AVERAGE($E$29:$E$40))^2/DEVSQ($E$29:$E$40) -> 0.50296994 | K29: =I29/(1-J29) -> -11.219901 | L29: =$C$44+$D$44*F29 -> 188.19161 | M29: =C29-L29 -> 32.308394 | N29: =1/COUNT($F$29:$F$40)+(F29-AVERAGE($F$29:$F$40))^2/DEVSQ($F$29:$F$40) -> 0.27803784 | O29: =$C$45+$D$45*G29 -> 228.34218 | P29: =D29-O29 -> 1.1578222 | Q29: =1/COUNT($G$29:$G$40)+(G29-AVERAGE($G$29:$G$40))^2/DEVSQ($G$29:$G$40) -> 0.28756554 | R29: =L29+O29 -> 416.53378 | S29: =B29-R29 -> 33.466216 | T29: =M29/(1-N29)+P29/(1-Q29) -> 46.375976
A30: =四半期集計!A8 -> 24/3期 3Q | B30: =KOKUSAI_四半期!D7 -> 540 | C30: =KOKUSAI_四半期!H7 -> 243 | D30: =KOKUSAI_四半期!I7 -> 297 | E30: =四半期集計!I8 -> 8835.7681 | F30: =四半期集計!J8 -> 4621.5038 | G30: =四半期集計!K8 -> 4214.2643 | H30: =$C$43+$D$43*E30 -> 492.8293 | I30: =B30-H30 -> 47.170702 | J30: =1/COUNT($E$29:$E$40)+(E30-AVERAGE($E$29:$E$40))^2/DEVSQ($E$29:$E$40) -> 0.2911772 | K30: =I30/(1-J30) -> 66.547946 | L30: =$C$44+$D$44*F30 -> 222.00065 | M30: =C30-L30 -> 20.999348 | N30: =1/COUNT($F$29:$F$40)+(F30-AVERAGE($F$29:$F$40))^2/DEVSQ($F$29:$F$40) -> 0.090950607 | O30: =$C$45+$D$45*G30 -> 232.40509 | P30: =D30-O30 -> 64.594907 | Q30: =1/COUNT($G$29:$G$40)+(G30-AVERAGE($G$29:$G$40))^2/DEVSQ($G$29:$G$40) -> 0.2742593 | R30: =L30+O30 -> 454.40575 | S30: =B30-R30 -> 85.594254 | T30: =M30/(1-N30)+P30/(1-Q30) -> 112.10583
A31: =四半期集計!A9 -> 24/3期 4Q | B31: =KOKUSAI_四半期!D8 -> 492 | C31: =KOKUSAI_四半期!H8 -> 246 | D31: =KOKUSAI_四半期!I8 -> 246 | E31: =四半期集計!I9 -> 10086.798 | F31: =四半期集計!J9 -> 5120.9835 | G31: =四半期集計!K9 -> 4965.8145 | H31: =$C$43+$D$43*E31 -> 546.87263 | I31: =B31-H31 -> -54.872634 | J31: =1/COUNT($E$29:$E$40)+(E31-AVERAGE($E$29:$E$40))^2/DEVSQ($E$29:$E$40) -> 0.11484412 | K31: =I31/(1-J31) -> -61.992058 | L31: =$C$44+$D$44*F31 -> 243.13818 | M31: =C31-L31 -> 2.8618204 | N31: =1/COUNT($F$29:$F$40)+(F31-AVERAGE($F$29:$F$40))^2/DEVSQ($F$29:$F$40) -> 0.10129742 | O31: =$C$45+$D$45*G31 -> 280.53612 | P31: =D31-O31 -> -34.536124 | Q31: =1/COUNT($G$29:$G$40)+(G31-AVERAGE($G$29:$G$40))^2/DEVSQ($G$29:$G$40) -> 0.15073169 | R31: =L31+O31 -> 523.6743 | S31: =B31-R31 -> -31.674304 | T31: =M31/(1-N31)+P31/(1-Q31) -> -37.481349
A32: =四半期集計!A10 -> 25/3期 1Q | B32: =KOKUSAI_四半期!D9 -> 652 | C32: =KOKUSAI_四半期!H9 -> 326 | D32: =KOKUSAI_四半期!I9 -> 326 | E32: =四半期集計!I10 -> 11565.652 | F32: =四半期集計!J10 -> 6089.0022 | G32: =四半期集計!K10 -> 5476.6502 | H32: =$C$43+$D$43*E32 -> 610.75778 | I32: =B32-H32 -> 41.242223 | J32: =1/COUNT($E$29:$E$40)+(E32-AVERAGE($E$29:$E$40))^2/DEVSQ($E$29:$E$40) -> 0.10630686 | K32: =I32/(1-J32) -> 46.148081 | L32: =$C$44+$D$44*F32 -> 284.10385 | M32: =C32-L32 -> 41.896151 | N32: =1/COUNT($F$29:$F$40)+(F32-AVERAGE($F$29:$F$40))^2/DEVSQ($F$29:$F$40) -> 0.40022965 | O32: =$C$45+$D$45*G32 -> 313.25124 | P32: =D32-O32 -> 12.748763 | Q32: =1/COUNT($G$29:$G$40)+(G32-AVERAGE($G$29:$G$40))^2/DEVSQ($G$29:$G$40) -> 0.10267465 | R32: =L32+O32 -> 597.35509 | S32: =B32-R32 -> 54.644914 | T32: =M32/(1-N32)+P32/(1-Q32) -> 84.06117
A33: =四半期集計!A11 -> 25/3期 2Q | B33: =KOKUSAI_四半期!D10 -> 493 | C33: =KOKUSAI_四半期!H10 -> 216.92 | D33: =KOKUSAI_四半期!I10 -> 276.08 | E33: =四半期集計!I11 -> 11086.34 | F33: =四半期集計!J11 -> 5363.69 | G33: =四半期集計!K11 -> 5722.65 | H33: =$C$43+$D$43*E33 -> 590.05192 | I33: =B33-H33 -> -97.051922 | J33: =1/COUNT($E$29:$E$40)+(E33-AVERAGE($E$29:$E$40))^2/DEVSQ($E$29:$E$40) -> 0.085350322 | K33: =I33/(1-J33) -> -106.1083 | L33: =$C$44+$D$44*F33 -> 253.4093 | M33: =C33-L33 -> -36.489296 | N33: =1/COUNT($F$29:$F$40)+(F33-AVERAGE($F$29:$F$40))^2/DEVSQ($F$29:$F$40) -> 0.14168816 | O33: =$C$45+$D$45*G33 -> 329.00564 | P33: =D33-O33 -> -52.925638 | Q33: =1/COUNT($G$29:$G$40)+(G33-AVERAGE($G$29:$G$40))^2/DEVSQ($G$29:$G$40) -> 0.08989854 | R33: =L33+O33 -> 582.41493 | S33: =B33-R33 -> -89.414934 | T33: =M33/(1-N33)+P33/(1-Q33) -> -100.66642
A34: =四半期集計!A12 -> 25/3期 3Q | B34: =KOKUSAI_四半期!D11 -> 601 | C34: =KOKUSAI_四半期!H11 -> 240.4 | D34: =KOKUSAI_四半期!I11 -> 360.6 | E34: =四半期集計!I12 -> 11789.85 | F34: =四半期集計!J12 -> 5428.46 | G34: =四半期集計!K12 -> 6361.39 | H34: =$C$43+$D$43*E34 -> 620.4429 | I34: =B34-H34 -> -19.442903 | J34: =1/COUNT($E$29:$E$40)+(E34-AVERAGE($E$29:$E$40))^2/DEVSQ($E$29:$E$40) -> 0.12391942 | K34: =I34/(1-J34) -> -22.193053 | L34: =$C$44+$D$44*F34 -> 256.1503 | M34: =C34-L34 -> -15.750303 | N34: =1/COUNT($F$29:$F$40)+(F34-AVERAGE($F$29:$F$40))^2/DEVSQ($F$29:$F$40) -> 0.15637674 | O34: =$C$45+$D$45*G34 -> 369.91204 | P34: =D34-O34 -> -9.3120394 | Q34: =1/COUNT($G$29:$G$40)+(G34-AVERAGE($G$29:$G$40))^2/DEVSQ($G$29:$G$40) -> 0.088190546 | R34: =L34+O34 -> 626.06234 | S34: =B34-R34 -> -25.062342 | T34: =M34/(1-N34)+P34/(1-Q34) -> -28.882533
A35: =四半期集計!A13 -> 25/3期 4Q | B35: =KOKUSAI_四半期!D12 -> 643 | C35: =KOKUSAI_四半期!H12 -> 263.63 | D35: =KOKUSAI_四半期!I12 -> 379.37 | E35: =四半期集計!I13 -> 11349.33 | F35: =四半期集計!J13 -> 4434.5 | G35: =四半期集計!K13 -> 6914.83 | H35: =$C$43+$D$43*E35 -> 601.41285 | I35: =B35-H35 -> 41.587153 | J35: =1/COUNT($E$29:$E$40)+(E35-AVERAGE($E$29:$E$40))^2/DEVSQ($E$29:$E$40) -> 0.094031699 | K35: =I35/(1-J35) -> 45.903541 | L35: =$C$44+$D$44*F35 -> 214.08682 | M35: =C35-L35 -> 49.543178 | N35: =1/COUNT($F$29:$F$40)+(F35-AVERAGE($F$29:$F$40))^2/DEVSQ($F$29:$F$40) -> 0.11227883 | O35: =$C$45+$D$45*G35 -> 405.35563 | P35: =D35-O35 -> -25.985629 | Q35: =1/COUNT($G$29:$G$40)+(G35-AVERAGE($G$29:$G$40))^2/DEVSQ($G$29:$G$40) -> 0.12344767 | R35: =L35+O35 -> 619.44245 | S35: =B35-R35 -> 23.557549 | T35: =M35/(1-N35)+P35/(1-Q35) -> 26.164122
A36: =四半期集計!A14 -> 26/3期 1Q | B36: =KOKUSAI_四半期!D13 -> 518 | C36: =KOKUSAI_四半期!H13 -> 196.84 | D36: =KOKUSAI_四半期!I13 -> 321.16 | E36: =四半期集計!I14 -> 12039.36 | F36: =四半期集計!J14 -> 5066.85 | G36: =四半期集計!K14 -> 6972.51 | H36: =$C$43+$D$43*E36 -> 631.2215 | I36: =B36-H36 -> -113.2215 | J36: =1/COUNT($E$29:$E$40)+(E36-AVERAGE($E$29:$E$40))^2/DEVSQ($E$29:$E$40) -> 0.14937321 | K36: =I36/(1-J36) -> -133.10362 | L36: =$C$44+$D$44*F36 -> 240.8473 | M36: =C36-L36 -> -44.007298 | N36: =1/COUNT($F$29:$F$40)+(F36-AVERAGE($F$29:$F$40))^2/DEVSQ($F$29:$F$40) -> 0.095443224 | O36: =$C$45+$D$45*G36 -> 409.04959 | P36: =D36-O36 -> -87.889591 | Q36: =1/COUNT($G$29:$G$40)+(G36-AVERAGE($G$29:$G$40))^2/DEVSQ($G$29:$G$40) -> 0.12908486 | R36: =L36+O36 -> 649.89689 | S36: =B36-R36 -> -131.89689 | T36: =M36/(1-N36)+P36/(1-Q36) -> -149.56704
A37: =四半期集計!A15 -> 26/3期 2Q | B37: =KOKUSAI_四半期!D14 -> 654 | C37: =KOKUSAI_四半期!H14 -> 287.76 | D37: =KOKUSAI_四半期!I14 -> 366.24 | E37: =四半期集計!I15 -> 10881.69 | F37: =四半期集計!J15 -> 4988.79 | G37: =四半期集計!K15 -> 5892.9 | H37: =$C$43+$D$43*E37 -> 581.21123 | I37: =B37-H37 -> 72.788768 | J37: =1/COUNT($E$29:$E$40)+(E37-AVERAGE($E$29:$E$40))^2/DEVSQ($E$29:$E$40) -> 0.083333729 | K37: =I37/(1-J37) -> 79.405963 | L37: =$C$44+$D$44*F37 -> 237.54387 | M37: =C37-L37 -> 50.21613 | N37: =1/COUNT($F$29:$F$40)+(F37-AVERAGE($F$29:$F$40))^2/DEVSQ($F$29:$F$40) -> 0.089027316 | O37: =$C$45+$D$45*G37 -> 339.90885 | P37: =D37-O37 -> 26.331154 | Q37: =1/COUNT($G$29:$G$40)+(G37-AVERAGE($G$29:$G$40))^2/DEVSQ($G$29:$G$40) -> 0.085002308 | R37: =L37+O37 -> 577.45272 | S37: =B37-R37 -> 76.547285 | T37: =M37/(1-N37)+P37/(1-Q37) -> 83.90093
A38: =四半期集計!A16 -> 26/3期 3Q | B38: =KOKUSAI_四半期!D15 -> 559 | C38: =KOKUSAI_四半期!H15 -> 173.29 | D38: =KOKUSAI_四半期!I15 -> 385.71 | E38: =四半期集計!I16 -> 11271.72 | F38: =四半期集計!J16 -> 4860.85 | G38: =四半期集計!K16 -> 6410.87 | H38: =$C$43+$D$43*E38 -> 598.06017 | I38: =B38-H38 -> -39.060167 | J38: =1/COUNT($E$29:$E$40)+(E38-AVERAGE($E$29:$E$40))^2/DEVSQ($E$29:$E$40) -> 0.090757343 | K38: =I38/(1-J38) -> -42.959013 | L38: =$C$44+$D$44*F38 -> 232.12957 | M38: =C38-L38 -> -58.839565 | N38: =1/COUNT($F$29:$F$40)+(F38-AVERAGE($F$29:$F$40))^2/DEVSQ($F$29:$F$40) -> 0.083685699 | O38: =$C$45+$D$45*G38 -> 373.08085 | P38: =D38-O38 -> 12.629146 | Q38: =1/COUNT($G$29:$G$40)+(G38-AVERAGE($G$29:$G$40))^2/DEVSQ($G$29:$G$40) -> 0.089954282 | R38: =L38+O38 -> 605.21042 | S38: =B38-R38 -> -46.21042 | T38: =M38/(1-N38)+P38/(1-Q38) -> -50.335815
A39: =四半期集計!A17 -> 26/3期 4Q | B39: =KOKUSAI_四半期!D16 -> 620 | C39: =KOKUSAI_四半期!H16 -> 161.2 | D39: =KOKUSAI_四半期!I16 -> 458.8 | E39: =四半期集計!I17 -> 10884.39 | F39: =四半期集計!J17 -> 3739.92 | G39: =四半期集計!K17 -> 7144.47 | H39: =$C$43+$D$43*E39 -> 581.32787 | I39: =B39-H39 -> 38.672131 | J39: =1/COUNT($E$29:$E$40)+(E39-AVERAGE($E$29:$E$40))^2/DEVSQ($E$29:$E$40) -> 0.083333334 | K39: =I39/(1-J39) -> 42.187779 | L39: =$C$44+$D$44*F39 -> 184.69283 | M39: =C39-L39 -> -23.49283 | N39: =1/COUNT($F$29:$F$40)+(F39-AVERAGE($F$29:$F$40))^2/DEVSQ($F$29:$F$40) -> 0.31170748 | O39: =$C$45+$D$45*G39 -> 420.06231 | P39: =D39-O39 -> 38.737689 | Q39: =1/COUNT($G$29:$G$40)+(G39-AVERAGE($G$29:$G$40))^2/DEVSQ($G$29:$G$40) -> 0.14808955 | R39: =L39+O39 -> 604.75514 | S39: =B39-R39 -> 15.244859 | T39: =M39/(1-N39)+P39/(1-Q39) -> 11.339508
A40: =四半期集計!A18 -> 27/3期 1Q | B40: =KOKUSAI_四半期!D17 -> 754 | C40: =KOKUSAI_四半期!H17 -> 188.5 | D40: =KOKUSAI_四半期!I17 -> 565.5 | E40: =四半期集計!I18 -> 12849.88 | F40: =四半期集計!J18 -> 4284.66 | G40: =四半期集計!K18 -> 8565.22 | H40: =$C$43+$D$43*E40 -> 666.23522 | I40: =B40-H40 -> 87.764782 | J40: =1/COUNT($E$29:$E$40)+(E40-AVERAGE($E$29:$E$40))^2/DEVSQ($E$29:$E$40) -> 0.27460283 | K40: =I40/(1-J40) -> 120.98859 | L40: =$C$44+$D$44*F40 -> 207.74573 | M40: =C40-L40 -> -19.24573 | N40: =1/COUNT($F$29:$F$40)+(F40-AVERAGE($F$29:$F$40))^2/DEVSQ($F$29:$F$40) -> 0.13927702 | O40: =$C$45+$D$45*G40 -> 511.05046 | P40: =D40-O40 -> 54.449542 | Q40: =1/COUNT($G$29:$G$40)+(G40-AVERAGE($G$29:$G$40))^2/DEVSQ($G$29:$G$40) -> 0.43110106 | R40: =L40+O40 -> 718.79619 | S40: =B40-R40 -> 35.203812 | T40: =M40/(1-N40)+P40/(1-Q40) -> 73.350435
B42: モデル | C42: 切片 a | D42: 傾き b | E42: R² | F42: LOOCV RMSE（億円）
B43: 単一：全社×世界 | C43: =INTERCEPT($B$29:$B$40,$E$29:$E$40) -> 111.1323 | D43: =SLOPE($B$29:$B$40,$E$29:$E$40) -> 0.043199074 | E43: =RSQ($B$29:$B$40,$E$29:$E$40) -> 0.44325558 | F43: =SQRT(SUMSQ($K$29:$K$40)/COUNT($K$29:$K$40)) -> 74.538144
B44: 構造：中国地場×中国 | C44: =INTERCEPT($C$29:$C$40,$F$29:$F$40) -> 26.422826 | D44: =SLOPE($C$29:$C$40,$F$29:$F$40) -> 0.042319088 | E44: =RSQ($C$29:$C$40,$F$29:$F$40) -> 0.36132394
B45: 構造：グローバル×中国以外 | C45: =INTERCEPT($D$29:$D$40,$G$29:$G$40) -> -37.48623 | D45: =SLOPE($D$29:$D$40,$G$29:$G$40) -> 0.064042335 | E45: =RSQ($D$29:$D$40,$G$29:$G$40) -> 0.76893835
B46: 構造：全社（和） | E46: =1-SUMSQ($S$29:$S$40)/DEVSQ($B$29:$B$40) -> 0.42983211 | F46: =SQRT(SUMSQ($T$29:$T$40)/COUNT($T$29:$T$40)) -> 77.617814
B47: 比較：ランダムウォーク | F47: =SQRT(SUMXMY2($B$30:$B$40,$B$29:$B$39)/(COUNT($B$29:$B$40)-1)) -> 112.62811

Sheet ナウキャスト
A1: 27/3期2Q（2026年7-9月）売上収益のナウキャスト（億円）
A2: k=0は9月の輸出を季節比で推計（9月速報は10/21公表予定）。k=1は6-8月の実績だけで完結する。帯＝予測±LOOCV RMSE。
A4: ① 9月÷7-8月平均（過去の季節比）
A5: 年 | B5: 中国 | C5: 中国以外 | D5: 世界
A6: 2023 | B6: =SUMIFS(貿易_月次!$D$5:$D$45,貿易_月次!$A$5:$A$45,DATE(2023,9,1))/AVERAGE(SUMIFS(貿易_月次!$D$5:$D$45,貿易_月次!$A$5:$A$45,DATE(2023,7,1)),SUMIFS(貿易_月次!$D$5:$D$45,貿易_月次!$A$5:$A$45,DATE(2023,8,1))) -> 1.3234583 | C6: =SUMIFS(貿易_月次!$I$5:$I$45,貿易_月次!$A$5:$A$45,DATE(2023,9,1))/AVERAGE(SUMIFS(貿易_月次!$I$5:$I$45,貿易_月次!$A$5:$A$45,DATE(2023,7,1)),SUMIFS(貿易_月次!$I$5:$I$45,貿易_月次!$A$5:$A$45,DATE(2023,8,1))) -> 1.147219 | D6: =SUMIFS(貿易_月次!$B$5:$B$45,貿易_月次!$A$5:$A$45,DATE(2023,9,1))/AVERAGE(SUMIFS(貿易_月次!$B$5:$B$45,貿易_月次!$A$5:$A$45,DATE(2023,7,1)),SUMIFS(貿易_月次!$B$5:$B$45,貿易_月次!$A$5:$A$45,DATE(2023,8,1))) -> 1.2343716
A7: 2024 | B7: =SUMIFS(貿易_月次!$D$5:$D$45,貿易_月次!$A$5:$A$45,DATE(2024,9,1))/AVERAGE(SUMIFS(貿易_月次!$D$5:$D$45,貿易_月次!$A$5:$A$45,DATE(2024,7,1)),SUMIFS(貿易_月次!$D$5:$D$45,貿易_月次!$A$5:$A$45,DATE(2024,8,1))) -> 1.132516 | C7: =SUMIFS(貿易_月次!$I$5:$I$45,貿易_月次!$A$5:$A$45,DATE(2024,9,1))/AVERAGE(SUMIFS(貿易_月次!$I$5:$I$45,貿易_月次!$A$5:$A$45,DATE(2024,7,1)),SUMIFS(貿易_月次!$I$5:$I$45,貿易_月次!$A$5:$A$45,DATE(2024,8,1))) -> 1.100709 | D7: =SUMIFS(貿易_月次!$B$5:$B$45,貿易_月次!$A$5:$A$45,DATE(2024,9,1))/AVERAGE(SUMIFS(貿易_月次!$B$5:$B$45,貿易_月次!$A$5:$A$45,DATE(2024,7,1)),SUMIFS(貿易_月次!$B$5:$B$45,貿易_月次!$A$5:$A$45,DATE(2024,8,1))) -> 1.1160783
A8: 2025 | B8: =SUMIFS(貿易_月次!$D$5:$D$45,貿易_月次!$A$5:$A$45,DATE(2025,9,1))/AVERAGE(SUMIFS(貿易_月次!$D$5:$D$45,貿易_月次!$A$5:$A$45,DATE(2025,7,1)),SUMIFS(貿易_月次!$D$5:$D$45,貿易_月次!$A$5:$A$45,DATE(2025,8,1))) -> 1.2164806 | C8: =SUMIFS(貿易_月次!$I$5:$I$45,貿易_月次!$A$5:$A$45,DATE(2025,9,1))/AVERAGE(SUMIFS(貿易_月次!$I$5:$I$45,貿易_月次!$A$5:$A$45,DATE(2025,7,1)),SUMIFS(貿易_月次!$I$5:$I$45,貿易_月次!$A$5:$A$45,DATE(2025,8,1))) -> 0.99552715 | D8: =SUMIFS(貿易_月次!$B$5:$B$45,貿易_月次!$A$5:$A$45,DATE(2025,9,1))/AVERAGE(SUMIFS(貿易_月次!$B$5:$B$45,貿易_月次!$A$5:$A$45,DATE(2025,7,1)),SUMIFS(貿易_月次!$B$5:$B$45,貿易_月次!$A$5:$A$45,DATE(2025,8,1))) -> 1.0977071
A9: 平均 | B9: =AVERAGE(B6:B8) -> 1.2241517 | C9: =AVERAGE(C6:C8) -> 1.0811517 | D9: =AVERAGE(D6:D8) -> 1.1493857
A10: 最大 | B10: =MAX(B6:B8) -> 1.3234583 | C10: =MAX(C6:C8) -> 1.147219 | D10: =MAX(D6:D8) -> 1.2343716
A12: ② 9月の季節比の前提（シナリオ） | G12: 2026年7-8月の輸出実績
A13: シナリオ | B13: 中国 | C13: 中国以外 | D13: 世界 | E13: 説明 | H13: 中国 | I13: 中国以外 | J13: 世界
A14: 低 | B14: 1 | C14: 1 | D14: 1 | E14: 9月＝7-8月平均（季節性なし） | G14: 7月 | H14: =SUMIFS(貿易_月次!$D$5:$D$45,貿易_月次!$A$5:$A$45,DATE(2026,7,1)) -> 2073.46 | I14: =SUMIFS(貿易_月次!$I$5:$I$45,貿易_月次!$A$5:$A$45,DATE(2026,7,1)) -> 2870.91 | J14: =SUMIFS(貿易_月次!$B$5:$B$45,貿易_月次!$A$5:$A$45,DATE(2026,7,1)) -> 4944.37
A15: 基準 | B15: =B9 -> 1.2241517 | C15: =C9 -> 1.0811517 | D15: =D9 -> 1.1493857 | E15: 過去3年平均の季節比 | G15: 8月 | H15: =SUMIFS(貿易_月次!$D$5:$D$45,貿易_月次!$A$5:$A$45,DATE(2026,8,1)) -> 1947.91 | I15: =SUMIFS(貿易_月次!$I$5:$I$45,貿易_月次!$A$5:$A$45,DATE(2026,8,1)) -> 2949.73 | J15: =SUMIFS(貿易_月次!$B$5:$B$45,貿易_月次!$A$5:$A$45,DATE(2026,8,1)) -> 4897.64
A16: 高 | B16: =B10 -> 1.3234583 | C16: =C10 -> 1.147219 | D16: =D10 -> 1.2343716 | E16: 過去3年の最大の季節比 | G16: 合計 | H16: =SUM(H14:H15) -> 4021.37 | I16: =SUM(I14:I15) -> 5820.64 | J16: =SUM(J14:J15) -> 9842.01
G17: 平均 | H17: =AVERAGE(H14:H15) -> 2010.685 | I17: =AVERAGE(I14:I15) -> 2910.32 | J17: =AVERAGE(J14:J15) -> 4921.005
A19: ③ k=0（7-8月実績＋9月推計）
A20: シナリオ | B20: 中国 7-9月 | C20: 中国以外 7-9月 | D20: 世界 7-9月 | E20: 構造:中国地場 | F20: 構造:グローバル | G20: 構造:全社 | H20: 帯 下限 | I20: 帯 上限 | J20: 単一:全社
A21: 低 | B21: =$H$16+$H$17*B14 -> 6032.055 | C21: =$I$16+$I$17*C14 -> 8730.96 | D21: =$J$16+$J$17*D14 -> 14763.015 | E21: =回帰!$C$21+回帰!$D$21*B21 -> 294.25758 | F21: =回帰!$C$22+回帰!$D$22*C21 -> 512.14331 | G21: =E21+F21 -> 806.40089 | H21: =G21-回帰!$F$23 -> 730.06978 | I21: =G21+回帰!$F$23 -> 882.732 | J21: =回帰!$C$20+回帰!$D$20*D21 -> 774.17578
A22: 基準 | B22: =$H$16+$H$17*B15 -> 6482.7534 | C22: =$I$16+$I$17*C15 -> 8967.1375 | D22: =$J$16+$J$17*D15 -> 15498.143 | E22: =回帰!$C$21+回帰!$D$21*B22 -> 318.43959 | F22: =回帰!$C$22+回帰!$D$22*C22 -> 527.10538 | G22: =E22+F22 -> 845.54497 | H22: =G22-回帰!$F$23 -> 769.21386 | I22: =G22+回帰!$F$23 -> 921.87608 | J22: =回帰!$C$20+回帰!$D$20*D22 -> 812.13073
A23: 高 | B23: =$H$16+$H$17*B16 -> 6682.4278 | C23: =$I$16+$I$17*C16 -> 9159.4145 | D23: =$J$16+$J$17*D16 -> 15916.359 | E23: =回帰!$C$21+回帰!$D$21*B23 -> 329.15303 | F23: =回帰!$C$22+回帰!$D$22*C23 -> 539.28631 | G23: =E23+F23 -> 868.43934 | H23: =G23-回帰!$F$23 -> 792.10823 | I23: =G23+回帰!$F$23 -> 944.77045 | J23: =回帰!$C$20+回帰!$D$20*D23 -> 833.7234
A25: ④ k=1（6-8月の実績のみ）
B26: 中国 6-8月 | C26: 中国以外 6-8月 | D26: 世界 6-8月 | E26: 構造:中国地場 | F26: 構造:グローバル | G26: 構造:全社 | H26: 帯 下限 | I26: 帯 上限 | J26: 単一:全社
A27: 実績 | B27: =四半期集計!J19 -> 5592 | C27: =四半期集計!K19 -> 8851.43 | D27: =四半期集計!I19 -> 14443.43 | E27: =回帰!$C$44+回帰!$D$44*B27 -> 263.07117 | F27: =回帰!$C$45+回帰!$D$45*C27 -> 529.38002 | G27: =E27+F27 -> 792.45118 | H27: =G27-回帰!$F$46 -> 714.83337 | I27: =G27+回帰!$F$46 -> 870.069 | J27: =回帰!$C$43+回帰!$D$43*D27 -> 735.0751
A29: ⑤ 会社計画との比較
A30: 上期（4-9月）売上収益計画（修正後） | D30: 1610
A31: 1Q実績 | D31: =KOKUSAI_四半期!D17 -> 754
A32: 計画が示す2Q売上 | D32: =D30-D31 -> 856
A33: 構造モデル k=0 基準との差（計画−予測） | D33: =D32-G22 -> 10.45503
A34: 計画が示す実質シェア（2Q計画÷6-8月の世界輸出） | D34: =D32/D27 -> 0.059265701
A35: 過去の実質シェア（k=1）最小／平均／最大 | D35: =MIN(四半期集計!M7:M18) -> 0.043025543 | E35: =AVERAGE(四半期集計!M7:M18) -> 0.053596938 | F35: =MAX(四半期集計!M7:M18) -> 0.06111523
A37: ⑥ 計画達成に必要な9月の輸出（構造 k=0、基準シナリオの地域構成を維持）
A38: 基準シナリオの9月推計：中国 | D38: =H17*B15 -> 2461.3834
A39: 基準シナリオの9月推計：中国以外 | D39: =I17*C15 -> 3146.4975
A40: 9月を1倍にしたときの売上増分 | D40: =回帰!$D$21*D38+回帰!$D$22*D39 -> 331.39798
A41: 必要な倍率 | D41: =1+(D32-G22)/D40 -> 1.0315483
A42: 必要な9月の世界輸出（億円） | D42: =(D38+D39)*D41 -> 5784.7998
A43: 2025年9月の世界輸出（億円） | D43: =SUMIFS(貿易_月次!$B$5:$B$45,貿易_月次!$A$5:$A$45,DATE(2025,9,1)) -> 3844.11
A44: 必要な前年同月比 | D44: =D42/D43-1 -> 0.50484762
A45: 参考：7月・8月の世界輸出の前年同月比 | D45: =J14/SUMIFS(貿易_月次!$B$5:$B$45,貿易_月次!$A$5:$A$45,DATE(2025,7,1))-1 -> 0.40888121 | E45: =J15/SUMIFS(貿易_月次!$B$5:$B$45,貿易_月次!$A$5:$A$45,DATE(2025,8,1))-1 -> 0.40154416

Sheet 出所・注記
A1: 出所・注記
A3: 【出所】
A4: 財務省 貿易統計 月次速報PDF（各月）: https://www.customs.go.jp/toukei/shinbun/trade-st/ （URLは速報_原データのG列）
A5: 財務省 貿易統計 2024年5月分 概要: https://www.customs.go.jp/toukei/shinbun/trade-st/gaiyo2024_05.pdf
A6: KOKUSAI ELECTRIC 25/3期 決算説明資料: https://finance-frontend-pc-dist.west.edge.storage-yahoo.jp/disclosure/20250513/20250513544797.pdf
A7: KOKUSAI ELECTRIC 26/3期 決算説明資料: https://finance.stockweather.co.jp/contents/dispPDF.aspx?disclosure=20260513527733
A8: 27/3期1Q実績（売上754億円、中国地場25％）: https://global-net.co.jp/archives/13621
A9: 27/3期上期計画1,610億円: https://finance.yahoo.co.jp/quote/6525.T/financials
A10: 伏木税関支署 2023年貿易概況: https://www.customs.go.jp/osaka/toukei/shosho/fushiki_2023nen.pdf
A12: 【注記】
A13: 1. 概況品「半導体等製造装置」はHS8486全体（FPD製造装置・部分品を含む）である。KOKUSAI固有の品目ではなく、同社は輸出全体の約4〜6％にあたる。
A14: 2. 速報値を使用している。翌年の前年比から逆算した値と当月速報値の差は、確認できた112組で最大0.7％（平均0.01％）である。
... A19: 7. 国内向け販売（JASM、Rapidus等）と海外生産分は輸出統計に現れない。
