Workbook

Sheet 1_前提
B1: SpaceX (SPCX) バリュエーション・モデル
B2: 青字・黄色セル = 入力値（書き換え可） ／ 黒字 = 計算式
B3: 単位: 十億ドル（株価・株数を除く） 出典: SpaceX 2026年Q2決算 (2026/8/4)
B5: ■ 株価・株式数
B6: 株価 ($) | C6: 134 | E6: 2026年8月時点。需給要因を含む
B7: Class A 株式数 (百万株) | C7: 7607 | E7: 貸借対照表 2026/6/30
B8: Class B 株式数 (百万株) | C8: 5569 | E8: 貸借対照表 2026/6/30
B9: Cursor買収の新規発行 (百万株) | C9: 389 | E9: 2026/8/14 完了 約600億ドル分
B10: 発行済株式数 合計 (百万株) | C10: =C7+C8+C9 -> 13565
B12: ■ 貸借対照表 (2026/6/30)
B13: 現金及び現金同等物 | C13: 93.522 | E13: 貸借対照表
B14: 有価証券 | C14: 6.487 | E14: 貸借対照表
B15: 有利子負債 (短期) | C15: 2.525 | E15: うち関連当事者 2.039
B16: 有利子負債 (長期) | C16: 36.839 | E16: うち関連当事者 11.290
B17: ネットキャッシュ | C17: =C13+C14-C15-C16 -> 60.645
B19: ■ Q2 2026 実績（部門別）
B20: 項目 | C20: 金額 | D20: 年換算
B21: Space 売上 | C21: 0.962 | D21: =C21*4 -> 3.848 | E21: 出典: 2026年Q2決算 3ページ セグメント表
B22: Connectivity 売上 | C22: 4.291 | D22: =C22*4 -> 17.164
B23: AI 売上 | C23: 2.561 | D23: =C23*4 -> 10.244
B24: Space 調整後EBITDA | C24: -0.205 | D24: =C24*4 -> -0.82
B25: Connectivity 調整後EBITDA | C25: 2.597 | D25: =C25*4 -> 10.388
B26: AI 調整後EBITDA | C26: 1.146 | D26: =C26*4 -> 4.584
B27: Space 設備投資 | C27: 1.174 | D27: =C27*4 -> 4.696
B28: Connectivity 設備投資 | C28: 1.367 | D28: =C28*4 -> 5.468
B29: AI 設備投資 | C29: 15.828 | D29: =C29*4 -> 63.312
B31: ■ その他
B32: Starlink 契約者数 (百万人) | C32: 12 | E32: Q2末
B33: Starlink ARPU ($/月) | C33: 66 | E33: 2四半期連続で横ばい
B34: AI 計算能力 (GW) | C34: 1.4 | E34: Q1の1.0GWから拡大
B35: 受注残 (バックログ) | C35: 47.5 | E35: 全社
B36: クラウド契約 受注額 | C36: 14.1 | E36: うちQ2に1.6十億ドルを認識

Sheet 2_企業価値
B1: 企業価値 (EV) の算出
B3: 株価 ($) | C3: =1_前提!C6 -> 134
B4: 発行済株式数 (百万株) | C4: =1_前提!$C$10 -> 13565
B5: 時価総額 | C5: =C3*C4/1000 -> 1817.71
B6: ＋ 有利子負債 | C6: =1_前提!C15+1_前提!C16 -> 39.364
B7: − 現金・有価証券 | C7: =-(1_前提!C13+1_前提!C14) -> -100.009
B8: 企業価値 (EV) | C8: =C5+C6+C7 -> 1757.065 | E8: 会社を借金ごと買い、手元現金を回収した場合の実質支払額
B10: ■ 参考指標
B11: 売上 (Q2年換算) | C11: =(1_前提!C21+1_前提!C22+1_前提!C23)*4 -> 31.256
B12: EV / 売上 | C12: =C8/C11 -> 56.215287
B13: 調整後EBITDA (Q2年換算) | C13: =(1_前提!C24+1_前提!C25+1_前提!C26)*4 -> 14.152
B14: EV / EBITDA | C14: =C8/C13 -> 124.15666
B15: フリーキャッシュフロー (Q2年換算) | C15: =(1_前提!C24+1_前提!C25+1_前提!C26-1_前提!C27-1_前提!C28-1_前提!C29)*4 -> -59.324 | E15: EBITDA − 設備投資。大幅なマイナスがこの会社の最大の論点

Sheet 3_SOTP逆算
B1: SOTP逆算 — AI部門にいくら付いているか
B2: 説明できる部門を引き算し、残余をAI部門への評価とみなす。3ケースで幅を確認する
B4: 項目 | C4: 弱気 | D4: 基本 | E4: 強気
B5: ■ Starlink (Connectivity)
B6: NTM売上 | C6: 20 | D6: 22 | E6: 25 | G6: 今後12ヶ月。Q2年換算17.2から個人+44%/法人+108%を減速させて置く
B7: EBITDA利益率 | C7: 0.575 | D7: 0.605 | E7: 0.625 | G7: Q2実績 60.5%
B8: NTM EBITDA | C8: =C6*C7 -> 11.5 | D8: =D6*D7 -> 13.31 | E8: =E6*E7 -> 15.625
B9: EV/EBITDA 倍率 | C9: 12 | D9: 18 | E9: 28 | G9: 通信インフラの標準は6-8倍。成長50%・利益率60%を反映して上乗せ
B10: Starlink 評価額 | C10: =C8*C9 -> 138 | D10: =D8*D9 -> 239.58 | E10: =E8*E9 -> 437.5
B12: ■ 打上げ (Space)
B13: 評価額 | C13: -20 | D13: 30 | E13: 100 | G13: 赤字のため倍率が使えず直接入力。強気=Starship再使用成立
B15: ■ 逆算
B16: 企業価値 (EV) | C16: =2_企業価値!$C$8 -> 1757.065 | D16: =2_企業価値!$C$8 -> 1757.065 | E16: =2_企業価値!$C$8 -> 1757.065
B17: − Starlink | C17: =-C10 -> -138 | D17: =-D10 -> -239.58 | E17: =-E10 -> -437.5
B18: − 打上げ | C18: =-C13 -> 20 | D18: =-D13 -> -30 | E18: =-E13 -> -100
B19: ＝ AI部門への残余 | C19: =C16+C17+C18 -> 1639.065 | D19: =D16+D17+D18 -> 1487.485 | E19: =E16+E17+E18 -> 1219.565 | G19: ★ この幅が狭ければ「残りかす」ではなく実体のある数字と言える
B20: AI部門 EV/売上 | C20: =C19/1_前提!$D$23 -> 160.00244 | D20: =D19/1_前提!$D$23 -> 145.20549 | E20: =E19/1_前提!$D$23 -> 119.05164
B22: 残余の幅 (強気ケース − 弱気ケース) | C22: =C19-E19 -> 419.5
B23: 幅 ÷ 残余中心値 | C23: =(C19-E19)/D19 -> 0.28201965 | G23: 30%以下なら残余は頑健と判断してよい

Sheet 4_逆DCF
B1: 逆DCF — 株価が要求する成長率
B2: AI部門の残余を正当化するために必要な将来売上を逆算する
B4: AI部門への残余 (基本ケース) | C4: =3_SOTP逆算!D19 -> 1487.485
B5: AI部門 現在売上 (年換算) | C5: =1_前提!$D$23 -> 10.244
B6: 予測年数 | C6: 5 | H6: 2031年まで
B8: ■ 必要な2031年売上 (十億ドル)
B9: 割引率 ＼ 出口EV/売上 | C9: 5 | D9: 8 | E9: 12
B10: 0.1 | C10: =4_逆DCF!$C$4*(1+$B10)^4_逆DCF!$C$6/C$9 -> 479.12189 | D10: =4_逆DCF!$C$4*(1+$B10)^4_逆DCF!$C$6/D$9 -> 299.45118 | E10: =4_逆DCF!$C$4*(1+$B10)^4_逆DCF!$C$6/E$9 -> 199.63412 | H10: 残余を将来価値に割り戻し、出口倍率で割って必要売上を出す
B11: 0.12 | C11: =4_逆DCF!$C$4*(1+$B11)^4_逆DCF!$C$6/C$9 -> 524.29136 | D11: =4_逆DCF!$C$4*(1+$B11)^4_逆DCF!$C$6/D$9 -> 327.6821 | E11: =4_逆DCF!$C$4*(1+$B11)^4_逆DCF!$C$6/E$9 -> 218.45473
B12: 0.15 | C12: =4_逆DCF!$C$4*(1+$B12)^4_逆DCF!$C$6/C$9 -> 598.37273 | D12: =4_逆DCF!$C$4*(1+$B12)^4_逆DCF!$C$6/D$9 -> 373.98296 | E12: =4_逆DCF!$C$4*(1+$B12)^4_逆DCF!$C$6/E$9 -> 249.32197
B14: ■ 必要な年率成長率 (CAGR)
B15: 割引率 ＼ 出口EV/売上 | C15: 5 | D15: 8 | E15: 12
B16: 0.1 | C16: =(C10/4_逆DCF!$C$5)^(1/4_逆DCF!$C$6)-1 -> 1.157721 | D16: =(D10/4_逆DCF!$C$5)^(1/4_逆DCF!$C$6)-1 -> 0.96413481 | E16: =(E10/4_逆DCF!$C$5)^(1/4_逆DCF!$C$6)-1 -> 0.81114425 | H16: ★ 9通りすべてで高水準なら、前提の問題ではなく株価の問題
B17: 0.12 | C17: =(C11/4_逆DCF!$C$5)^(1/4_逆DCF!$C$6)-1 -> 1.1969523 | D17: =(D11/4_逆DCF!$C$5)^(1/4_逆DCF!$C$6)-1 -> 0.99984635 | E17: =(E11/4_逆DCF!$C$5)^(1/4_逆DCF!$C$6)-1 -> 0.84407414
B18: 0.15 | C18: =(C12/4_逆DCF!$C$5)^(1/4_逆DCF!$C$6)-1 -> 1.2557992 | D18: =(D12/4_逆DCF!$C$5)^(1/4_逆DCF!$C$6)-1 -> 1.0534137 | E18: =(E12/4_逆DCF!$C$5)^(1/4_逆DCF!$C$6)-1 -> 0.89346899

Sheet 5_目標株価
B1: 1年後の目標株価 — 感応度表
B2: AI部門の「売上」と「倍率」の組み合わせで1株価値を出す
B4: Starlink 評価額 (基本) | C4: =3_SOTP逆算!D10 -> 239.58
B5: 打上げ 評価額 (基本) | C5: =3_SOTP逆算!D13 -> 30
B6: 1年後のネットキャッシュ | C6: 0 | H6: 現在606億ドル。今のFCFペースで1年後にほぼゼロと想定
B7: 1年後の株式数 (百万株) | C7: 13700 | H7: 株式報酬による希薄化を織り込む
B9: ■ 1株価値 ($)
B10: AI売上(NTM) ＼ 倍率 | C10: 60 | D10: 80 | E10: 100 | F10: 142
B11: 7.2 | C11: =($B11*C$10+5_目標株価!$C$4+5_目標株価!$C$5+5_目標株価!$C$6)*1000/5_目標株価!$C$7 -> 51.210219 | D11: =($B11*D$10+5_目標株価!$C$4+5_目標株価!$C$5+5_目標株価!$C$6)*1000/5_目標株価!$C$7 -> 61.721168 | E11: =($B11*E$10+5_目標株価!$C$4+5_目標株価!$C$5+5_目標株価!$C$6)*1000/5_目標株価!$C$7 -> 72.232117 | F11: =($B11*F$10+5_目標株価!$C$4+5_目標株価!$C$5+5_目標株価!$C$6)*1000/5_目標株価!$C$7 -> 94.305109 | H11: 弱気=一回性で頭打ち／基本=減速しつつ成長／強気=契約積み増し
B12: 14.4 | C12: =($B12*C$10+5_目標株価!$C$4+5_目標株価!$C$5+5_目標株価!$C$6)*1000/5_目標株価!$C$7 -> 82.743066 | D12: =($B12*D$10+5_目標株価!$C$4+5_目標株価!$C$5+5_目標株価!$C$6)*1000/5_目標株価!$C$7 -> 103.76496 | E12: =($B12*E$10+5_目標株価!$C$4+5_目標株価!$C$5+5_目標株価!$C$6)*1000/5_目標株価!$C$7 -> 124.78686 | F12: =($B12*F$10+5_目標株価!$C$4+5_目標株価!$C$5+5_目標株価!$C$6)*1000/5_目標株価!$C$7 -> 168.93285
B13: 20.6 | C13: =($B13*C$10+5_目標株価!$C$4+5_目標株価!$C$5+5_目標株価!$C$6)*1000/5_目標株価!$C$7 -> 109.89635 | D13: =($B13*D$10+5_目標株価!$C$4+5_目標株価!$C$5+5_目標株価!$C$6)*1000/5_目標株価!$C$7 -> 139.96934 | E13: =($B13*E$10+5_目標株価!$C$4+5_目標株価!$C$5+5_目標株価!$C$6)*1000/5_目標株価!$C$7 -> 170.04234 | F13: =($B13*F$10+5_目標株価!$C$4+5_目標株価!$C$5+5_目標株価!$C$6)*1000/5_目標株価!$C$7 -> 233.19562
B15: 現在値 ($) | C15: =1_前提!C6 -> 134
B16: 現在値を維持するのに必要な倍率 | C16: =(C15*5_目標株価!$C$7/1000-5_目標株価!$C$4-5_目標株価!$C$5-5_目標株価!$C$6)/B12 -> 108.76528 | H16: ★ 基本ケースの売上でこの倍率を維持できるかが論点

Sheet 6_感応度
B1: 感応度分析 — どの変数が株価を動かすか
B2: 各変数を単独で動かしたときの1株価値への影響。これがドライバー特定の根拠になる
B4: 基準ケースの1株価値 | C4: =5_目標株価!D12 -> 103.76496 | H4: AI売上14.4 × 倍率80倍
B6: 変数 | C6: 変更後の値 | D6: 1株価値 | E6: 影響額 | F6: 感応度
B7: AI倍率 80x → 60x | C7: 60x | D7: =(14.4*60+5_目標株価!$C$4+5_目標株価!$C$5+5_目標株価!$C$6)*1000/5_目標株価!$C$7 -> 82.743066 | E7: =D7-6_感応度!$C$4 -> -21.021898 | F7: =IF(ABS(E7)>20,"★★★",IF(ABS(E7)>10,"★★","★")) -> ★★★
B8: AI売上 14.4 → 10.0 | C8: $10.0 | D8: =(10*80+5_目標株価!$C$4+5_目標株価!$C$5+5_目標株価!$C$6)*1000/5_目標株価!$C$7 -> 78.071533 | E8: =D8-6_感応度!$C$4 -> -25.693431 | F8: =IF(ABS(E8)>20,"★★★",IF(ABS(E8)>10,"★★","★")) -> ★★★
B9: Starlink倍率 18x → 12x | C9: 12x | D9: =(14.4*80+3_SOTP逆算!C10+5_目標株価!$C$5+5_目標株価!$C$6)*1000/5_目標株価!$C$7 -> 96.350365 | E9: =D9-6_感応度!$C$4 -> -7.4145985 | F9: =IF(ABS(E9)>20,"★★★",IF(ABS(E9)>10,"★★","★")) -> ★
B10: Starlink売上 22 → 19 | C10: $19.0 | D10: =(14.4*80+19*0.605*18+5_目標株価!$C$5+5_目標株価!$C$6)*1000/5_目標株価!$C$7 -> 101.38029 | E10: =D10-6_感応度!$C$4 -> -2.3846715 | F10: =IF(ABS(E10)>20,"★★★",IF(ABS(E10)>10,"★★","★")) -> ★
B11: 打上げ 30 → 0 | C11: $0 | D11: =(14.4*80+5_目標株価!$C$4+0+5_目標株価!$C$6)*1000/5_目標株価!$C$7 -> 101.57518 | E11: =D11-6_感応度!$C$4 -> -2.189781 | F11: =IF(ABS(E11)>20,"★★★",IF(ABS(E11)>10,"★★","★")) -> ★
B12: ネットキャッシュ 0 → -20 | C12: -$20 | D12: =(14.4*80+5_目標株価!$C$4+5_目標株価!$C$5-20)*1000/5_目標株価!$C$7 -> 102.30511 | E12: =D12-6_感応度!$C$4 -> -1.459854 | F12: =IF(ABS(E12)>20,"★★★",IF(ABS(E12)>10,"★★","★")) -> ★
B14: AI部門2変数の影響合計 | C14: =ABS(E7)+ABS(E8) -> 46.715328
B15: その他4変数の影響合計 | C15: =ABS(E9)+ABS(E10)+ABS(E11)+ABS(E12) -> 13.448905
B16: AI部門が占める割合 | C16: =C14/(C14+C15) -> 0.77646345 | H16: ★ ここが高いほど「AIがキードライバー」と定量的に言える
B18: 【読み方】
B19: ・影響額の大きい変数がキードライバー。主観ではなく計算で決まる
B20: ・Starlinkは事業として重要でも、株価への感応度は小さい
B21: ・AI倍率は会社が制御できない変数（市場の空気で決まる）

Sheet 7_検証条件
B1: 検証条件 — 仮説の白黒をつける指標
B2: 分析の前に判定基準を決めておく。後から都合よく解釈するのを防ぐため
B4: 時期 | C4: 指標 | D4: 閾値 | E4: 判定
B5: 2026/11/3 | C5: AI部門 四半期売上 | D5: $2.56B 未満 | E5: 弱気シナリオ確定。一回性だった
B6: 2026/11/3 | C6: AI部門 四半期売上 | D6: $3.0-3.5B | E6: 基本シナリオ通り
B7: 2026/11/3 | C7: AI部門 四半期売上 | D7: $4.5B 超 | E7: モデルが低すぎる。全面見直し
B8: 2026/11/3 | C8: AI部門 設備投資 | D8: $15.8B 未満 | E8: ピーク到達。FCF改善の道筋
B9: 2026/11/3 | C9: 新規クラウド契約 | D9: 公表あり | E9: 倍率維持の根拠。強気へ
B10: 2026/11/3 | C10: 手元資金 | D10: $85B 未満 | E10: 燃焼加速
B11: 2026/9/9 | C11: ロックアップ解除 | D11: 最大3.19億株 | E11: 需給の重し
B12: 2026/12/8 | C12: ロックアップ解除 | D12: 最大規模 | E12: 最終関門
B13: 2027/6 | C13: S&P500採用 | D13: GAAP黒字が前提 | E13: 実現なら約$14Bの資金流入
B15: 【出典】
B16: 財務数値: SpaceX 2026年第2四半期決算 (2026年8月4日発表)
B17: 株価・時価総額: 2026年8月時点の市場データ
B18: その他の前提: ユーザーとの議論に基づく分析上の仮定
B19: ※ 本モデルは分析の枠組みであり、投資助言ではありません
